Workbook
Name Z_DAF976D5_FCCB_4417_8719_3CCA499BF400_.wvu.Cols: ABR!$K:$K,ABR!$T:$T,ABR!$W:$W,ABR!#REF!
Name Z_DAF976D5_FCCB_4417_8719_3CCA499BF400_.wvu.Cols: AGO!$K:$K,AGO!$T:$T,AGO!$W:$W,AGO!#REF!
Name Z_DAF976D5_FCCB_4417_8719_3CCA499BF400_.wvu.Cols: DIC!$K:$K,DIC!$T:$T,DIC!$W:$W,DIC!#REF!
Name Z_DAF976D5_FCCB_4417_8719_3CCA499BF400_.wvu.Cols: ENE!$K:$K,ENE!$T:$T,ENE!$W:$W,ENE!#REF!
Name Z_DAF976D5_FCCB_4417_8719_3CCA499BF400_.wvu.Cols: FEB!$K:$K,FEB!$T:$T,FEB!$W:$W,FEB!#REF!
Name Z_DAF976D5_FCCB_4417_8719_3CCA499BF400_.wvu.Cols: JUL!$K:$K,JUL!$T:$T,JUL!$W:$W,JUL!#REF!
Name Z_DAF976D5_FCCB_4417_8719_3CCA499BF400_.wvu.Cols: JUN!$K:$K,JUN!$T:$T,JUN!$W:$W,JUN!#REF!
Name Z_DAF976D5_FCCB_4417_8719_3CCA499BF400_.wvu.Cols: MAR!$K:$K,MAR!$T:$T,MAR!$W:$W,MAR!#REF!
Name Z_DAF976D5_FCCB_4417_8719_3CCA499BF400_.wvu.Cols: MAY!$K:$K,MAY!$T:$T,MAY!$W:$W,MAY!#REF!
Name Z_DAF976D5_FCCB_4417_8719_3CCA499BF400_.wvu.Cols: Modelo!$K:$K,Modelo!$P:$P,Modelo!$R:$R,Modelo!#REF!
Name Z_DAF976D5_FCCB_4417_8719_3CCA499BF400_.wvu.Cols: NOV!$K:$K,NOV!$T:$T,NOV!$W:$W,NOV!#REF!
Name Z_DAF976D5_FCCB_4417_8719_3CCA499BF400_.wvu.Cols: OCT!$K:$K,OCT!$T:$T,OCT!$W:$W,OCT!#REF!
Name Z_DAF976D5_FCCB_4417_8719_3CCA499BF400_.wvu.Cols: SEP!$K:$K,SEP!$T:$T,SEP!$W:$W,SEP!#REF!

Sheet ENE
B1: Producción | AH1: Extracción | AN1: Indicadores
C2: 50 | D2: 25 | E2: 10 | F2: 50 | G2: 25 | H2: 50 | I2: 25 | J2: 25 | K2: 50 | L2: 25 | Q2: 50 | R2: 1 | S2: 1 | T2: 1 | U2: 25 | X2: 25 | Y2: 25 | Z2: 25 | AA2: 25 | AB2: 40 | AC2: 50
B3: HARINA EN BULTO | R3: HARINA GRANEL | U3: P. EXP | V3: REPASO | X3: ESPECIAL | AA3: SUBPRODUCTO | AF3: EXTRACION | AN3: HORAS | AQ3: INDICACORES MOLINO | AV3: MOJADORA | AW3: EQUIPOS ELECTRONICOS
A4: Dia | B4: Fecha | C4: Extrapan 50 | D4: Extrapan 25 | E4: Extrapan 10 | F4: Artesanal 50 | G4: Artesanal 25 | H4: Natural 50 | I4: Fuerte 25 | J4: Fuerte exp 25 | K4: Exclusiva 50 | L4: Exclusiva 25 | M4: S. Sal 25 | N4: Harina Tortas y Ponques | O4: Harina Galeras Ligera | P4: H. Manitova | Q4: ESPECIAL 50 | R4: Harina de alta proteina x 1 G | S4: Harina de baja proteina x 1 | T4: ARTESANAL X 1 G | U4: H. espcial x 25 | V4: + Repaso | W4: - Reproceso | X4: Germen 25 | Y4: Semola 25 | Z4: Grano entero 25 | AA4: Salvado 25 | AB4: Mogolla 40 | AC4: Segunda 50 | AD4: Total trigo | AE4: Total Bultos | AF4: Harina | AG4: Grano entero partido | AH4: =X4 -> Germen 25 | AI4: Semola | AJ4: =AA4 -> Salvado 25 | AK4: =AB4 -> Mogolla 40 | AL4: =AC4 -> Segunda 50 | AM4: =B4 -> Fecha | AN4: Molienda | AO4: moje | AP4: Horas varada | AQ4: Molido/ Mojado | AR4: Capacidad TM. hora | AS4: Capacidad TM. Día | AT4: % Utilizado | AU4: Bultos Hora | AV4: capacidad TM. hora | AW4: MYFC | AX4: Bascula Trigo | AY4: Bascula Harina | AZ4: Agua M³ | BA4: Bascula Mejorante A | BB4: Bascula Mejorante B | BC4: Flowbalacer 1 | BD4: Flowbalacer 2 | BE4: Flowbalacer 3 | BF4: Flowbalacer 4
A5: 1 | B5: 46027 | R5: 40672 | S5: 37488 | AA5: =97+50 -> 147 | AB5: =138+152 -> 290 | AC5: =86+50 -> 136 | AD5: =+IF(B5="","",SUMPRODUCT(C5:AC5,$C$2:$AC$2)) -> 100235 | AE5: =IF(B5="","",C5+F5+H5+K5+Q5+N5+O5+((I5+J5+D5+G5)/2)+(R5/50)+(S5/50)+(T5/50)+(U5/2)+(E5/5)) -> 1563.2 | AF5: =IF(B5="","",((AE5*50)/AD5)) -> 0.77976755 | AG5: =IF(C5="","",((Z5)*25)/AD5) | AH5: =IF(B5="","",(X5*25)/AD5) -> 0 | AI5: =IF(B5="","",(Y5*25)/AD5) -> 0 | AJ5: =IF(B5="","",(AA5*25)/AD5) -> 0.03666384 | AK5: =IF(B5="","",(AB5*40)/AD5) -> 0.11572804 | AL5: =IF(B5="","",(AC5*50)/AD5) -> 0.067840575 | AM5: =IF(B5="","",B5) -> 46027 | AN5: 18 | AO5: 16.5 | AP5: 0.25 | AQ5: =IF(AN5="","",AN5/AO5) -> 1.0909091 | AR5: =IF(AN5="","",(AD5/AN5)/1000) -> 5.5686111 | AS5: =IF(AN5="","",AR5*24) -> 133.64667 | AT5: =IF(AN5="","",(AD5/1000)*100%/AS5) -> 0.75 | AU5: =IF(AN5="","",(AE5/AN5)) -> 86.844444 | AV5: =IF(AN5="","",(AD5/AO5)/1000) -> 6.0748485 | AX5: 2031488 | AY5: 1577712 | AZ5: 68862 | BA5: 1632 | BB5: 374982 | BC5: 1540192 | BD5: 1476 | BE5: 431952 | BF5: 245848
A6: 2 | B6: 46028 | F6: 180 | I6: 909 | J6: 80 | R6: 33856 | T6: 20640 | Z6: 131 | AA6: =145+58+78 -> 281 | AB6: =133+115+139 -> 387 | AC6: =37+30 -> 67 | AD6: =+IF(B6="","",SUMPRODUCT(C6:AC6,$C$2:$AC$2)) -> 117351 | AE6: =IF(B6="","",C6+F6+H6+K6+Q6+N6+O6+((I6+J6+D6+G6+U6)/2)+(R6/50)+(S6/50)+(T6/50)+(E6/5)) -> 1764.42 | AF6: =IF(B6="","",((AE6*50)/AD6)) -> 0.75177033 | AG6: =IF(C6="","",((Z6)*25)/AD6) | AH6: =IF(B6="","",(X6*25)/AD6) -> 0 | AI6: =IF(B6="","",(Y6*25)/AD6) -> 0 | AJ6: =IF(B6="","",(AA6*25)/AD6) -> 0.059863146 | AK6: =IF(B6="","",(AB6*40)/AD6) -> 0.13191196 | AL6: =IF(B6="","",(AC6*50)/AD6) -> 0.028546838 | AM6: =IF(B6="","",B6) -> 46028 | AN6: 23 | AO6: =14.5+18.5/2 -> 23.75 | AP6: 0.33 | AQ6: =IF(AN6="","",AN6/AO6) -> 0.96842105 | AR6: =IF(AN6="","",(AD6/AN6)/1000) -> 5.1022174 | AS6: =IF(AN6="","",AR6*24) -> 122.45322 | AT6: =IF(AN6="","",(AD6/1000)*100%/AS6) -> 0.95833333 | AU6: =IF(AN6="","",(AE6/AN6)) -> 76.713913 | AV6: =IF(AN6="","",(AD6/AO6)/1000) -> 4.9410947
A7: 3 | B7: 46029 | C7: 1471 | F7: 315 | G7: 182 | AA7: 175 | AB7: 398 | AC7: 95 | AD7: =+IF(B7="","",SUMPRODUCT(C7:AC7,$C$2:$AC$2)) -> 118895 | AE7: =IF(B7="","",C7+F7+H7+K7+Q7+N7+O7+((I7+J7+D7+G7+U7)/2)+(R7/50)+(S7/50)+(T7/50)+(E7/5)) -> 1877 | AF7: =IF(B7="","",((AE7*50)/AD7)) -> 0.78935195 | AG7: =IF(C7="","",((Z7)*25)/AD7) -> 0 | AH7: =IF(B7="","",(X7*25)/AD7) -> 0 | AI7: =IF(B7="","",(Y7*25)/AD7) -> 0 | AJ7: =IF(B7="","",(AA7*25)/AD7) -> 0.036797174 | AK7: =IF(B7="","",(AB7*40)/AD7) -> 0.13389966 | AL7: =IF(B7="","",(AC7*50)/AD7) -> 0.039951217 | AM7: =IF(B7="","",B7) -> 46029 | AN7: 24 | AO7: 18.3 | AP7: 0 | AQ7: =IF(AN7="","",AN7/AO7) -> 1.3114754 | AR7: =IF(AN7="","",(AD7/AN7)/1000) -> 4.9539583 | AS7: =IF(AN7="","",AR7*24) -> 118.895 | AT7: =IF(AN7="","",(AD7/1000)*100%/AS7) -> 1 | AU7: =IF(AN7="","",(AE7/AN7)) -> 78.208333 | AV7: =IF(AN7="","",(AD7/AO7)/1000) -> 6.4969945
A8: 4 | B8: 46030 | C8: 1386 | D8: 248 | R8: 10352 | AA8: 173 | AB8: 376 | AC8: 95 | AD8: =+IF(B8="","",SUMPRODUCT(C8:AC8,$C$2:$AC$2)) -> 109967 | AE8: =IF(B8="","",C8+F8+H8+K8+Q8+N8+O8+((I8+J8+D8+G8+U8)/2)+(R8/50)+(S8/50)+(T8/50)+(E8/5)) -> 1717.04 | AF8: =IF(B8="","",((AE8*50)/AD8)) -> 0.78070694 | AG8: =IF(C8="","",((Z8)*25)/AD8) -> 0 | AH8: =IF(B8="","",(X8*25)/AD8) -> 0 | AI8: =IF(B8="","",(Y8*25)/AD8) -> 0 | AJ8: =IF(B8="","",(AA8*25)/AD8) -> 0.039329981 | AK8: =IF(B8="","",(AB8*40)/AD8) -> 0.1367683 | AL8: =IF(B8="","",(AC8*50)/AD8) -> 0.043194777 | AM8: =IF(B8="","",B8) -> 46030 | AN8: 23.75 | AO8: 14 | AP8: 0.25 | AQ8: =IF(AN8="","",AN8/AO8) -> 1.6964286 | AR8: =IF(AN8="","",(AD8/AN8)/1000) -> 4.6301895 | AS8: =IF(AN8="","",AR8*24) -> 111.12455 | AT8: =IF(AN8="","",(AD8/1000)*100%/AS8) -> 0.98958333 | AU8: =IF(AN8="","",(AE8/AN8)) -> 72.296421 | AV8: =IF(AN8="","",(AD8/AO8)/1000) -> 7.8547857
A9: 5 | B9: 46031 | R9: 38912 | S9: 49552 | Z9: 121 | AA9: 193 | AB9: 447 | AC9: 209 | AD9: =+IF(B9="","",SUMPRODUCT(C9:AC9,$C$2:$AC$2)) -> 124644 | AE9: =IF(B9="","",C9+F9+H9+K9+Q9+N9+O9+((I9+J9+D9+G9+U9)/2)+(R9/50)+(S9/50)+(T9/50)+(E9/5)) -> 1769.28 | AF9: =IF(B9="","",((AE9*50)/AD9)) -> 0.70973332 | AG9: =IF(C9="","",((Z9)*25)/AD9) | AH9: =IF(B9="","",(X9*25)/AD9) -> 0 | AI9: =IF(B9="","",(Y9*25)/AD9) -> 0 | AJ9: =IF(B9="","",(AA9*25)/AD9) -> 0.038710247 | AK9: =IF(B9="","",(AB9*40)/AD9) -> 0.14344854 | AL9: =IF(B9="","",(AC9*50)/AD9) -> 0.083838773 | AM9: =IF(B9="","",B9) -> 46031 | AN9: 24 | AO9: 14.3 | AP9: 0 | AQ9: =IF(AN9="","",AN9/AO9) -> 1.6783217 | AR9: =IF(AN9="","",(AD9/AN9)/1000) -> 5.1935 | AS9: =IF(AN9="","",AR9*24) -> 124.644 | AT9: =IF(AN9="","",(AD9/1000)*100%/AS9) -> 1 | AU9: =IF(AN9="","",(AE9/AN9)) -> 73.72 | AV9: =IF(AN9="","",(AD9/AO9)/1000) -> 8.7163636
A10: 6 | B10: 46035 | I10: 407 | R10: 104476 | AA10: 263 | AB10: 433 | AC10: 140 | AD10: =+IF(B10="","",SUMPRODUCT(C10:AC10,$C$2:$AC$2)) -> 145546 | AE10: =IF(B10="","",C10+F10+H10+K10+Q10+N10+O10+((I10+J10+D10+G10+U10)/2)+(R10/50)+(S10/50)+(T10/50)+(E10/5)) -> 2293.02 | AF10: =IF(B10="","",((AE10*50)/AD10)) -> 0.78773034 | AG10: =IF(C10="","",((Z10)*25)/AD10) | AH10: =IF(B10="","",(X10*25)/AD10) -> 0 | AI10: =IF(B10="","",(Y10*25)/AD10) -> 0 | AJ10: =IF(B10="","",(AA10*25)/AD10) -> 0.045174721 | AK10: =IF(B10="","",(AB10*40)/AD10) -> 0.11900018 | AL10: =IF(B10="","",(AC10*50)/AD10) -> 0.04809476 | AM10: =IF(B10="","",B10) -> 46035 | AN10: 23.5 | AO10: =5.25+15.5 -> 20.75 | AP10: 0.5 | AQ10: =IF(AN10="","",AN10/AO10) -> 1.1325301 | AR10: =IF(AN10="","",(AD10/AN10)/1000) -> 6.1934468 | AS10: =IF(AN10="","",AR10*24) -> 148.64272 | AT10: =IF(AN10="","",(AD10/1000)*100%/AS10) -> 0.97916667 | AU10: =IF(AN10="","",(AE10/AN10)) -> 97.575319 | AV10: =IF(AN10="","",(AD10/AO10)/1000) -> 7.0142651
A11: 7 | B11: 46036 | C11: 552 | D11: 1000 | I11: 611 | K11: 746 | Y11: 10 | AA11: 137 | AB11: 403 | AC11: 90 | AD11: =+IF(B11="","",SUMPRODUCT(C11:AC11,$C$2:$AC$2)) -> 129470 | AE11: =IF(B11="","",C11+F11+H11+K11+Q11+N11+O11+((I11+J11+D11+G11+U11)/2)+(R11/50)+(S11/50)+(T11/50)+(E11/5)) -> 2103.5 | AF11: =IF(B11="","",((AE11*50)/AD11)) -> 0.81235035 | AG11: =IF(C11="","",((Z11)*25)/AD11) -> 0 | AH11: =IF(B11="","",(X11*25)/AD11) -> 0 | AI11: =IF(B11="","",(Y11*25)/AD11) -> 0.0019309493 | AJ11: =IF(B11="","",(AA11*25)/AD11) -> 0.026454005 | AK11: =IF(B11="","",(AB11*40)/AD11) -> 0.12450761 | AL11: =IF(B11="","",(AC11*50)/AD11) -> 0.034757087 | AM11: =IF(B11="","",B11) -> 46036 | AN11: 23.5 | AO11: 18.5 | AP11: 0.5 | AQ11: =IF(AN11="","",AN11/AO11) -> 1.2702703 | AR11: =IF(AN11="","",(AD11/AN11)/1000) -> 5.5093617 | AS11: =IF(AN11="","",AR11*24) -> 132.22468 | AT11: =IF(AN11="","",(AD11/1000)*100%/AS11) -> 0.97916667 | AU11: =IF(AN11="","",(AE11/AN11)) -> 89.510638 | AV11: =IF(AN11="","",(AD11/AO11)/1000) -> 6.9983784
A12: 8 | B12: 46037 | C12: 505 | R12: 64528 | Y12: 15 | AA12: 147 | AB12: 364 | AC12: 131 | AD12: =+IF(B12="","",SUMPRODUCT(C12:AC12,$C$2:$AC$2)) -> 114938 | AE12: =IF(B12="","",C12+F12+H12+K12+Q12+N12+O12+((I12+J12+D12+G12+U12)/2)+(R12/50)+(S12/50)+(T12/50)+(E12/5)) -> 1795.56 | AF12: =IF(B12="","",((AE12*50)/AD12)) -> 0.78109938 | AG12: =IF(C12="","",((Z12)*25)/AD12) -> 0 | AH12: =IF(B12="","",(X12*25)/AD12) -> 0 | AI12: =IF(B12="","",(Y12*25)/AD12) -> 0.0032626285 | AJ12: =IF(B12="","",(AA12*25)/AD12) -> 0.03197376 | AK12: =IF(B12="","",(AB12*40)/AD12) -> 0.12667699 | AL12: =IF(B12="","",(AC12*50)/AD12) -> 0.056987245 | AM12: =IF(B12="","",B12) -> 46037 | AN12: 24 | AO12: 12 | AP12: 0 | AQ12: =IF(AN12="","",AN12/AO12) -> 2 | AR12: =IF(AN12="","",(AD12/AN12)/1000) -> 4.7890833 | AS12: =IF(AN12="","",AR12*24) -> 114.938 | AT12: =IF(AN12="","",(AD12/1000)*100%/AS12) -> 1 | AU12: =IF(AN12="","",(AE12/AN12)) -> 74.815 | AV12: =IF(AN12="","",(AD12/AO12)/1000) -> 9.5781667
A13: 9 | B13: 46038 | R13: 39760 | S13: 44536 | U13: 200 | AA13: 191 | AB13: 457 | AC13: 88 | AD13: =+IF(B13="","",SUMPRODUCT(C13:AC13,$C$2:$AC$2)) -> 116751 | AE13: =IF(B13="","",C13+F13+H13+K13+Q13+N13+O13+((I13+J13+D13+G13+U13)/2)+(R13/50)+(S13/50)+(T13/50)+(E13/5)) -> 1785.92 | AF13: =IF(B13="","",((AE13*50)/AD13)) -> 0.76484141 | AG13: =IF(C13="","",((Z13)*25)/AD13) | AH13: =IF(B13="","",(X13*25)/AD13) -> 0 | AI13: =IF(B13="","",(Y13*25)/AD13) -> 0 | AJ13: =IF(B13="","",(AA13*25)/AD13) -> 0.040899007 | AK13: =IF(B13="","",(AB13*40)/AD13) -> 0.15657253 | AL13: =IF(B13="","",(AC13*50)/AD13) -> 0.037687043 | AM13: =IF(B13="","",B13) -> 46038 | AN13: 23.75 | AO13: 14.9 | AP13: 0.25 | AQ13: =IF(AN13="","",AN13/AO13) -> 1.5939597 | AR13: =IF(AN13="","",(AD13/AN13)/1000) -> 4.9158316 | AS13: =IF(AN13="","",AR13*24) -> 117.97996 | AT13: =IF(AN13="","",(AD13/1000)*100%/AS13) -> 0.98958333 | AU13: =IF(AN13="","",(AE13/AN13)) -> 75.196632 | AV13: =IF(AN13="","",(AD13/AO13)/1000) -> 7.8356376
A14: 10 | B14: 46041 | R14: 100080 | Y14: 10 | AA14: 179 | AB14: 406 | AC14: 127 | AD14: =+IF(B14="","",SUMPRODUCT(C14:AC14,$C$2:$AC$2)) -> 127395 | AE14: =IF(B14="","",C14+F14+H14+K14+Q14+N14+O14+((I14+J14+D14+G14+U14)/2)+(R14/50)+(S14/50)+(T14/50)+(E14/5)) -> 2001.6 | AF14: =IF(B14="","",((AE14*50)/AD14)) -> 0.78558813 | AG14: =IF(C14="","",((Z14)*25)/AD14) | AH14: =IF(B14="","",(X14*25)/AD14) -> 0 | AI14: =IF(B14="","",(Y14*25)/AD14) -> 0.0019624004 | AJ14: =IF(B14="","",(AA14*25)/AD14) -> 0.035126967 | AK14: =IF(B14="","",(AB14*40)/AD14) -> 0.12747753 | AL14: =IF(B14="","",(AC14*50)/AD14) -> 0.04984497 | AM14: =IF(B14="","",B14) -> 46041 | AN14: 24 | AO14: =9.1+14.75 -> 23.85 | AP14: 0 | AQ14: =IF(AN14="","",AN14/AO14) -> 1.0062893 | AR14: =IF(AN14="","",(AD14/AN14)/1000) -> 5.308125 | AS14: =IF(AN14="","",AR14*24) -> 127.395 | AT14: =IF(AN14="","",(AD14/1000)*100%/AS14) -> 1 | AU14: =IF(AN14="","",(AE14/AN14)) -> 83.4 | AV14: =IF(AN14="","",(AD14/AO14)/1000) -> 5.3415094
A15: 11 | B15: 46042 | C15: 1100 | R15: 3328 | S15: 24560 | Y15: 31 | AA15: 138 | AB15: 416 | AC15: 81 | AD15: =+IF(B15="","",SUMPRODUCT(C15:AC15,$C$2:$AC$2)) -> 107803 | AE15: =IF(B15="","",C15+F15+H15+K15+Q15+N15+O15+((I15+J15+D15+G15+U15)/2)+(R15/50)+(S15/50)+(T15/50)+(E15/5)) -> 1657.76 | AF15: =IF(B15="","",((AE15*50)/AD15)) -> 0.76888398 | AG15: =IF(C15="","",((Z15)*25)/AD15) -> 0 | AH15: =IF(B15="","",(X15*25)/AD15) -> 0 | AI15: =IF(B15="","",(Y15*25)/AD15) -> 0.0071890393 | AJ15: =IF(B15="","",(AA15*25)/AD15) -> 0.03200282 | AK15: =IF(B15="","",(AB15*40)/AD15) -> 0.15435563 | AL15: =IF(B15="","",(AC15*50)/AD15) -> 0.037568528 | AM15: =IF(B15="","",B15) -> 46042 | AN15: 24 | AO15: 22.25 | AP15: 0 | AQ15: =IF(AN15="","",AN15/AO15) -> 1.0786517 | AR15: =IF(AN15="","",(AD15/AN15)/1000) -> 4.4917917 | AS15: =IF(AN15="","",AR15*24) -> 107.803 | AT15: =IF(AN15="","",(AD15/1000)*100%/AS15) -> 1 | AU15: =IF(AN15="","",(AE15/AN15)) -> 69.073333 | AV15: =IF(AN15="","",(AD15/AO15)/1000) -> 4.8450787
A16: 12 | B16: 46043 | C16: 792 | F16: 346 | G16: 300 | I16: 826 | J16: 120 | Y16: 19 | AA16: 160 | AB16: 390 | AC16: 98 | AD16: =+IF(B16="","",SUMPRODUCT(C16:AC16,$C$2:$AC$2)) -> 113025 | AE16: =IF(B16="","",C16+F16+H16+K16+Q16+N16+O16+((I16+J16+D16+G16+U16)/2)+(R16/50)+(S16/50)+(T16/50)+(E16/5)) -> 1761 | AF16: =IF(B16="","",((AE16*50)/AD16)) -> 0.77903119 | AG16: =IF(C16="","",((Z16)*25)/AD16) -> 0 | AH16: =IF(B16="","",(X16*25)/AD16) -> 0 | AI16: =IF(B16="","",(Y16*25)/AD16) -> 0.00420261 | AJ16: =IF(B16="","",(AA16*25)/AD16) -> 0.0353904 | AK16: =IF(B16="","",(AC16*40)/AD16) -> 0.034682592 | AL16: =IF(B16="","",(AC16*50)/AD16) -> 0.04335324 | AM16: =IF(B16="","",B16) -> 46043 | AN16: 24 | AO16: 14.9 | AP16: 0 | AQ16: =IF(AN16="","",AN16/AO16) -> 1.6107383 | AR16: =IF(AN16="","",(AD16/AN16)/1000) -> 4.709375 | AS16: =IF(AN16="","",AR16*24) -> 113.025 | AT16: =IF(AN16="","",(AD16/1000)*100%/AS16) -> 1 | AU16: =IF(AN16="","",(AE16/AN16)) -> 73.375 | AV16: =IF(AN16="","",(AD16/AO16)/1000) -> 7.5855705
A17: 13 | B17: 46044 | C17: 1718 | Q17: 30 | AA17: 156 | AB17: 379 | AC17: 59 | AD17: =+IF(B17="","",SUMPRODUCT(C17:AC17,$C$2:$AC$2)) -> 109410 | AE17: =IF(B17="","",C17+F17+H17+K17+Q17+N17+O17+((I17+J17+D17+G17+U17)/2)+(R17/50)+(S17/50)+(T17/50)+(E17/5)) -> 1748 | AF17: =IF(B17="","",((AE17*50)/AD17)) -> 0.79883009 | AG17: =IF(C17="","",((Z17)*25)/AD17) -> 0 | AH17: =IF(B17="","",(X17*25)/AD17) -> 0 | AI17: =IF(B17="","",(Y17*25)/AD17) -> 0 | AJ17: =IF(B17="","",(AA17*25)/AD17) -> 0.035645736 | AK17: =IF(B17="","",(AB17*40)/AD17) -> 0.13856137 | AL17: =IF(B17="","",(AC17*50)/AD17) -> 0.0269628 | AM17: =IF(B17="","",B17) -> 46044 | AN17: 23 | AO17: 19.25 | AP17: 1 | AQ17: =IF(AN17="","",AN17/AO17) -> 1.1948052 | AR17: =IF(AN17="","",(AD17/AN17)/1000) -> 4.7569565 | AS17: =IF(AN17="","",AR17*24) -> 114.16696 | AT17: =IF(AN17="","",(AD17/1000)*100%/AS17) -> 0.95833333 | AU17: =IF(AN17="","",(AE17/AN17)) -> 76 | AV17: =IF(AN17="","",(AD17/AO17)/1000) -> 5.6836364
A18: 14 | B18: 46045 | Q18: 235 | R18: 57552 | S18: 7850 | X18: 15 | Z18: 103 | AA18: 181 | AB18: 364 | AC18: 158 | AD18: =+IF(B18="","",SUMPRODUCT(C18:AC18,$C$2:$AC$2)) -> 107087 | AE18: =IF(B18="","",C18+F18+H18+K18+Q18+N18+O18+((I18+J18+D18+G18+U18)/2)+(R18/50)+(S18/50)+(T18/50)+(E18/5)) -> 1543.04 | AF18: =IF(B18="","",((AE18*50)/AD18)) -> 0.72046093 | AG18: =IF(C18="","",((Z18)*25)/AD18) | AH18: =IF(B18="","",(X18*25)/AD18) -> 0.0035018256 | AI18: =IF(B18="","",(Y18*25)/AD18) -> 0 | AJ18: =IF(B18="","",(AA18*25)/AD18) -> 0.042255362 | AK18: =IF(B18="","",(AB18*40)/AD18) -> 0.13596422 | AL18: =IF(B18="","",(AC18*50)/AD18) -> 0.073771793 | AM18: =IF(B18="","",B18) -> 46045 | AN18: 21.7 | AO18: 19.1 | AP18: 2.28 | AQ18: =IF(AN18="","",AN18/AO18) -> 1.1361257 | AR18: =IF(AN18="","",(AD18/AN18)/1000) -> 4.9348848 | AS18: =IF(AN18="","",AR18*24) -> 118.43724 | AT18: =IF(AN18="","",(AD18/1000)*100%/AS18) -> 0.90416667 | AU18: =IF(AN18="","",(AE18/AN18)) -> 71.107834 | AV18: =IF(AN18="","",(AD18/AO18)/1000) -> 5.6066492
A19: 15 | B19: 46050 | C19: 581 | F19: 317 | G19: 300 | H19: 488 | S19: 24736 | AA19: 220 | AB19: 484 | AC19: 43 | AD19: =+IF(B19="","",SUMPRODUCT(C19:AC19,$C$2:$AC$2)) -> 128546 | AE19: =IF(B19="","",C19+F19+H19+K19+Q19+N19+O19+((I19+J19+D19+G19+U19)/2)+(R19/50)+(S19/50)+(T19/50)+(E19/5)) -> 2030.72 | AF19: =IF(B19="","",((AE19*50)/AD19)) -> 0.78988067 | AG19: =IF(C19="","",((Z19)*25)/AD19) -> 0 | AH19: =IF(B19="","",(X19*25)/AD19) -> 0 | AI19: =IF(B19="","",(Y19*25)/AD19) -> 0 | AJ19: =IF(B19="","",(AA19*25)/AD19) -> 0.04278624 | AK19: =IF(B19="","",(AB19*40)/AD19) -> 0.15060756 | AL19: =IF(B19="","",(AC19*50)/AD19) -> 0.01672553 | AM19: =IF(B19="","",B19) -> 46050 | AN19: 23.58 | AO19: =17.5+1.5 -> 19 | AP19: 0.41 | AQ19: =IF(AN19="","",AN19/AO19) -> 1.2410526 | AR19: =IF(AN19="","",(AD19/AN19)/1000) -> 5.4514843 | AS19: =IF(AN19="","",AR19*24) -> 130.83562 | AT19: =IF(AN19="","",(AD19/1000)*100%/AS19) -> 0.9825 | AU19: =IF(AN19="","",(AE19/AN19)) -> 86.120441 | AV19: =IF(AN19="","",(AD19/AO19)/1000) -> 6.7655789
A20: 16 | B20: 46051 | C20: 1892 | Z20: 23 | AA20: 160 | AB20: 403 | AC20: 71 | AD20: =+IF(B20="","",SUMPRODUCT(C20:AC20,$C$2:$AC$2)) -> 118845 | AE20: =IF(B20="","",C20+F20+H20+K20+Q20+N20+O20+((I20+J20+D20+G20+U20)/2)+(R20/50)+(S20/50)+(T20/50)+(E20/5)) -> 1892 | AF20: =IF(B20="","",((AE20*50)/AD20)) -> 0.79599478 | AG20: =IF(C20="","",((Z20)*25)/AD20) -> 0.0048382347 | AH20: =IF(B20="","",(X20*25)/AD20) -> 0 | AI20: =IF(B20="","",(Y20*25)/AD20) -> 0 | AJ20: =IF(B20="","",(AA20*25)/AD20) -> 0.033657285 | AK20: =IF(B20="","",(AB20*40)/AD20) -> 0.13563886 | AL20: =IF(B20="","",(AC20*50)/AD20) -> 0.02987084 | AM20: =IF(B20="","",B20) -> 46051 | AN20: 23.67 | AO20: 18.9 | AP20: 0.33 | AQ20: =IF(AN20="","",AN20/AO20) -> 1.252381 | AR20: =IF(AN20="","",(AD20/AN20)/1000) -> 5.0209125 | AS20: =IF(AN20="","",AR20*24) -> 120.5019 | AT20: =IF(AN20="","",(AD20/1000)*100%/AS20) -> 0.98625 | AU20: =IF(AN20="","",(AE20/AN20)) -> 79.932404 | AV20: =IF(AN20="","",(AD20/AO20)/1000) -> 6.2880952
A21: 17 | B21: 46052 | C21: 192 | F21: 110 | G21: 200 | H21: 267 | R21: 44224 | AA21: 174 | AB21: 354 | AC21: 177 | AD21: =+IF(B21="","",SUMPRODUCT(C21:AC21,$C$2:$AC$2)) -> 105034 | AE21: =IF(B21="","",C21+F21+H21+K21+Q21+N21+O21+((I21+J21+D21+G21+U21)/2)+(R21/50)+(S21/50)+(T21/50)+(E21/5)) -> 1553.48 | AF21: =IF(B21="","",((AE21*50)/AD21)) -> 0.73951292 | AG21: =IF(C21="","",((Z21)*25)/AD21) -> 0 | AH21: =IF(B21="","",(X21*25)/AD21) -> 0 | AI21: =IF(B21="","",(Y21*25)/AD21) -> 0 | AJ21: =IF(B21="","",(AA21*25)/AD21) -> 0.041415161 | AK21: =IF(B21="","",(AB21*40)/AD21) -> 0.13481349 | AL21: =IF(B21="","",(AC21*50)/AD21) -> 0.084258431 | AM21: =IF(B21="","",B21) -> 46052 | AN21: 23.58 | AO21: 19.1 | AP21: 0.41 | AQ21: =IF(AN21="","",AN21/AO21) -> 1.234555 | AR21: =IF(AN21="","",(AD21/AN21)/1000) -> 4.4543681 | AS21: =IF(AN21="","",AR21*24) -> 106.90483 | AT21: =IF(AN21="","",(AD21/1000)*100%/AS21) -> 0.9825 | AU21: =IF(AN21="","",(AE21/AN21)) -> 65.881255 | AV21: =IF(AN21="","",(AD21/AO21)/1000) -> 5.4991623
AE22: =IF(B22="","",C22+F22+H22+K22+Q22+N22+O22+((I22+J22+D22+G22+U22)/2)+(R22/50)+(S22/50)+(T22/50)+(E22/5)) | AF22: =IF(B22="","",((AE22*50)/AD22)) | AG22: =IF(C22="","",((Z22)*25)/AD22) | AH22: =IF(B22="","",(X22*25)/AD22) | AI22: =IF(B22="","",(Y22*25)/AD22) | AJ22: =IF(B22="","",(AA22*25)/AD22) | AK22: =IF(B22="","",(AB22*40)/AD22) | AL22: =IF(B22="","",(AC22*50)/AD22) | AM22: =IF(B22="","",B22) | AQ22: =IF(AN22="","",AN22/AO22) | AR22: =IF(AN22="","",(AD22/AN22)/1000) | AS22: =IF(AN22="","",AR22*24) | AT22: =IF(AN22="","",(AD22/1000)*100%/AS22) | AU22: =IF(AN22="","",(AE22/AN22)) | AV22: =IF(AN22="","",(AD22/AO22)/1000)
AD23: =IF(B23="","",(((C23+F23+H23+K23+Q23+N23+O23)*50))+((E23*10))+(((I23+J23+D23+G23+L23+M23+U23)*25)+(X23*25)+(Y23*25)+(Z23*25)+(AA23*25)+(AB23*40)+(AC23*50)+(R23*1)+(S23*1)+(T23*1))) | AE23: =IF(B23="","",C23+F23+H23+K23+Q23+N23+O23+((I23+J23+D23+G23+U23)/2)+(R23/50)+(S23/50)+(T23/50)+(E23/5)) | AF23: =IF(B23="","",((AE23*50)/AD23)) | AG23: =IF(C23="","",((Z23)*25)/AD23) | AH23: =IF(B23="","",(X23*25)/AD23) | AI23: =IF(B23="","",(Y23*25)/AD23) | AJ23: =IF(B23="","",(AA23*25)/AD23) | AK23: =IF(B23="","",(AB23*40)/AD23) | AL23: =IF(B23="","",(AC23*50)/AD23) | AM23: =IF(B23="","",B23) | AQ23: =IF(AN23="","",AN23/AO23) | AR23: =IF(AN23="","",(AD23/AN23)/1000) | AS23: =IF(AN23="","",AR23*24) | AT23: =IF(AN23="","",(AD23/1000)*100%/AS23) | AU23: =IF(AN23="","",(AE23/AN23)) | AV23: =IF(AN23="","",(AD23/AO23)/1000)
AE24: =IF(B24="","",C24+F24+H24+K24+Q24+N24+O24+((I24+J24+D24+G24+U24)/2)+(R24/50)+(S24/50)+(T24/50)+(E24/5)) | AF24: =IF(B24="","",((AE24*50)/AD24)) | AG24: =IF(C24="","",((Z24)*25)/AD24) | AH24: =IF(B24="","",(X24*25)/AD24) | AI24: =IF(B24="","",(Y24*25)/AD24) | AJ24: =IF(B24="","",(AA24*25)/AD24) | AK24: =IF(B24="","",(AB24*40)/AD24) | AL24: =IF(B24="","",(AC24*50)/AD24) | AM24: =IF(B24="","",B24) | AQ24: =IF(AN24="","",AN24/AO24) | AR24: =IF(AN24="","",(AD24/AN24)/1000) | AS24: =IF(AN24="","",AR24*24) | AT24: =IF(AN24="","",(AD24/1000)*100%/AS24) | AU24: =IF(AN24="","",(AE24/AN24)) | AV24: =IF(AN24="","",(AD24/AO24)/1000)
A25: =IF(B25="","",1+A24) | AD25: =IF(B25="","",(((C25+F25+H25+K25+Q25+N25+O25)*50))+((E25*10))+(((I25+J25+D25+G25+L25+M25+U25)*25)+(X25*25)+(Y25*25)+(Z25*25)+(AA25*25)+(AB25*40)+(AC25*50)+(R25*1)+(S25*1)+(T25*1))) | AE25: =IF(B25="","",C25+F25+H25+K25+Q25+N25+O25+((I25+J25+D25+G25+U25)/2)+(R25/50)+(S25/50)+(T25/50)+(E25/5)) | AF25: =IF(B25="","",((AE25*50)/AD25)) | AG25: =IF(C25="","",((Z25)*25)/AD25) | AH25: =IF(B25="","",(X25*25)/AD25) | AI25: =IF(B25="","",(Y25*25)/AD25) | AJ25: =IF(B25="","",(AA25*25)/AD25) | AK25: =IF(B25="","",(AB25*40)/AD25) | AL25: =IF(B25="","",(AC25*50)/AD25) | AM25: =IF(B25="","",B25) | AQ25: =IF(AN25="","",AN25/AO25) | AR25: =IF(AN25="","",(AD25/AN25)/1000) | AS25: =IF(AN25="","",AR25*24) | AT25: =IF(AN25="","",(AD25/1000)*100%/AS25) | AU25: =IF(AN25="","",(AE25/AN25)) | AV25: =IF(AN25="","",(AD25/AO25)/1000)
AD26: =IF(B26="","",(((C26+F26+H26+K26+Q26+N26+O26)*50))+((E26*10))+(((I26+J26+D26+G26+L26+M26+U26)*25)+(X26*25)+(Y26*25)+(Z26*25)+(AA26*25)+(AB26*40)+(AC26*50)+(R26*1)+(S26*1)+(T26*1))) | AE26: =IF(B26="","",C26+F26+H26+K26+Q26+N26+O26+((I26+J26+D26+G26+U26)/2)+(R26/50)+(S26/50)+(T26/50)+(E26/5)) | AF26: =IF(B26="","",((AE26*50)/AD26)) | AG26: =IF(C26="","",((Z26)*25)/AD26) | AH26: =IF(B26="","",(X26*25)/AD26) | AI26: =IF(B26="","",(Y26*25)/AD26) | AJ26: =IF(B26="","",(AA26*25)/AD26) | AK26: =IF(B26="","",(AB26*40)/AD26) | AL26: =IF(B26="","",(AC26*50)/AD26) | AM26: =IF(B26="","",B26) | AQ26: =IF(AN26="","",AN26/AO26) | AR26: =IF(AN26="","",(AD26/AN26)/1000) | AS26: =IF(AN26="","",AR26*24) | AT26: =IF(AN26="","",(AD26/1000)*100%/AS26) | AU26: =IF(AN26="","",(AE26/AN26)) | AV26: =IF(AN26="","",(AD26/AO26)/1000)
AD27: =IF(B27="","",(((C27+F27+H27+K27+Q27+N27+O27)*50))+((E27*10))+(((I27+J27+D27+G27+L27+M27+U27)*25)+(X27*25)+(Y27*25)+(Z27*25)+(AA27*25)+(AB27*40)+(AC27*50)+(R27*1)+(S27*1)+(T27*1))) | AE27: =IF(B27="","",C27+F27+H27+K27+Q27+N27+O27+((I27+J27+D27+G27+U27)/2)+(R27/50)+(S27/50)+(T27/50)+(E27/5)) | AF27: =IF(B27="","",((AE27*50)/AD27)) | AG27: =IF(C27="","",((Z27)*25)/AD27) | AH27: =IF(B27="","",(X27*25)/AD27) | AI27: =IF(B27="","",(Y27*25)/AD27) | AJ27: =IF(B27="","",(AA27*25)/AD27) | AK27: =IF(B27="","",(AB27*40)/AD27) | AL27: =IF(B27="","",(AC27*50)/AD27) | AM27: =IF(B27="","",B27) | AQ27: =IF(AN27="","",AN27/AO27) | AR27: =IF(AN27="","",(AD27/AN27)/1000) | AS27: =IF(AN27="","",AR27*24) | AT27: =IF(AN27="","",(AD27/1000)*100%/AS27) | AU27: =IF(AN27="","",(AE27/AN27)) | AV27: =IF(AN27="","",(AD27/AO27)/1000)
AD28: =IF(B28="","",(((C28+F28+H28+K28+Q28+N28+O28)*50))+((E28*10))+(((I28+J28+D28+G28+L28+M28+U28)*25)+(X28*25)+(Y28*25)+(Z28*25)+(AA28*25)+(AB28*40)+(AC28*50)+(R28*1)+(S28*1)+(T28*1))) | AE28: =IF(B28="","",C28+F28+H28+K28+Q28+N28+O28+((I28+J28+D28+G28+U28)/2)+(R28/50)+(S28/50)+(T28/50)+(E28/5)) | AF28: =IF(B28="","",((AE28*50)/AD28)) | AG28: =IF(C28="","",((Z28)*25)/AD28) | AH28: =IF(B28="","",(X28*25)/AD28) | AI28: =IF(B28="","",(Y28*25)/AD28) | AJ28: =IF(B28="","",(AA28*25)/AD28) | AK28: =IF(B28="","",(AB28*40)/AD28) | AL28: =IF(B28="","",(AC28*50)/AD28) | AM28: =IF(B28="","",B28) | AQ28: =IF(AN28="","",AN28/AO28) | AR28: =IF(AN28="","",(AD28/AN28)/1000) | AS28: =IF(AN28="","",AR28*24) | AT28: =IF(AN28="","",(AD28/1000)*100%/AS28) | AU28: =IF(AN28="","",(AE28/AN28)) | AV28: =IF(AN28="","",(AD28/AO28)/1000)
AD29: =IF(B29="","",(((C29+F29+H29+K29+Q29+N29+O29)*50))+((E29*10))+(((I29+J29+D29+G29+L29+M29+U29)*25)+(X29*25)+(Y29*25)+(Z29*25)+(AA29*25)+(AB29*40)+(AC29*50)+(R29*1)+(S29*1)+(T29*1))) | AE29: =IF(B29="","",C29+F29+H29+K29+Q29+N29+O29+((I29+J29+D29+G29+U29)/2)+(R29/50)+(S29/50)+(T29/50)+(E29/5)) | AF29: =IF(B29="","",((AE29*50)/AD29)) | AG29: =IF(C29="","",((Z29)*25)/AD29) | AH29: =IF(B29="","",(X29*25)/AD29) | AI29: =IF(B29="","",(Y29*25)/AD29) | AJ29: =IF(B29="","",(AA29*25)/AD29) | AK29: =IF(B29="","",(AB29*40)/AD29) | AL29: =IF(B29="","",(AC29*50)/AD29) | AM29: =IF(B29="","",B29) | AQ29: =IF(AN29="","",AN29/AO29) | AR29: =IF(AN29="","",(AD29/AN29)/1000) | AS29: =IF(AN29="","",AR29*24) | AT29: =IF(AN29="","",(AD29/1000)*100%/AS29) | AU29: =IF(AN29="","",(AE29/AN29)) | AV29: =IF(AN29="","",(AD29/AO29)/1000)
AD30: =IF(B30="","",(((C30+F30+H30+K30+Q30+N30+O30)*50))+((E30*10))+(((I30+J30+D30+G30+L30+M30+U30)*25)+(X30*25)+(Y30*25)+(Z30*25)+(AA30*25)+(AB30*40)+(AC30*50)+(R30*1)+(S30*1)+(T30*1))) | AE30: =IF(B30="","",C30+F30+H30+K30+Q30+N30+O30+((I30+J30+D30+G30+U30)/2)+(R30/50)+(S30/50)+(T30/50)+(E30/5)) | AF30: =IF(B30="","",((AE30*50)/AD30)) | AG30: =IF(C30="","",((Z30)*25)/AD30) | AH30: =IF(B30="","",(X30*25)/AD30) | AI30: =IF(B30="","",(Y30*25)/AD30) | AJ30: =IF(B30="","",(AA30*25)/AD30) | AK30: =IF(B30="","",(AB30*40)/AD30) | AL30: =IF(B30="","",(AC30*50)/AD30) | AM30: =IF(B30="","",B30) | AQ30: =IF(AN30="","",AN30/AO30) | AR30: =IF(AN30="","",(AD30/AN30)/1000) | AS30: =IF(AN30="","",AR30*24) | AT30: =IF(AN30="","",(AD30/1000)*100%/AS30) | AU30: =IF(AN30="","",(AE30/AN30)) | AV30: =IF(AN30="","",(AD30/AO30)/1000)
A31: =IF(B31="","",1+A30) | AD31: =IF(B31="","",(((C31+F31+H31+K31+Q31+N31+O31)*50))+((E31*10))+(((I31+J31+D31+G31+L31+M31+U31)*25)+(X31*25)+(Y31*25)+(Z31*25)+(AA31*25)+(AB31*40)+(AC31*50)+(R31*1)+(S31*1)+(T31*1))) | AE31: =IF(B31="","",C31+F31+H31+K31+Q31+N31+O31+((I31+J31+D31+G31+U31)/2)+(R31/50)+(S31/50)+(T31/50)+(E31/5)) | AF31: =IF(B31="","",((AE31*50)/AD31)) | AG31: =IF(C31="","",((Z31)*25)/AD31) | AH31: =IF(B31="","",(X31*25)/AD31) | AI31: =IF(B31="","",(Y31*25)/AD31) | AJ31: =IF(B31="","",(AA31*25)/AD31) | AK31: =IF(B31="","",(AB31*40)/AD31) | AL31: =IF(B31="","",(AC31*50)/AD31) | AM31: =IF(B31="","",B31) | AQ31: =IF(AN31="","",AN31/AO31) | AR31: =IF(AN31="","",(AD31/AN31)/1000) | AS31: =IF(AN31="","",AR31*24) | AT31: =IF(AN31="","",(AD31/1000)*100%/AS31) | AU31: =IF(AN31="","",(AE31/AN31)) | AV31: =IF(AN31="","",(AD31/AO31)/1000)
A32: =IF(B32="","",1+A31) | AD32: =IF(B32="","",(((C32+F32+H32+K32+Q32+N32+O32)*50))+((E32*10))+(((I32+J32+D32+G32+L32+M32+U32)*25)+(X32*25)+(Y32*25)+(Z32*25)+(AA32*25)+(AB32*40)+(AC32*50)+(R32*1)+(S32*1)+(T32*1))) | AE32: =IF(B32="","",C32+F32+H32+K32+Q32+N32+O32+((I32+J32+D32+G32+U32)/2)+(R32/50)+(S32/50)+(T32/50)+(E32/5)) | AF32: =IF(B32="","",((AE32*50)/AD32)) | AG32: =IF(C32="","",((Z32)*25)/AD32) | AH32: =IF(B32="","",(X32*25)/AD32) | AI32: =IF(B32="","",(Y32*25)/AD32) | AJ32: =IF(B32="","",(AA32*25)/AD32) | AK32: =IF(B32="","",(AB32*40)/AD32) | AL32: =IF(B32="","",(AC32*50)/AD32) | AM32: =IF(B32="","",B32) | AQ32: =IF(AN32="","",AN32/AO32) | AR32: =IF(AN32="","",(AD32/AN32)/1000) | AS32: =IF(AN32="","",AR32*24) | AT32: =IF(AN32="","",(AD32/1000)*100%/AS32) | AU32: =IF(AN32="","",(AE32/AN32)) | AV32: =IF(AN32="","",(AD32/AO32)/1000)
A33: =IF(B33="","",1+A32) | AD33: =IF(B33="","",(((C33+F33+H33+K33+Q33+N33+O33)*50))+((E33*10))+(((I33+J33+D33+G33+L33+M33+U33)*25)+(X33*25)+(Y33*25)+(Z33*25)+(AA33*25)+(AB33*40)+(AC33*50)+(R33*1)+(S33*1)+(T33*1))) | AE33: =IF(B33="","",C33+F33+H33+K33+Q33+N33+O33+((I33+J33+D33+G33+U33)/2)+(R33/50)+(S33/50)+(T33/50)+(E33/5)) | AF33: =IF(B33="","",((AE33*50)/AD33)) | AG33: =IF(C33="","",((Z33)*25)/AD33) | AH33: =IF(B33="","",(X33*25)/AD33) | AI33: =IF(B33="","",(Y33*25)/AD33) | AJ33: =IF(B33="","",(AA33*25)/AD33) | AK33: =IF(B33="","",(AB33*40)/AD33) | AL33: =IF(B33="","",(AC33*50)/AD33) | AM33: =IF(B33="","",B33) | AQ33: =IF(AN33="","",AN33/AO33) | AR33: =IF(AN33="","",(AD33/AN33)/1000) | AS33: =IF(AN33="","",AR33*24) | AT33: =IF(AN33="","",(AD33/1000)*100%/AS33) | AU33: =IF(AN33="","",(AE33/AN33)) | AV33: =IF(AN33="","",(AD33/AO33)/1000)
A34: =IF(B34="","",1+A33) | AD34: =IF(B34="","",(((C34+F34+H34+K34+Q34+N34+O34)*50))+((E34*10))+(((I34+J34+D34+G34+L34+M34+U34)*25)+(X34*25)+(Y34*25)+(Z34*25)+(AA34*25)+(AB34*40)+(AC34*50)+(R34*1)+(S34*1)+(T34*1))) | AE34: =IF(B34="","",C34+F34+H34+K34+Q34+N34+O34+((I34+J34+D34+G34+U34)/2)+(R34/50)+(S34/50)+(T34/50)+(E34/5)) | AF34: =IF(B34="","",((AE34*50)/AD34)) | AG34: =IF(C34="","",((Z34)*25)/AD34) | AH34: =IF(B34="","",(X34*25)/AD34) | AI34: =IF(B34="","",(Y34*25)/AD34) | AJ34: =IF(B34="","",(AA34*25)/AD34) | AK34: =IF(B34="","",(AB34*40)/AD34) | AL34: =IF(B34="","",(AC34*50)/AD34) | AM34: =IF(B34="","",B34) | AQ34: =IF(AN34="","",AN34/AO34) | AR34: =IF(AN34="","",(AD34/AN34)/1000) | AS34: =IF(AN34="","",AR34*24) | AT34: =IF(AN34="","",(AD34/1000)*100%/AS34) | AU34: =IF(AN34="","",(AE34/AN34)) | AV34: =IF(AN34="","",(AD34/AO34)/1000)
A35: =IF(B35="","",1+A34) | AD35: =IF(B35="","",(((C35+F35+H35+K35+Q35+N35+O35)*50))+((E35*10))+(((I35+J35+D35+G35+L35+M35+U35)*25)+(X35*25)+(Y35*25)+(Z35*25)+(AA35*25)+(AB35*40)+(AC35*50)+(R35*1)+(S35*1)+(T35*1))) | AE35: =IF(B35="","",C35+F35+H35+K35+Q35+N35+O35+((I35+J35+D35+G35+U35)/2)+(R35/50)+(S35/50)+(T35/50)+(E35/5)) | AF35: =IF(B35="","",((AE35*50)/AD35)) | AG35: =IF(C35="","",((Z35)*25)/AD35) | AH35: =IF(B35="","",(X35*25)/AD35) | AI35: =IF(B35="","",(Y35*25)/AD35) | AJ35: =IF(B35="","",(AA35*25)/AD35) | AK35: =IF(B35="","",(AB35*40)/AD35) | AL35: =IF(B35="","",(AC35*50)/AD35) | AM35: =IF(B35="","",B35) | AQ35: =IF(AN35="","",AN35/AO35) | AR35: =IF(AN35="","",(AD35/AN35)/1000) | AS35: =IF(AN35="","",AR35*24) | AT35: =IF(AN35="","",(AD35/1000)*100%/AS35) | AU35: =IF(AN35="","",(AE35/AN35)) | AV35: =IF(AN35="","",(AD35/AO35)/1000)
A36: =IF(B36="","",1+A35) | AD36: =IF(B36="","",(((C36+F36+H36+K36+Q36+N36+O36)*50))+((E36*10))+(((I36+J36+D36+G36+L36+M36+U36)*25)+(X36*25)+(Y36*25)+(Z36*25)+(AA36*25)+(AB36*40)+(AC36*50)+(R36*1)+(S36*1)+(T36*1))) | AE36: =IF(B36="","",C36+F36+H36+K36+Q36+N36+O36+((I36+J36+D36+G36+U36)/2)+(R36/50)+(S36/50)+(T36/50)+(E36/5)) | AF36: =IF(B36="","",((AE36*50)/AD36)) | AG36: =IF(C36="","",((Z36)*25)/AD36) | AH36: =IF(B36="","",(X36*25)/AD36) | AI36: =IF(B36="","",(Y36*25)/AD36) | AJ36: =IF(B36="","",(AA36*25)/AD36) | AK36: =IF(B36="","",(AB36*40)/AD36) | AL36: =IF(B36="","",(AC36*50)/AD36) | AM36: =IF(B36="","",B36) | AQ36: =IF(AN36="","",AN36/AO36) | AR36: =IF(AN36="","",(AD36/AN36)/1000) | AS36: =IF(AN36="","",AR36*24) | AT36: =IF(AN36="","",(AD36/1000)*100%/AS36) | AU36: =IF(AN36="","",(AE36/AN36)) | AV36: =IF(AN36="","",(AD36/AO36)/1000)
B37: Total | C37: =SUM(C5:C11) -> 3409 | D37: =SUM(D5:D11) -> 1248 | E37: =SUM(E5:E11) -> 0 | F37: =SUM(F5:F15) -> 495 | G37: =SUM(G5:G15) -> 182 | H37: =SUM(H5:H21) -> 755 | I37: =SUM(I5:I11) -> 1927 | J37: =SUM(J5:J11) -> 80 | K37: =SUM(K5:K36) -> 746 | L37: =SUM(L5:L36) -> 0 | M37: =SUM(M5:M36) -> 0 | N37: =SUM(N5:N36) -> 0 | O37: =SUM(O5:O36) -> 0 | P37: =SUM(P5:P36) -> 0 | Q37: =SUM(Q5:Q36) -> 265 | R37: =SUM(R5:R10) -> 228268 | S37: =SUM(S5:S36) -> 188722 | T37: =SUM(T5:T36) -> 20640 | U37: =SUM(U5:U36) -> 200 | V37: =SUM(V5:V36) -> 0 | W37: =SUM(W5:W36) -> 0 | X37: =SUM(X5:X36) -> 15 | Y37: =SUM(Y5:Y36) -> 85 | Z37: =+SUM(Z5:Z36) -> 378 | AA37: =SUM(AA5:AA36) -> 3075 | AB37: =SUM(AB5:AB36) -> 6751 | AC37: =SUM(AC5:AC36) -> 1865 | AD37: =SUM(AD5:AD36) -> 1994942 | AE37: =SUM(AE5:AE36) -> 30856.54 | AF37: =IF(AD45=0,"",(AE37*50)/AD37) -> 0.77336935 | AG37: =IF(AD45=0,"",(Z37*50)/AD37) -> 0.0094739596 | AH37: =IF(AD45=0,"",(X37*25)/AD37) -> 0.00018797539 | AI37: =IF(AD45=0,"",(Y37*25)/AD37) -> 0.0010651939 | AJ37: =IF(AD45=0,"",(AA37*25)/AD37) -> 0.038534955 | AK37: =IF(AD45=0,"",(AB37*40)/AD37) -> 0.13536233 | AL37: =IF(AD45=0,"",(AC37*50)/AD37) -> 0.046743214 | AM37: Total | AN37: =SUM(AN5:AN36) -> 395.03 | AO37: =SUM(AO5:AO36) -> 309.35 | AP37: =SUM(AP5:AP36) -> 6.51 | AQ37: =IF(AN37=0,"",AN37/AO37) -> 1.2769678 | AR37: =IF(AN37=0,"",(AD37/AN37)/1000) -> 5.0501025 | AS37: =IF(AN37=0,"",AR37*24) -> 121.20246 | AT37: =IF(AN37=0,"",AD45/(AS37*26)) -> 0.6330609 | AU37: =IF(AN37=0,"",(AE37/AN37)) -> 78.11189 | AV37: =IF(AO37=0,"",(AD37/AO37)/1000) -> 6.4488185 | AW37: =SUM(AW5:AW36)/1000 -> 0 | AX37: =SUM(AX5:AX36)/1000 -> 2031.488 | AY37: =SUM(AY5:AY36)/1000 -> 1577.712 | AZ37: =SUM(AZ5) -> 68862 | BA37: =SUM(BA5:BA36) -> 1632 | BB37: =SUM(BB5:BB36) -> 374982 | BC37: =SUM(BC5:BC36)/1000 -> 1540.192 | BD37: =SUM(BD5:BD36)/1000 -> 1.476 | BE37: =SUM(BE5:BE36)/1000 -> 431.952 | BF37: =SUM(BF5:BF36)/1000 -> 245.848
C38: =+SUM(C12:C14) -> 505 | D38: =+SUM(D12:D14) -> 0 | E38: =+SUM(E12:E14) -> 0 | F38: =SUM(F16:F21) -> 773 | G38: =SUM(G16:G21) -> 800 | I38: =+SUM(I12:I35) -> 826 | J38: =+SUM(J12:J35) -> 120 | R38: =SUM(R11:R13) -> 104288
C39: =+SUM(C15:C21) -> 6275 | D39: =+SUM(D15:D21) -> 0 | E39: =+SUM(E15:E21) -> 0 | R39: =+SUM(R14) -> 100080
R40: =+SUM(R15:R18) -> 60880
R41: =+SUM(R19:R35) -> 44224
B42: Promedio | C42: =IF(C37=0,"",AVERAGE(C5:C36)) -> 1018.9 | D42: =IF(D37=0,"",AVERAGE(D5:D36)) -> 624 | E42: =IF(E37=0,"",AVERAGE(E5:E36)) | F42: =IF(F37=0,"",AVERAGE(F5:F36)) -> 253.6 | G42: =IF(G37=0,"",AVERAGE(G5:G36)) -> 245.5 | H42: =IF(H37=0,"",AVERAGE(H5:H36)) -> 377.5 | I42: =IF(I37=0,"",AVERAGE(I5:I36)) -> 688.25 | J42: =IF(J37=0,"",AVERAGE(J5:J36)) -> 100 | K42: =IF(K37=0,"",AVERAGE(K5:K36)) -> 746 | N42: =IF(N37=0,"",AVERAGE(N5:N36)) | O42: =IF(O37=0,"",AVERAGE(O5:O36)) | P42: =IF(P37=0,"",AVERAGE(P5:P36)) | Q42: =IF(Q37=0,"",AVERAGE(Q5:Q36)) -> 132.5 | R42: =IF(R37=0,"",AVERAGE(R5:R36)) -> 48885.455 | S42: =IF(S37=0,"",AVERAGE(S5:S36)) -> 31453.667 | T42: =IF(T37=0,"",AVERAGE(T5:T36)) -> 20640 | U42: =IF(U37=0,"",AVERAGE(U5:U36)) -> 200 | ... Y42: =IF(Y37=0,"",AVERAGE(Y5:Y36)) -> 17 | Z42: 354 | AA42: =IF(AA37=0,"",AVERAGE(AA5:AA36)) -> 180.88235 | AB42: =IF(AB37=0,"",AVERAGE(AB5:AB36)) -> 397.11765 | AC42: =IF(AC37=0,"",AVERAGE(AC5:AC36)) -> 109.70588 | AM42: Promedio | AN42: =IF(AN37=0,"",AVERAGE(AN5:AN36)) -> 23.237059 | AO42: =IF(AO37=0,"",AVERAGE(AO5:AO36)) -> 18.197059 | AP42: =IF(AP37=0,"",AVERAGE(AP5:AP36)) -> 0.38294118 | AQ42: =IF(AQ37="","",AVERAGE(AQ5:AQ36)) -> 1.3233479 | AR42: =IF(AR37="","",AVERAGE(AR5:AR36)) -> 5.0578881 | AS42: =IF(AS37="","",AVERAGE(AS5:AS36)) -> 121.38931 | AT42: =IF(AT37="","",AVERAGE(AT5:AT36)) -> 0.96821078 | AU42: =IF(AU37="","",AVERAGE(AU5:AU36)) -> 78.221822 | AV42: =IF(AV37="","",AVERAGE(AV5:AV36)) -> 6.6544597
B43: Cambio de Mezcla | AD43: Total Kg.
AE44: Total Tm.
B45: Total | C45: =SUM(C5:C36) -> 10189 | D45: =SUM(D5:D36) -> 1248 | E45: =SUM(E5:E36) -> 0 | F45: =SUM(F5:F36) -> 1268 | G45: =SUM(G5:G36) -> 982 | H45: =SUM(H5:H36) -> 755 | I45: =SUM(I5:I36) -> 2753 | J45: =SUM(J5:J36) -> 200 | ... AC45: =SUM(AC5:AC36) -> 1865 | AD45: =AD37/1000 -> 1994.942
A47: Grano entero | Z47: 378 | AD47: =(Z47+AA47)*25.8 -> 9752.4 | AF47: =IF(B47="","",((AE47*25)/AD47)) | AG47: =IF(B47="","",((Z47)*25)/AD47) | AH47: =IF(B47="","",(X47*25)/AD47) | AI47: =IF(B47="","",(Y47*25)/AD47) | AJ47: =IF(B47="","",(AA47*25)/AD47) | AK47: =IF(B47="","",(AB47*40)/AD47) | AL47: =IF(B47="","",(AC47*50)/AD47) | AM47: =IF(B47="","",B47) | AQ47: =IF(AN47="","",AN47/AO47) | AR47: =IF(AN47="","",(AD47/AN47)/1000) | AS47: =IF(AN47="","",AR47*24) | AT47: =IF(AN47="","",(AD47/1000)*100%/AS47) | AU47: =IF(AN47="","",(AE47/AN47)) | AV47: =IF(AN47="","",(AD47/AO47)/1000)
A48: Bio Convercion | AD48: =(Z48*25)+(AA48*25)+(AB48*40)+(AC48*50) -> 0 | AE48: =IF(B48="","",C48+E48+G48+K48+N48+O48+Q48+R48+((D48+H48)/4)+((F48+I48+J48+T48+Z48)/2)) | AF48: =IF(B48="","",((AE48*50)/AD48)) | AG48: =IF(B48="","",((Z48)*25)/AD48) | AH48: =IF(B48="","",(X48*25)/AD48) | AI48: =IF(B48="","",(Y48*25)/AD48) | AJ48: =IF(B48="","",(AA48*25)/AD48) | AK48: =IF(B48="","",(AB48*40)/AD48) | AL48: =IF(B48="","",(AC48*50)/AD48) | AM48: =IF(B48="","",B48) | AQ48: =IF(AN48="","",AN48/AO48) | AR48: =IF(AN48="","",(AD48/AN48)/1000) | AS48: =IF(AN48="","",AR48*24) | AT48: =IF(AN48="","",(AD48/1000)*100%/AS48) | AU48: =IF(AN48="","",(AE48/AN48)) | AV48: =IF(AN48="","",(AD48/AO48)/1000)
A49: Kamut | AD49: =Z49*25 -> 0 | AE49: =IF(B49="","",C49+E49+G49+K49+N49+O49+Q49+R49+((D49+H49)/4)+((F49+I49+J49+T49)/2)) | AF49: =IF(B49="","",((AE49*50)/AD49)) | AG49: =IF(B49="","",((Z49)*25)/AD49) | AH49: =IF(B49="","",(X49*25)/AD49) | AI49: =IF(B49="","",(Y49*25)/AD49) | AJ49: =IF(B49="","",(AA49*25)/AD49) | AK49: =IF(B49="","",(AB49*40)/AD49) | AL49: =IF(B49="","",(AC49*50)/AD49) | AM49: =IF(B49="","",B49) | AQ49: =IF(AN49="","",AN49/AO49) | AR49: =IF(AN49="","",(AD49/AN49)/1000) | AS49: =IF(AN49="","",AR49*24) | AT49: =IF(AN49="","",(AD49/1000)*100%/AS49) | AU49: =IF(AN49="","",(AE49/AN49)) | AV49: =IF(AN49="","",(AD49/AO49)/1000)
A50: Trigo entero | Z50: 200 | AD50: =(Z50+AA50)*25.275 -> 5055 | AE50: =IF(B50="","",C50+E50+G50+K50+N50+O50+Q50+R50+((D50+H50)/4)+((F50+I50+J50+T50)/2)) | AF50: =IF(B50="","",((AE50*50)/AD50)) | AG50: =IF(B50="","",((Z50)*25)/AD50) | AH50: =IF(B50="","",(X50*25)/AD50) | AI50: =IF(B50="","",(Y50*25)/AD50) | AJ50: =IF(B50="","",(AA50*25)/AD50) | AK50: =IF(B50="","",(AB50*40)/AD50) | AL50: =IF(B50="","",(AC50*50)/AD50) | AM50: =IF(B50="","",B50) | AQ50: =IF(AN50="","",AN50/AO50) | AR50: =IF(AN50="","",(AD50/AN50)/1000) | AS50: =IF(AN50="","",AR50*24) | AT50: =IF(AN50="","",(AD50/1000)*100%/AS50) | AU50: =IF(AN50="","",(AE50/AN50)) | AV50: =IF(AN50="","",(AD50/AO50)/1000)
AD51: =SUM(AD47:AD50) -> 14807.4 | AX51: =AX47/1000 -> 0
AD52: Total Kg. | AF52: Total Tm.
I53: 3.6 | AD53: =AD51/1000 -> 14.8074 | AF53: =+AD53+AD37/1000 -> 2009.7494
A54: Produccion | C54: % rendimiento | F54: Energia | I54: ART | K54: PEDIDO PUERTO | N54: SAP | O54: Inicial | R54: CONSUMOS | V54: FINAL
A55: tm trigo: | B55: =AD45+AD53 -> 2009.7494 | F55: Precio Kw: | H55: =IF(G58="",0,G61/G58) -> 0 | I55: =IF(I58="",0,I61/I58) -> 0 | K55: 2753 | M55: =IF(K55=0,"",+K55/$K$60) -> 0.7075302 | N55: 1214 | O55: 1214 | Q55: =+IF(O55=0,"",O55/$O$60) -> 0.65198711 | R55: =D85 -> CWRS | S55: =+SUMPRODUCT(B87:B123,D87:D123) -> 1434.2254 | U55: =+IF(S55=0,"",S55/$S$60) -> 0.71364814 | V55: =+K55+O55-S55 -> 2532.7746 | X55: =+IF(V55=0,"",V55/$V$60) -> 0.67661715
A56: Blt harina: | B56: =AE37 -> 30856.54 | C56: =B55/(B65*120) -> 1.0467445 | F56: Kw/tm trigo: | H56: =IF(G58="",0,G58/B55) -> 0 | K56: 0 | M56: =IF(K56=0,"",+K56/$K$60) | N56: 0 | O56: 0 | Q56: =+IF(O56=0,"",O56/$O$60) | R56: =IF(E85="","",E85) -> CPS | S56: =SUMPRODUCT(B87:B123,E87:E123) -> 0 | U56: =+IF(S56=0,"",S56/$S$60) | V56: =K56+O56-S56 -> 0 | X56: =+IF(V56=0,"",V56/$V$60)
A57: Tm harina: | B57: =(B56*50)/1000 -> 1542.827 | F57: Kw/tm harina: | H57: =IF(G58="",0,G58/((B56*50)/1000)) -> 0 | K57: 765 | M57: =IF(K57=0,"",+K57/$K$60) -> 0.19660756 | N57: 18 | O57: 18 | Q57: =+IF(O57=0,"",O57/$O$60) -> 0.0096670247 | R57: HRW | S57: =SUMPRODUCT(B87:B123,G87:G123) -> 194.51603 | U57: =+IF(S57=0,"",S57/$S$60) -> 0.096788139 | V57: =K57+O57-S57 -> 588.48397 | X57: =+IF(V57=0,"",V57/$V$60) -> 0.15721033
A58: Extraccion: | B58: =IF(AF37="",0,AF37) -> 0.77336935 | F58: KW: | K58: 373 | M58: =IF(K58=0,"",+K58/$K$60) -> 0.095862246 | N58: 630 | O58: 630 | Q58: =+IF(O58=0,"",O58/$O$60) -> 0.33834586 | R58: SRW | S58: =SUMPRODUCT(B87:B123,F87:F123) -> 380.96799 | U58: =+IF(S58=0,"",S58/$S$60) -> 0.18956372 | V58: =K58+O58-S58 -> 622.03201 | X58: =+IF(V58=0,"",V58/$V$60) -> 0.16617251
A59: Hrs molienda: | B59: =AN37 -> 395.03 | F59: KVAR: | K59: 0 | M59: =IF(K59=0,"",+K59/$K$60) | O59: 0 | Q59: =+IF(O59=0,"",O59/$O$60) | R59: BIO | S59: =IF(AD48="",0,AD48) -> 0 | U59: =+IF(S59=0,"",S59/$S$60) | V59: =K59+O59-S59 -> 0 | X59: =+IF(V59=0,"",V59/$V$60) | AC59: =+S60-AF53 -> -0.04
A60: Hrs varada: | B60: =IF(B55=0,0,AP37/AN37) -> 0.016479761 | F60: Reactiva: | K60: =SUM(K55:K59) -> 3891 | N60: =SUM(N55:N59) -> 1862 | O60: =SUM(O55:O59) -> 1862 | S60: =SUM(S55:T59) -> 2009.7094 | V60: =SUM(V55:V59) -> 3743.2906
A61: % dia utilizado: | B61: =AT42 -> 0.96821078 | F61: Precio:
A62: Capacidad utilizada: | B62: =+AT37 -> 0.6330609 | F62: Hz neumatico: | H62: 60 | K62: Basculas
A63: Capacidad: | B63: =IF(AS37="",0,AS37) -> 121.20246 | K63: Tm Trigo T1: | M63: =AX37 -> 2031.488 | O63: tm
A64: Bultos hora: | B64: =IF(AU37="",0,AU37) -> 78.11189 | F64: Granza: | G64: 12333 | H64: kg. | K64: Bascula Harina: | M64: =AY37 -> 1577.712 | O64: tm
A65: Dias molienda: | B65: =31-COUNTBLANK(A5:A36) -> 16 | F65: % | G65: =G64/(B55*1000) -> 0.006136586 | K65: Extraccion: | M65: =M64/M63 -> 0.77662876 | T65: MYCE | Y65: AA | Z65: Granozyme | AA65: 900 | AB65: Alfa | AC65: 7200 | AD65: 4200
A66: Total Ton de trig: | B66: =AD45+AD53 -> 2009.7494 | G66: grf | T66: TRIGO | X66: =C87 -> Extrapan 50 | Y66: 10 | Z66: 3 | AA66: 2.5 | AB66: 3 | AC66: 7 | AD66: 2
A67: Ton. molidas/persona: | B67: =B55/B72 -> 80.389976 | F67: Energia M.martillo | K67: Energia C.granel | T67: AGUA m3 | U67: =AZ5 -> 68862 | X67: =C91 -> Extrapan 25 | Y67: =+Y66/2 -> 5 | Z67: =+Z66/2 -> 1.5 | AA67: =+AA66/2 -> 1.25 | AB67: =+AB66/2 -> 1.5 | AC67: =+AC66/2 -> 3.5 | AD67: =+AD66/2 -> 1
A68: Valor tonelada/nomina: | B68: =B80/B55 -> 31875.733 | F68: Ton Molidas | H68: 20 | K68: Ton despachadas | O68: =+(R45+S45+T45)/1000 -> 747.102 | X68: =C95 -> Extrapan 10 | Y68: =+Y66/5 -> 2 | Z68: =+Z66/5 -> 0.6 | AA68: =+AA66/5 -> 0.5 | AB68: =+AB66/5 -> 0.6 | AC68: =+AC66/5 -> 1.4 | AD68: =+AD66/5 -> 0.4
A69: Valor ton/Horas extras: | B69: =B81/B55 -> 3899.7061 | F69: Tiempo de cargue | H69: =(H68*1)*2 -> 40 | K69: Tiempo de cargue | O69: 40.18 | T69: Flowbalancer | X69: =C96 -> Artesanal 50 | Y69: 10 | Z69: 3 | AA69: 0 | AB69: 6 | AC69: 7 | AD69: 0
F70: TRIGO | K70: HARINA | T70: CRWS | U70: =+BC37+BD37 -> 1541.668 | X70: =C107 -> Exclusiva 25 | Y70: 0 | Z70: 0 | AA70: 0 | AB70: 0 | AC70: 0 | AD70: 0
A71: Datos Generales | F71: HRW | K71: SRW | T71: CPS / HRW | U71: =+BF37 -> 245.848 | X71: =C109 -> Harina de alta proteina x 1 G | Y71: 0 | Z71: 0 | AA71: 0 | AB71: 0 | AC71: 0 | AD71: 0
A72: Personal de planta | B72: 25 | F72: AMP | G72: 50 | H72: =H69*G72 -> 2000 | K72: AMP | L72: 100 | M72: =(O69*L72) -> 4018 | T72: SRW | U72: =+BE37 -> 431.952 | X72: Total | Y72: =+SUM(Y66:Y71) -> 27 | Z72: =+SUM(Z66:Z71) -> 8.1 | AA72: =+SUM(AA66:AA71) -> 4.25 | AB72: =+SUM(AB66:AB71) -> 11.1 | AC72: =+SUM(AC66:AC71) -> 18.9 | AD72: =+SUM(AD66:AD71) -> 3.4
A73: Cuota de ventas | B73: 28760 | F73: KW/H | G73: =(G72*436*1.7321*0.96)/1000 -> 36.249389 | H73: =(H72*436*1.7321*0.96)/1000 -> 1449.9756 | K73: KW/H | L73: =(L72*436*1.7321*0.96)/1000 -> 72.498778 | T73: OTROS | U73: 0 | X73: Fisico
A74: Ventas reales | B74: 36087 | F74: KW Total | G74: =G73*H68 -> 724.98778 | K74: KW Total | M74: =L73*O69 -> 2913.0009
A75: % de cumplimiento Proy | B75: =+B56/B73 -> 1.0728978 | F75: Precio Kw: | H75: =G74*H55 -> 0 | K75: Precio Kw: | M75: =M74*H55 -> 0 | T75: VALOR X HORA DE VARADA
A76: % de cumplimiento Real | B76: =+B56/B74 -> 0.85505972 | T76: Mob | V76: =AP37*(U76+U77) -> 0 | Y76: Vitamina | Z76: COP | AA76: EXP
T77: Cif | Y77: gr/blt | Z77: 12.5 | AA77: 13.5 | AC77: gr/blt
Y78: Total | Z78: =SUM(A87+A90+A91+A94+A96+A99+A101+A105+A107+A109+A110+A115+A112+A117+A120+A122+A116+A88+A89+A97+A95+A98+A103+A104+A111+A113+A118)*Z77 -> 304407.5 | AA78: =(A102+A106)*AA77 -> 23078.25 | AC78: gr.
A79: Datos Nomina Producción | Y79: Fisico | AC79: gr.
A80: Nomina | B80: 64062235
A81: Horas extras | B81: 7837432
D85: CWRS | E85: CPS | F85: SRW | G85: HRW
A86: Harina | B86: trigo | C86: Codigo | D86: % | E86: % | F86: % | G86: %
A87: =C37 -> 3409 | B87: =IF(A87=0,0,A87*50/$B$58)/1000 -> 220.39922 | C87: Extrapan 50 | D87: 0.85 | E87: 0 | F87: 0.05 | G87: 0.1 | H87: =+SUM(D87:G87) -> 1
A88: =+C38 -> 505 | B88: =IF(A88=0,0,A88*50/$B$58)/1000 -> 32.649341 | C88: Extrapan 50 | D88: 0.85 | E88: 0 | F88: 0 | G88: 0.15 | H88: =+SUM(D88:G88) -> 1 | I88: 46041
A89: =C39 -> 6275 | B89: =IF(A89=0,0,A89*50/$B$58)/1000 -> 405.69231 | C89: Extrapan 50 | D89: 0.8 | E89: 0 | F89: 0 | G89: 0.2 | H89: =+SUM(D89:G89) -> 1 | I89: 46050
A90: =D37/2 -> 624 | B90: =IF(A90=0,0,A90*50/$B$58)/1000 -> 40.342949 | C90: Extrapan 25 | D90: 0.85 | E90: 0 | F90: 0.05 | G90: 0.1 | H90: =+SUM(D90:G90) -> 1
A91: =D38/2 -> 0 | B91: =IF(A91=0,0,A91*50/$B$58)/1000 -> 0 | C91: Extrapan 25 | D91: 0.85 | E91: 0 | F91: 0 | G91: 0.15 | H91: =+SUM(D91:G91) -> 1 | I91: 46041
A92: =D39/2 -> 0 | B92: =IF(A92=0,0,A92*50/$B$58)/1000 -> 0 | C92: Extrapan 25 | D92: 0.8 | E92: 0 | F92: 0 | G92: 0.2 | H92: =+SUM(D92:G92) -> 1 | I92: 46050
A93: =+E37/5 -> 0 | B93: =IF(A93=0,0,A93*50/$B$58)/1000 -> 0 | C93: Extrapan 10 | D93: 0.85 | E93: 0 | F93: 0.05 | G93: 0.1 | H93: =+SUM(D93:G93) -> 1
A94: =E38/5 -> 0 | B94: =IF(A94=0,0,A94*50/$B$58)/1000 -> 0 | C94: Extrapan 10 | D94: 0.85 | E94: 0 | F94: 0 | G94: 0.15 | H94: =+SUM(D94:G94) -> 1 | I94: 46041
A95: =E39/5 -> 0 | B95: =IF(A95=0,0,A95*50/$B$58)/1000 -> 0 | C95: Extrapan 10 | D95: 0.8 | E95: 0 | F95: 0 | G95: 0.2 | H95: =+SUM(D95:G95) -> 1 | I95: 46050
A96: =F37 -> 495 | B96: =IF(A96=0,0,A96*50/$B$58)/1000 -> 32.00282 | C96: =F4 -> Artesanal 50 | D96: 0.75 | E96: 0 | F96: 0.25 | G96: 0 | H96: =+SUM(D96:G96) -> 1 | I96: 46028
A97: =F38 -> 773 | B97: =IF(A97=0,0,A97*50/$B$58)/1000 -> 49.976121 | C97: Artesanal 50 | D97: 0.52 | E97: 0 | F97: 0.25 | G97: 0.23 | H97: =+SUM(D97:G97) -> 1 | I97: 46043
A98: =G37/2 -> 91 | B98: =IF(A98=0,0,A98*50/$B$58)/1000 -> 5.8833467 | C98: Artesanal 25 | D98: 0.75 | E98: 0 | F98: 0.25 | G98: 0 | H98: 1 | I98: 46028
A99: =G38/2 -> 400 | B99: =IF(A99=0,0,A99*50/$B$58)/1000 -> 25.860865 | C99: Artesanal 25 | D99: 0.52 | E99: 0 | F99: 0.25 | G99: 0.23 | H99: 1 | I99: 46043
A100: =+H37 -> 755 | B100: =IF(A100=0,0,A100*50/$B$58)/1000 -> 48.812382 | C100: =H4 -> Natural 50 | D100: 0.63 | E100: 0 | F100: 0.23 | G100: 0.14 | H100: =+SUM(D100:G100) -> 1
B101: =IF(A101=0,0,A101*50/$B$58)/1000 -> 0
A102: =I37/2 -> 963.5 | B102: =IF(A102=0,0,A102*50/$B$58)/1000 -> 62.292357 | C102: =I4 -> Fuerte 25 | D102: 0.75 | E102: 0 | F102: 0.25 | G102: 0 | H102: =+SUM(D102:G102) -> 1 | I102: 46027
A103: =J37/2 -> 40 | B103: =IF(A103=0,0,A103*50/$B$58)/1000 -> 2.5860865 | C103: =J4 -> Fuerte exp 25 | D103: 0.75 | E103: 0 | F103: 0.25 | G103: 0 | H103: =+SUM(D103:G103) -> 1
A104: =I38/2 -> 413 | B104: =IF(A104=0,0,A104*50/$B$58)/1000 -> 26.701343 | C104: Fuerte 25 | D104: 0.52 | E104: 0 | F104: 0.23 | G104: 0.25 | H104: =+SUM(D104:G104) -> 1 | I104: 46035
...

Sheet FEB
B1: Producción | AH1: Extracción | AN1: Indicadores
B2: HARINA EN BULTO | R2: HARINA GRANEL | U2: P. EXP | V2: REPASO | X2: ESPECIAL | AA2: SUBPRODUCTO | AF2: EXTRACION | AN2: HORAS | AQ2: INDICACORES MOLINO | AV2: MOJADORA | AW2: EQUIPOS ELECTRONICOS
A3: Dia | B3: Fecha | C3: Extrapan 50 | D3: Extrapan 25 | E3: Extrapan 10 | F3: Artesanal 50 | G3: Artesanal 25 | H3: Natural 50 | I3: Fuerte 25 | J3: Fuerte exp 25 | K3: Exclusiva 50 | L3: Exclusiva 25 | M3: S. Sal 25 | N3: Harina Tortas y Ponques | O3: Harina Galeras Ligera | P3: H. Manitova | Q3: ESPECIAL 50 | R3: Harina de alta proteina x 1 G | S3: Harina de baja proteina x 1 | T3: ARTESANAL X 1 G | U3: H. espcial x 25 | V3: + Repaso | W3: - Reproceso | X3: Germen 25 | Y3: Semola 25 | Z3: Grano entero 25 | AA3: Salvado 25 | AB3: Mogolla 40 | AC3: Segunda 50 | AD3: Total trigo | AE3: Total Bultos | AF3: Harina | AG3: Grano entero partido | AH3: =X3 -> Germen 25 | AI3: Semola | AJ3: =AA3 -> Salvado 25 | AK3: =AB3 -> Mogolla 40 | AL3: =AC3 -> Segunda 50 | AM3: =B3 -> Fecha | AN3: Molienda | AO3: moje | AP3: Horas varada | AQ3: Molido/ Mojado | AR3: Capacidad TM. hora | AS3: Capacidad TM. Día | AT3: % Utilizado | AU3: Bultos Hora | AV3: capacidad TM. hora | AW3: MYFC | AX3: Bascula Trigo | AY3: Bascula Harina | AZ3: Agua M³ | BA3: Bascula Mejorante A | BB3: Bascula Mejorante B | BC3: Flowbalacer 1 | BD3: Flowbalacer 2 | BE3: Flowbalacer 3 | BF3: Flowbalacer 4
A4: =IF(B4="","",1) -> 1 | B4: 46055 | R4: 85416 | Y4: 20 | AA4: 155 | AB4: 327 | AC4: 129 | AD4: =IF(B4="","",(((C4+F4+H4+K4+Q4+N4+O4)*50))+((E4*10))+(((I4+J4+D4+G4+L4+M4+U4)*25)+(X4*25)+(Y4*25)+(Z4*25)+(AA4*25)+(AB4*40)+(AC4*50)+(R4*1)+(S4*1)+(T4*1))) -> 109321 | AE4: =IF(B4="","",C4+F4+H4+K4+Q4+N4+O4+((I4+J4+D4+G4)/2)+(R4/50)+(S4/50)+(T4/50)+(U4/2)+(E4/5)) -> 1708.32 | AF4: =IF(B4="","",((AE4*50)/AD4)) -> 0.78133204 | AG4: =IF(C4="","",((Z4)*25)/AD4) | AH4: =IF(B4="","",(X4*25)/AD4) -> 0 | AI4: =IF(B4="","",(Y4*25)/AD4) -> 0.0045736867 | AJ4: =IF(B4="","",(AA4*25)/AD4) -> 0.035446072 | AK4: =IF(B4="","",(AB4*40)/AD4) -> 0.11964764 | AL4: =IF(B4="","",(AC4*50)/AD4) -> 0.059000558 | AM4: =IF(B4="","",B4) -> 46055 | AN4: 24 | AO4: 16.62 | AP4: =24-AN4 -> 0 | AQ4: =IF(AN4="","",AN4/AO4) -> 1.4440433 | AR4: =IF(AN4="","",(AD4/AN4)/1000) -> 4.5550417 | AS4: =IF(AN4="","",AR4*24) -> 109.321 | AT4: =IF(AN4="","",(AD4/1000)*100%/AS4) -> 1 | AU4: =IF(AN4="","",(AE4/AN4)) -> 71.18 | AV4: =IF(AN4="","",(AD4/AO4)/1000) -> 6.5776775 | AX4: 2373408 | AY4: 1837104 | AZ4: 69185 | BA4: 580 | BB4: 354434 | BC4: 123963750 | BD4: 5884169 | BE4: 39502680 | BF4: 47025740
A5: =IF(B5="","",1+A4) -> 2 | B5: 46056 | C5: 1009 | I5: 882 | J5: 80 | R5: 16192 | AA5: 153 | AB5: 381 | AC5: 64 | AD5: =IF(B5="","",(((C5+F5+H5+K5+Q5+N5+O5)*50))+((E5*10))+(((I5+J5+D5+G5+L5+M5+U5)*25)+(X5*25)+(Y5*25)+(Z5*25)+(AA5*25)+(AB5*40)+(AC5*50)+(R5*1)+(S5*1)+(T5*1))) -> 112957 | AE5: =IF(B5="","",C5+F5+H5+K5+Q5+N5+O5+((I5+J5+D5+G5)/2)+(R5/50)+(S5/50)+(T5/50)+(U5/2)+(E5/5)) -> 1813.84 | AF5: =IF(B5="","",((AE5*50)/AD5)) -> 0.8028896 | AG5: =IF(C5="","",((Z5)*25)/AD5) -> 0 | AH5: =IF(B5="","",(X5*25)/AD5) -> 0 | AI5: =IF(B5="","",(Y5*25)/AD5) -> 0 | AJ5: =IF(B5="","",(AA5*25)/AD5) -> 0.033862443 | AK5: =IF(B5="","",(AB5*40)/AD5) -> 0.1349186 | AL5: =IF(B5="","",(AC5*50)/AD5) -> 0.028329364 | AM5: =IF(B5="","",B5) -> 46056 | AN5: 23.75 | AO5: 19.12 | AP5: =24-AN5 -> 0.25 | AQ5: =IF(AN5="","",AN5/AO5) -> 1.2421548 | AR5: =IF(AN5="","",(AD5/AN5)/1000) -> 4.7560842 | AS5: =IF(AN5="","",AR5*24) -> 114.14602 | AT5: =IF(AN5="","",(AD5/1000)*100%/AS5) -> 0.98958333 | AU5: =IF(AN5="","",(AE5/AN5)) -> 76.372211 | AV5: =IF(AN5="","",(AD5/AO5)/1000) -> 5.9077929
A6: =IF(B6="","",1+A5) -> 3 | B6: 46057 | C6: 720 | D6: 1542 | E6: 199 | R6: 14128 | AA6: 172 | AB6: 439 | AC6: 49 | AD6: =IF(B6="","",(((C6+F6+H6+K6+Q6+N6+O6)*50))+((E6*10))+(((I6+J6+D6+G6+L6+M6+U6)*25)+(X6*25)+(Y6*25)+(Z6*25)+(AA6*25)+(AB6*40)+(AC6*50)+(R6*1)+(S6*1)+(T6*1))) -> 114978 | AE6: =IF(B6="","",C6+F6+H6+K6+Q6+N6+O6+((I6+J6+D6+G6)/2)+(R6/50)+(S6/50)+(T6/50)+(U6/2)+(E6/5)) -> 1813.36 | AF6: =IF(B6="","",((AE6*50)/AD6)) -> 0.78856825 | AG6: =IF(C6="","",((Z6)*25)/AD6) -> 0 | AH6: =IF(B6="","",(X6*25)/AD6) -> 0 | AI6: =IF(B6="","",(Y6*25)/AD6) -> 0 | AJ6: =IF(B6="","",(AA6*25)/AD6) -> 0.037398459 | AK6: =IF(B6="","",(AB6*40)/AD6) -> 0.15272487 | AL6: =IF(B6="","",(AC6*50)/AD6) -> 0.021308424 | AM6: =IF(B6="","",B6) -> 46057 | AN6: 23.41 | AO6: 14.48 | AP6: =24-AN6 -> 0.59 | AQ6: =IF(AN6="","",AN6/AO6) -> 1.6167127 | AR6: =IF(AN6="","",(AD6/AN6)/1000) -> 4.9114908 | AS6: =IF(AN6="","",AR6*24) -> 117.87578 | AT6: =IF(AN6="","",(AD6/1000)*100%/AS6) -> 0.97541667 | AU6: =IF(AN6="","",(AE6/AN6)) -> 77.460914 | AV6: =IF(AN6="","",(AD6/AO6)/1000) -> 7.9404696
A7: =IF(B7="","",1+A6) -> 4 | B7: 46058 | F7: 490 | H7: 513 | R7: 12144 | S7: 24880 | U7: 200 | AA7: 111 | AB7: 432 | AC7: 159 | AD7: =IF(B7="","",(((C7+F7+H7+K7+Q7+N7+O7)*50))+((E7*10))+(((I7+J7+D7+G7+L7+M7+U7)*25)+(X7*25)+(Y7*25)+(Z7*25)+(AA7*25)+(AB7*40)+(AC7*50)+(R7*1)+(S7*1)+(T7*1))) -> 120179 | AE7: =IF(B7="","",C7+F7+H7+K7+Q7+N7+O7+((I7+J7+D7+G7)/2)+(R7/50)+(S7/50)+(T7/50)+(U7/2)+(E7/5)) -> 1843.48 | AF7: =IF(B7="","",((AE7*50)/AD7)) -> 0.7669726 | AG7: =IF(C7="","",((Z7)*25)/AD7) | AH7: =IF(B7="","",(X7*25)/AD7) -> 0 | AI7: =IF(B7="","",(Y7*25)/AD7) -> 0 | AJ7: =IF(B7="","",(AA7*25)/AD7) -> 0.023090557 | AK7: =IF(B7="","",(AB7*40)/AD7) -> 0.14378552 | AL7: =IF(B7="","",(AC7*50)/AD7) -> 0.066151324 | AM7: =IF(B7="","",B7) -> 46058 | AN7: 24 | AO7: 18.87 | AP7: =24-AN7 -> 0 | AQ7: =IF(AN7="","",AN7/AO7) -> 1.2718601 | AR7: =IF(AN7="","",(AD7/AN7)/1000) -> 5.0074583 | AS7: =IF(AN7="","",AR7*24) -> 120.179 | AT7: =IF(AN7="","",(AD7/1000)*100%/AS7) -> 1 | AU7: =IF(AN7="","",(AE7/AN7)) -> 76.811667 | AV7: =IF(AN7="","",(AD7/AO7)/1000) -> 6.3687864
A8: =IF(B8="","",1+A7) -> 5 | B8: 46059 | R8: 73336 | AA8: 174 | AB8: 329 | AC8: 144 | AD8: =IF(B8="","",(((C8+F8+H8+K8+Q8+N8+O8)*50))+((E8*10))+(((I8+J8+D8+G8+L8+M8+U8)*25)+(X8*25)+(Y8*25)+(Z8*25)+(AA8*25)+(AB8*40)+(AC8*50)+(R8*1)+(S8*1)+(T8*1))) -> 98046 | AE8: =IF(B8="","",C8+F8+H8+K8+Q8+N8+O8+((I8+J8+D8+G8)/2)+(R8/50)+(S8/50)+(T8/50)+(U8/2)+(E8/5)) -> 1466.72 | AF8: =IF(B8="","",((AE8*50)/AD8)) -> 0.74797544 | AG8: =IF(C8="","",((Z8)*25)/AD8) | AH8: =IF(B8="","",(X8*25)/AD8) -> 0 | AI8: =IF(B8="","",(Y8*25)/AD8) -> 0 | AJ8: =IF(B8="","",(AA8*25)/AD8) -> 0.04436693 | AK8: =IF(B8="","",(AB8*40)/AD8) -> 0.13422271 | AL8: =IF(B8="","",(AC8*50)/AD8) -> 0.073434918 | AM8: =IF(B8="","",B8) -> 46059 | AN8: 22.25 | AO8: =4.48+9.25 -> 13.73 | AP8: =24-AN8 -> 1.75 | AQ8: =IF(AN8="","",AN8/AO8) -> 1.620539 | AR8: =IF(AN8="","",(AD8/AN8)/1000) -> 4.4065618 | AS8: =IF(AN8="","",AR8*24) -> 105.75748 | AT8: =IF(AN8="","",(AD8/1000)*100%/AS8) -> 0.92708333 | AU8: =IF(AN8="","",(AE8/AN8)) -> 65.92 | AV8: =IF(AN8="","",(AD8/AO8)/1000) -> 7.1410051
A9: =IF(B9="","",1+A8) -> 6 | B9: 46062 | C9: =281+30 -> 311 | G9: 161 | I9: =92+1248+35+161+415 -> 1951 | T9: 20360 | AA9: =44+30+18+75 -> 167 | AB9: =103+40+67+145 -> 355 | AC9: 12 | AD9: =IF(B9="","",(((C9+F9+H9+K9+Q9+N9+O9)*50))+((E9*10))+(((I9+J9+D9+G9+L9+M9+U9)*25)+(X9*25)+(Y9*25)+(Z9*25)+(AA9*25)+(AB9*40)+(AC9*50)+(R9*1)+(S9*1)+(T9*1))) -> 107685 | AE9: =IF(B9="","",C9+F9+H9+K9+Q9+N9+O9+((I9+J9+D9+G9)/2)+(R9/50)+(S9/50)+(T9/50)+(U9/2)+(E9/5)) -> 1774.2 | AF9: =IF(B9="","",((AE9*50)/AD9)) -> 0.82379161 | AG9: =IF(C9="","",((Z9)*25)/AD9) -> 0 | AH9: =IF(B9="","",(X9*25)/AD9) -> 0 | AI9: =IF(B9="","",(Y9*25)/AD9) -> 0 | AJ9: =IF(B9="","",(AA9*25)/AD9) -> 0.038770488 | AK9: =IF(B9="","",(AB9*40)/AD9) -> 0.13186609 | AL9: =IF(B9="","",(AC9*50)/AD9) -> 0.0055718067 | AM9: =IF(B9="","",B9) -> 46062 | AN9: 24 | AO9: 15.77 | AP9: =24-AN9 -> 0 | AQ9: =IF(AN9="","",AN9/AO9) -> 1.521877 | AR9: =IF(AN9="","",(AD9/AN9)/1000) -> 4.486875 | AS9: =IF(AN9="","",AR9*24) -> 107.685 | AT9: =IF(AN9="","",(AD9/1000)*100%/AS9) -> 1 | AU9: =IF(AN9="","",(AE9/AN9)) -> 73.925 | AV9: =IF(AN9="","",(AD9/AO9)/1000) -> 6.8284718
A10: =IF(B10="","",1+A9) -> 7 | B10: 46063 | C10: =86500/50 -> 1730 | Y10: =17+5+5 -> 27 | AA10: =44+50+59 -> 153 | AB10: =154*2+132 -> 440 | AC10: 70 | AD10: =IF(B10="","",(((C10+F10+H10+K10+Q10+N10+O10)*50))+((E10*10))+(((I10+J10+D10+G10+L10+M10+U10)*25)+(X10*25)+(Y10*25)+(Z10*25)+(AA10*25)+(AB10*40)+(AC10*50)+(R10*1)+(S10*1)+(T10*1))) -> 112100 | AE10: =IF(B10="","",C10+F10+H10+K10+Q10+N10+O10+((I10+J10+D10+G10)/2)+(R10/50)+(S10/50)+(T10/50)+(U10/2)+(E10/5)) -> 1730 | AF10: =IF(B10="","",((AE10*50)/AD10)) -> 0.77163247 | AG10: =IF(C10="","",((Z10)*25)/AD10) -> 0 | AH10: =IF(B10="","",(X10*25)/AD10) -> 0 | AI10: =IF(B10="","",(Y10*25)/AD10) -> 0.0060214095 | AJ10: =IF(B10="","",(AA10*25)/AD10) -> 0.03412132 | AK10: =IF(B10="","",(AB10*40)/AD10) -> 0.15700268 | AL10: =IF(B10="","",(AC10*50)/AD10) -> 0.031222123 | AM10: =IF(B10="","",B10) -> 46063 | AN10: 22.25 | AO10: 18.25 | AP10: =24-AN10 -> 1.75 | AQ10: =IF(AN10="","",AN10/AO10) -> 1.2191781 | AR10: =IF(AN10="","",(AD10/AN10)/1000) -> 5.0382022 | AS10: =IF(AN10="","",AR10*24) -> 120.91685 | AT10: =IF(AN10="","",(AD10/1000)*100%/AS10) -> 0.92708333 | AU10: =IF(AN10="","",(AE10/AN10)) -> 77.752809 | AV10: =IF(AN10="","",(AD10/AO10)/1000) -> 6.1424658
A11: =IF(B11="","",1+A10) -> 8 | B11: 46064 | C11: 1862 | AA11: 160 | AB11: 396 | AC11: 70 | AD11: =IF(B11="","",(((C11+F11+H11+K11+Q11+N11+O11)*50))+((E11*10))+(((I11+J11+D11+G11+L11+M11+U11)*25)+(X11*25)+(Y11*25)+(Z11*25)+(AA11*25)+(AB11*40)+(AC11*50)+(R11*1)+(S11*1)+(T11*1))) -> 116440 | AE11: =IF(B11="","",C11+F11+H11+K11+Q11+N11+O11+((I11+J11+D11+G11)/2)+(R11/50)+(S11/50)+(T11/50)+(U11/2)+(E11/5)) -> 1862 | AF11: =IF(B11="","",((AE11*50)/AD11)) -> 0.79955342 | AG11: =IF(C11="","",((Z11)*25)/AD11) -> 0 | AH11: =IF(B11="","",(X11*25)/AD11) -> 0 | AI11: =IF(B11="","",(Y11*25)/AD11) -> 0 | AJ11: =IF(B11="","",(AA11*25)/AD11) -> 0.034352456 | AK11: =IF(B11="","",(AB11*40)/AD11) -> 0.13603573 | AL11: =IF(B11="","",(AC11*50)/AD11) -> 0.030058399 | AM11: =IF(B11="","",B11) -> 46064 | AN11: 22.5 | AO11: 14.07 | AP11: =24-AN11 -> 1.5 | AQ11: =IF(AN11="","",AN11/AO11) -> 1.5991471 | AR11: =IF(AN11="","",(AD11/AN11)/1000) -> 5.1751111 | AS11: =IF(AN11="","",AR11*24) -> 124.20267 | AT11: =IF(AN11="","",(AD11/1000)*100%/AS11) -> 0.9375 | AU11: =IF(AN11="","",(AE11/AN11)) -> 82.755556 | AV11: =IF(AN11="","",(AD11/AO11)/1000) -> 8.275764
A12: =IF(B12="","",1+A11) -> 9 | B12: 46065 | C12: 149 | R12: 81024 | AA12: 172 | AB12: 385 | AC12: 196 | AD12: =IF(B12="","",(((C12+F12+H12+K12+Q12+N12+O12)*50))+((E12*10))+(((I12+J12+D12+G12+L12+M12+U12)*25)+(X12*25)+(Y12*25)+(Z12*25)+(AA12*25)+(AB12*40)+(AC12*50)+(R12*1)+(S12*1)+(T12*1))) -> 117974 | AE12: =IF(B12="","",C12+F12+H12+K12+Q12+N12+O12+((I12+J12+D12+G12)/2)+(R12/50)+(S12/50)+(T12/50)+(U12/2)+(E12/5)) -> 1769.48 | AF12: =IF(B12="","",((AE12*50)/AD12)) -> 0.7499449 | AG12: =IF(C12="","",((Z12)*25)/AD12) -> 0 | AH12: =IF(B12="","",(X12*25)/AD12) -> 0 | AI12: =IF(B12="","",(Y12*25)/AD12) -> 0 | AJ12: =IF(B12="","",(AA12*25)/AD12) -> 0.036448709 | AK12: =IF(B12="","",(AB12*40)/AD12) -> 0.13053724 | AL12: =IF(B12="","",(AC12*50)/AD12) -> 0.083069151 | AM12: =IF(B12="","",B12) -> 46065 | AN12: 23.3 | AO12: 22.3 | AP12: =24-AN12 -> 0.7 | AQ12: =IF(AN12="","",AN12/AO12) -> 1.044843 | AR12: =IF(AN12="","",(AD12/AN12)/1000) -> 5.0632618 | AS12: =IF(AN12="","",AR12*24) -> 121.51828 | AT12: =IF(AN12="","",(AD12/1000)*100%/AS12) -> 0.97083333 | AU12: =IF(AN12="","",(AE12/AN12)) -> 75.943348 | AV12: =IF(AN12="","",(AD12/AO12)/1000) -> 5.2903139
A13: =IF(B13="","",1+A12) -> 10 | B13: 46066 | R13: 82608 | AA13: 142 | AB13: 366 | AC13: 189 | AD13: =IF(B13="","",(((C13+F13+H13+K13+Q13+N13+O13)*50))+((E13*10))+(((I13+J13+D13+G13+L13+M13+U13)*25)+(X13*25)+(Y13*25)+(Z13*25)+(AA13*25)+(AB13*40)+(AC13*50)+(R13*1)+(S13*1)+(T13*1))) -> 110248 | AE13: =IF(B13="","",C13+F13+H13+K13+Q13+N13+O13+((I13+J13+D13+G13)/2)+(R13/50)+(S13/50)+(T13/50)+(U13/2)+(E13/5)) -> 1652.16 | AF13: =IF(B13="","",((AE13*50)/AD13)) -> 0.7492925 | AG13: =IF(C13="","",((Z13)*25)/AD13) | AH13: =IF(B13="","",(X13*25)/AD13) -> 0 | AI13: =IF(B13="","",(Y13*25)/AD13) -> 0 | AJ13: =IF(B13="","",(AA13*25)/AD13) -> 0.032200131 | AK13: =IF(B13="","",(AB13*40)/AD13) -> 0.13279152 | AL13: =IF(B13="","",(AC13*50)/AD13) -> 0.085715841 | AM13: =IF(B13="","",B13) -> 46066 | AN13: 24 | AO13: =8.43+10.14 -> 18.57 | AP13: =24-AN13 -> 0 | AQ13: =IF(AN13="","",AN13/AO13) -> 1.2924071 | AR13: =IF(AN13="","",(AD13/AN13)/1000) -> 4.5936667 | AS13: =IF(AN13="","",AR13*24) -> 110.248 | AT13: =IF(AN13="","",(AD13/1000)*100%/AS13) -> 1 | AU13: =IF(AN13="","",(AE13/AN13)) -> 68.84 | AV13: =IF(AN13="","",(AD13/AO13)/1000) -> 5.9368875
A14: =IF(B14="","",1+A13) -> 11 | B14: 46069 | R14: =50352+28912+2120+6592 -> 87976 | Y14: =15+23 -> 38 | AA14: =100+63+59 -> 222 | AB14: =150+80+131+125 -> 486 | AC14: =73+40 -> 113 | AD14: =IF(B14="","",(((C14+F14+H14+K14+Q14+N14+O14)*50))+((E14*10))+(((I14+J14+D14+G14+L14+M14+U14)*25)+(X14*25)+(Y14*25)+(Z14*25)+(AA14*25)+(AB14*40)+(AC14*50)+(R14*1)+(S14*1)+(T14*1))) -> 119566 | AE14: =IF(B14="","",C14+F14+H14+K14+Q14+N14+O14+((I14+J14+D14+G14)/2)+(R14/50)+(S14/50)+(T14/50)+(U14/2)+(E14/5)) -> 1759.52 | AF14: =IF(B14="","",((AE14*50)/AD14)) -> 0.73579446 | AG14: =IF(C14="","",((Z14)*25)/AD14) | AH14: =IF(B14="","",(X14*25)/AD14) -> 0 | AI14: =IF(B14="","",(Y14*25)/AD14) -> 0.0079454025 | AJ14: =IF(B14="","",(AA14*25)/AD14) -> 0.046417878 | AK14: =IF(B14="","",(AB14*40)/AD14) -> 0.16258803 | AL14: =IF(B14="","",(AC14*50)/AD14) -> 0.047254236 | AM14: =IF(B14="","",B14) -> 46069 | AN14: 24 | AO14: 20.38 | AP14: =24-AN14 -> 0 | AQ14: =IF(AN14="","",AN14/AO14) -> 1.1776251 | AR14: =IF(AN14="","",(AD14/AN14)/1000) -> 4.9819167 | AS14: =IF(AN14="","",AR14*24) -> 119.566 | AT14: =IF(AN14="","",(AD14/1000)*100%/AS14) -> 1 | AU14: =IF(AN14="","",(AE14/AN14)) -> 73.313333 | AV14: =IF(AN14="","",(AD14/AO14)/1000) -> 5.8668302
A15: =IF(B15="","",1+A14) -> 12 | B15: 46070 | C15: 62 | R15: =14112+30016 -> 44128 | T15: 24400 | Y15: 2 | AA15: =30+59+35 -> 124 | AB15: =66+125+170 -> 361 | AC15: =34+67 -> 101 | AD15: =IF(B15="","",(((C15+F15+H15+K15+Q15+N15+O15)*50))+((E15*10))+(((I15+J15+D15+G15+L15+M15+U15)*25)+(X15*25)+(Y15*25)+(Z15*25)+(AA15*25)+(AB15*40)+(AC15*50)+(R15*1)+(S15*1)+(T15*1))) -> 94268 | AE15: =IF(B15="","",C15+F15+H15+K15+Q15+N15+O15+((I15+J15+D15+G15)/2)+(R15/50)+(S15/50)+(T15/50)+(U15/2)+(E15/5)) -> 1432.56 | AF15: =IF(B15="","",((AE15*50)/AD15)) -> 0.75983367 | AG15: =IF(C15="","",((Z15)*25)/AD15) -> 0 | AH15: =IF(B15="","",(X15*25)/AD15) -> 0 | AI15: =IF(B15="","",(Y15*25)/AD15) -> 0.00053040268 | AJ15: =IF(B15="","",(AA15*25)/AD15) -> 0.032884966 | AK15: =IF(B15="","",(AB15*40)/AD15) -> 0.15318029 | AL15: =IF(B15="","",(AC15*50)/AD15) -> 0.053570671 | AM15: =IF(B15="","",B15) -> 46070 | AN15: 23.41 | AO15: 14.22 | AP15: =24-AN15 -> 0.59 | AQ15: =IF(AN15="","",AN15/AO15) -> 1.6462729 | AR15: =IF(AN15="","",(AD15/AN15)/1000) -> 4.0268261 | AS15: =IF(AN15="","",AR15*24) -> 96.643827 | AT15: =IF(AN15="","",(AD15/1000)*100%/AS15) -> 0.97541667 | AU15: =IF(AN15="","",(AE15/AN15)) -> 61.194361 | AV15: =IF(AN15="","",(AD15/AO15)/1000) -> 6.6292546
A16: =IF(B16="","",1+A15) -> 13 | B16: 46071 | C16: =68+568+210+426+355+271 -> 1898 | AA16: =59+61 -> 120 | AB16: =135+132+123 -> 390 | AC16: 56 | AD16: =IF(B16="","",(((C16+F16+H16+K16+Q16+N16+O16)*50))+((E16*10))+(((I16+J16+D16+G16+L16+M16+U16)*25)+(X16*25)+(Y16*25)+(Z16*25)+(AA16*25)+(AB16*40)+(AC16*50)+(R16*1)+(S16*1)+(T16*1))) -> 116300 | AE16: =IF(B16="","",C16+F16+H16+K16+Q16+N16+O16+((I16+J16+D16+G16)/2)+(R16/50)+(S16/50)+(T16/50)+(U16/2)+(E16/5)) -> 1898 | AF16: =IF(B16="","",((AE16*50)/AD16)) -> 0.81599312 | AG16: =IF(C16="","",((Z16)*25)/AD16) -> 0 | AH16: =IF(B16="","",(X16*25)/AD16) -> 0 | AI16: =IF(B16="","",(Y16*25)/AD16) -> 0 | AJ16: =IF(B16="","",(AA16*25)/AD16) -> 0.025795357 | AK16: =IF(B16="","",(AB16*40)/AD16) -> 0.13413586 | AL16: =IF(B16="","",(AC16*50)/AD16) -> 0.024075666 | AM16: =IF(B16="","",B16) -> 46071 | AN16: 23.83 | AO16: 13.87 | AP16: =24-AN16 -> 0.17 | AQ16: =IF(AN16="","",AN16/AO16) -> 1.7180966 | AR16: =IF(AN16="","",(AD16/AN16)/1000) -> 4.8804029 | AS16: =IF(AN16="","",AR16*24) -> 117.12967 | AT16: =IF(AN16="","",(AD16/1000)*100%/AS16) -> 0.99291667 | AU16: =IF(AN16="","",(AE16/AN16)) -> 79.647503 | AV16: =IF(AN16="","",(AD16/AO16)/1000) -> 8.3850036
A17: =IF(B17="","",1+A16) -> 14 | B17: 46072 | C17: =509+117+474 -> 1100 | R17: =6912+29024 -> 35936 | AA17: =90+84+62 -> 236 | AB17: =63+167+134 -> 364 | AC17: 130 | AD17: =IF(B17="","",(((C17+F17+H17+K17+Q17+N17+O17)*50))+((E17*10))+(((I17+J17+D17+G17+L17+M17+U17)*25)+(X17*25)+(Y17*25)+(Z17*25)+(AA17*25)+(AB17*40)+(AC17*50)+(R17*1)+(S17*1)+(T17*1))) -> 117896 | AE17: =IF(B17="","",C17+F17+H17+K17+Q17+N17+O17+((I17+J17+D17+G17)/2)+(R17/50)+(S17/50)+(T17/50)+(U17/2)+(E17/5)) -> 1818.72 | AF17: =IF(B17="","",((AE17*50)/AD17)) -> 0.77132388 | AG17: =IF(C17="","",((Z17)*25)/AD17) -> 0 | AH17: =IF(B17="","",(X17*25)/AD17) -> 0 | AI17: =IF(B17="","",(Y17*25)/AD17) -> 0 | AJ17: =IF(B17="","",(AA17*25)/AD17) -> 0.050044107 | AK17: =IF(B17="","",(AB17*40)/AD17) -> 0.12349868 | AL17: =IF(B17="","",(AC17*50)/AD17) -> 0.055133338 | AM17: =IF(B17="","",B17) -> 46072 | AN17: 19.58 | AO17: 14.72 | AP17: =24-AN17 -> 4.42 | AQ17: =IF(AN17="","",AN17/AO17) -> 1.330163 | AR17: =IF(AN17="","",(AD17/AN17)/1000) -> 6.0212462 | AS17: =IF(AN17="","",AR17*24) -> 144.50991 | AT17: =IF(AN17="","",(AD17/1000)*100%/AS17) -> 0.81583333 | AU17: =IF(AN17="","",(AE17/AN17)) -> 92.886619 | AV17: =IF(AN17="","",(AD17/AO17)/1000) -> 8.0092391
A18: =IF(B18="","",1+A17) -> 15 | B18: 46073 | R18: =24656+15024 -> 39680 | S18: =9296+39984 -> 49280 | AA18: 163 | AB18: =118+110+246 -> 474 | AC18: =42+11+88 -> 141 | AD18: =IF(B18="","",(((C18+F18+H18+K18+Q18+N18+O18)*50))+((E18*10))+(((I18+J18+D18+G18+L18+M18+U18)*25)+(X18*25)+(Y18*25)+(Z18*25)+(AA18*25)+(AB18*40)+(AC18*50)+(R18*1)+(S18*1)+(T18*1))) -> 119045 | AE18: =IF(B18="","",C18+F18+H18+K18+Q18+N18+O18+((I18+J18+D18+G18)/2)+(R18/50)+(S18/50)+(T18/50)+(U18/2)+(E18/5)) -> 1779.2 | AF18: =IF(B18="","",((AE18*50)/AD18)) -> 0.74728044 | AG18: =IF(C18="","",((Z18)*25)/AD18) | AH18: =IF(B18="","",(X18*25)/AD18) -> 0 | AI18: =IF(B18="","",(Y18*25)/AD18) -> 0 | AJ18: =IF(B18="","",(AA18*25)/AD18) -> 0.034230753 | AK18: =IF(B18="","",(AB18*40)/AD18) -> 0.1592675 | AL18: =IF(B18="","",(AC18*50)/AD18) -> 0.059221303 | AM18: =IF(B18="","",B18) -> 46073 | AN18: 24 | AO18: =9.17+9.65 -> 18.82 | AP18: =24-AN18 -> 0 | AQ18: =IF(AN18="","",AN18/AO18) -> 1.2752391 | AR18: =IF(AN18="","",(AD18/AN18)/1000) -> 4.9602083 | AS18: =IF(AN18="","",AR18*24) -> 119.045 | AT18: =IF(AN18="","",(AD18/1000)*100%/AS18) -> 1 | AU18: =IF(AN18="","",(AE18/AN18)) -> 74.133333 | AV18: =IF(AN18="","",(AD18/AO18)/1000) -> 6.3254516
A19: =IF(B19="","",1+A18) -> 16 | B19: 46075 | R19: 55504 | AA19: 92 | AB19: 245 | AC19: 0 | AD19: =IF(B19="","",(((C19+F19+H19+K19+Q19+N19+O19)*50))+((E19*10))+(((I19+J19+D19+G19+L19+M19+U19)*25)+(X19*25)+(Y19*25)+(Z19*25)+(AA19*25)+(AB19*40)+(AC19*50)+(R19*1)+(S19*1)+(T19*1))) -> 67604 | AE19: =IF(B19="","",C19+F19+H19+K19+Q19+N19+O19+((I19+J19+D19+G19)/2)+(R19/50)+(S19/50)+(T19/50)+(U19/2)+(E19/5)) -> 1110.08 | AF19: =IF(B19="","",((AE19*50)/AD19)) -> 0.82101651 | AG19: =IF(C19="","",((Z19)*25)/AD19) | AH19: =IF(B19="","",(X19*25)/AD19) -> 0 | AI19: =IF(B19="","",(Y19*25)/AD19) -> 0 | AJ19: =IF(B19="","",(AA19*25)/AD19) -> 0.034021656 | AK19: =IF(B19="","",(AB19*40)/AD19) -> 0.14496184 | AL19: =IF(B19="","",(AC19*50)/AD19) -> 0 | AM19: =IF(B19="","",B19) -> 46075 | AN19: 24 | AO19: 15.7 | AP19: =24-AN19 -> 0 | AQ19: =IF(AN19="","",AN19/AO19) -> 1.5286624 | AR19: =IF(AN19="","",(AD19/AN19)/1000) -> 2.8168333 | AS19: =IF(AN19="","",AR19*24) -> 67.604 | AT19: =IF(AN19="","",(AD19/1000)*100%/AS19) -> 1 | AU19: =IF(AN19="","",(AE19/AN19)) -> 46.253333 | AV19: =IF(AN19="","",(AD19/AO19)/1000) -> 4.3059873
A20: =IF(B20="","",1+A19) -> 17 | B20: 46076 | I20: =320+880+85+584 -> 1869 | R20: 35760 | U20: 275 | AA20: =55+25+77 -> 157 | AB20: =134+126+147 -> 407 | AC20: 173 | AD20: =IF(B20="","",(((C20+F20+H20+K20+Q20+N20+O20)*50))+((E20*10))+(((I20+J20+D20+G20+L20+M20+U20)*25)+(X20*25)+(Y20*25)+(Z20*25)+(AA20*25)+(AB20*40)+(AC20*50)+(R20*1)+(S20*1)+(T20*1))) -> 118215 | AE20: =IF(B20="","",C20+F20+H20+K20+Q20+N20+O20+((I20+J20+D20+G20+U20)/2)+(R20/50)+(S20/50)+(T20/50)+(E20/5)) -> 1787.2 | AF20: =IF(B20="","",((AE20*50)/AD20)) -> 0.75591084 | AG20: =IF(C20="","",((Z20)*25)/AD20) | AH20: =IF(B20="","",(X20*25)/AD20) -> 0 | AI20: =IF(B20="","",(Y20*25)/AD20) -> 0 | AJ20: =IF(B20="","",(AA20*25)/AD20) -> 0.033202216 | AK20: =IF(B20="","",(AB20*40)/AD20) -> 0.13771518 | AL20: =IF(B20="","",(AC20*50)/AD20) -> 0.073171763 | AM20: =IF(B20="","",B20) -> 46076 | AN20: 21.83 | AO20: 20.98 | AP20: =24-AN20 -> 2.17 | AQ20: =IF(AN20="","",AN20/AO20) -> 1.0405148 | AR20: =IF(AN20="","",(AD20/AN20)/1000) -> 5.4152542 | AS20: =IF(AN20="","",AR20*24) -> 129.9661 | AT20: =IF(AN20="","",(AD20/1000)*100%/AS20) -> 0.90958333 | AU20: =IF(AN20="","",(AE20/AN20)) -> 81.868988 | AV20: =IF(AN20="","",(AD20/AO20)/1000) -> 5.634652
A21: =IF(B21="","",1+A20) -> 18 | B21: 46077 | I21: 40 | R21: 86766 | AA21: =4550/25 -> 182 | AB21: =14880/40 -> 372 | AC21: =5200/50 -> 104 | AD21: =IF(B21="","",(((C21+F21+H21+K21+Q21+N21+O21)*50))+((E21*10))+(((I21+J21+D21+G21+L21+M21+U21)*25)+(X21*25)+(Y21*25)+(Z21*25)+(AA21*25)+(AB21*40)+(AC21*50)+(R21*1)+(S21*1)+(T21*1))) -> 112396 | AE21: =IF(B21="","",C21+F21+H21+K21+Q21+N21+O21+((I21+J21+D21+G21+U21)/2)+(R21/50)+(S21/50)+(T21/50)+(E21/5)) -> 1755.32 | AF21: =IF(B21="","",((AE21*50)/AD21)) -> 0.78086409 | AG21: =IF(C21="","",((Z21)*25)/AD21) | AH21: =IF(B21="","",(X21*25)/AD21) -> 0 | AI21: =IF(B21="","",(Y21*25)/AD21) -> 0 | AJ21: =IF(B21="","",(AA21*25)/AD21) -> 0.040481868 | AK21: =IF(B21="","",(AB21*40)/AD21) -> 0.13238905 | AL21: =IF(B21="","",(AC21*50)/AD21) -> 0.046264992 | AM21: =IF(B21="","",B21) -> 46077 | AN21: 24 | AO21: 14.38 | AP21: =24-AN21 -> 0 | AQ21: =IF(AN21="","",AN21/AO21) -> 1.6689847 | AR21: =IF(AN21="","",(AD21/AN21)/1000) -> 4.6831667 | AS21: =IF(AN21="","",AR21*24) -> 112.396 | AT21: =IF(AN21="","",(AD21/1000)*100%/AS21) -> 1 | AU21: =IF(AN21="","",(AE21/AN21)) -> 73.138333 | AV21: =IF(AN21="","",(AD21/AO21)/1000) -> 7.8161335
A22: =IF(B22="","",1+A21) -> 19 | B22: 46078 | C22: =46100/50 -> 922 | F22: =115+250 -> 365 | G22: =39+198 -> 237 | I22: =96+871 -> 967 | AA22: =52+60+47 -> 159 | AB22: =135+126+126 -> 387 | AC22: =18+35 -> 53 | AD22: =IF(B22="","",(((C22+F22+H22+K22+Q22+N22+O22)*50))+((E22*10))+(((I22+J22+D22+G22+L22+M22+U22)*25)+(X22*25)+(Y22*25)+(Z22*25)+(AA22*25)+(AB22*40)+(AC22*50)+(R22*1)+(S22*1)+(T22*1))) -> 116555 | AE22: =IF(B22="","",C22+F22+H22+K22+Q22+N22+O22+((I22+J22+D22+G22+U22)/2)+(R22/50)+(S22/50)+(T22/50)+(E22/5)) -> 1889 | AF22: =IF(B22="","",((AE22*50)/AD22)) -> 0.81034705 | AG22: =IF(C22="","",((Z22)*25)/AD22) -> 0 | AH22: =IF(B22="","",(X22*25)/AD22) -> 0 | AI22: =IF(B22="","",(Y22*25)/AD22) -> 0 | AJ22: =IF(B22="","",(AA22*25)/AD22) -> 0.034104071 | AK22: =IF(B22="","",(AB22*40)/AD22) -> 0.13281284 | AL22: =IF(B22="","",(AC22*50)/AD22) -> 0.022736047 | AM22: =IF(B22="","",B22) -> 46078 | AN22: 24 | AO22: 16.92 | AP22: =24-AN22 -> 0 | AQ22: =IF(AN22="","",AN22/AO22) -> 1.4184397 | AR22: =IF(AN22="","",(AD22/AN22)/1000) -> 4.8564583 | AS22: =IF(AN22="","",AR22*24) -> 116.555 | AT22: =IF(AN22="","",(AD22/1000)*100%/AS22) -> 1 | AU22: =IF(AN22="","",(AE22/AN22)) -> 78.708333 | AV22: =IF(AN22="","",(AD22/AO22)/1000) -> 6.8885934
A23: =IF(B23="","",1+A22) -> 20 | B23: 46079 | C23: =68+45 -> 113 | I23: =35+983 -> 1018 | R23: 31424 | S23: 25536 | AA23: =48+71+62 -> 181 | AB23: =160+176+134 -> 470 | AC23: =11+90 -> 101 | AD23: =IF(B23="","",(((C23+F23+H23+K23+Q23+N23+O23)*50))+((E23*10))+(((I23+J23+D23+G23+L23+M23+U23)*25)+(X23*25)+(Y23*25)+(Z23*25)+(AA23*25)+(AB23*40)+(AC23*50)+(R23*1)+(S23*1)+(T23*1))) -> 116435 | AE23: =IF(B23="","",C23+F23+H23+K23+Q23+N23+O23+((I23+J23+D23+G23+U23)/2)+(R23/50)+(S23/50)+(T23/50)+(E23/5)) -> 1761.2 | AF23: =IF(B23="","",((AE23*50)/AD23)) -> 0.7563018 | AG23: =IF(C23="","",((Z23)*25)/AD23) -> 0 | AH23: =IF(B23="","",(X23*25)/AD23) -> 0 | AI23: =IF(B23="","",(Y23*25)/AD23) -> 0 | AJ23: =IF(B23="","",(AA23*25)/AD23) -> 0.038862885 | AK23: =IF(B23="","",(AB23*40)/AD23) -> 0.16146348 | AL23: =IF(B23="","",(AC23*50)/AD23) -> 0.043371838 | AM23: =IF(B23="","",B23) -> 46079 | AN23: 24 | AO23: =9.8+9.48 -> 19.28 | AP23: =24-AN23 -> 0 | AQ23: =IF(AN23="","",AN23/AO23) -> 1.2448133 | AR23: =IF(AN23="","",(AD23/AN23)/1000) -> 4.8514583 | AS23: =IF(AN23="","",AR23*24) -> 116.435 | AT23: =IF(AN23="","",(AD23/1000)*100%/AS23) -> 1 | AU23: =IF(AN23="","",(AE23/AN23)) -> 73.383333 | AV23: =IF(AN23="","",(AD23/AO23)/1000) -> 6.0391598
A24: =IF(B24="","",1+A23) -> 21 | B24: 46080 | C24: 233 | R24: 43760 | S24: 24928 | AA24: =61+65+76 -> 202 | AB24: =125+165+152 -> 442 | AC24: =23+152 -> 175 | AD24: =IF(B24="","",(((C24+F24+H24+K24+Q24+N24+O24)*50))+((E24*10))+(((I24+J24+D24+G24+L24+M24+U24)*25)+(X24*25)+(Y24*25)+(Z24*25)+(AA24*25)+(AB24*40)+(AC24*50)+(R24*1)+(S24*1)+(T24*1))) -> 111818 | AE24: =IF(B24="","",C24+F24+H24+K24+Q24+N24+O24+((I24+J24+D24+G24+U24)/2)+(R24/50)+(S24/50)+(T24/50)+(E24/5)) -> 1606.76 | AF24: =IF(B24="","",((AE24*50)/AD24)) -> 0.71847109 | AG24: =IF(C24="","",((Z24)*25)/AD24) -> 0 | AH24: =IF(B24="","",(X24*25)/AD24) -> 0 | AI24: =IF(B24="","",(Y24*25)/AD24) -> 0 | AJ24: =IF(B24="","",(AA24*25)/AD24) -> 0.045162675 | AK24: =IF(B24="","",(AB24*40)/AD24) -> 0.15811408 | AL24: =IF(B24="","",(AC24*50)/AD24) -> 0.07825216 | AM24: =IF(B24="","",B24) -> 46080 | AN24: 23.5 | AO24: =+AD24/7500 -> 14.909067 | AP24: =24-AN24 -> 0.5 | AQ24: =IF(AN24="","",AN24/AO24) -> 1.5762221 | AR24: =IF(AN24="","",(AD24/AN24)/1000) -> 4.7582128 | AS24: =IF(AN24="","",AR24*24) -> 114.19711 | AT24: =IF(AN24="","",(AD24/1000)*100%/AS24) -> 0.97916667 | AU24: =IF(AN24="","",(AE24/AN24)) -> 68.372766 | AV24: =IF(AN24="","",(AD24/AO24)/1000) -> 7.5
AD25: =IF(B25="","",(((C25+F25+H25+K25+Q25+N25+O25)*50))+((E25*10))+(((I25+J25+D25+G25+L25+M25+U25)*25)+(X25*25)+(Y25*25)+(Z25*25)+(AA25*25)+(AB25*40)+(AC25*50)+(R25*1)+(S25*1)+(T25*1))) | AE25: =IF(B25="","",C25+F25+H25+K25+Q25+N25+O25+((I25+J25+D25+G25+U25)/2)+(R25/50)+(S25/50)+(T25/50)+(E25/5)) | AF25: =IF(B25="","",((AE25*50)/AD25)) | AG25: =IF(C25="","",((Z25)*25)/AD25) | AH25: =IF(B25="","",(X25*25)/AD25) | AI25: =IF(B25="","",(Y25*25)/AD25) | AJ25: =IF(B25="","",(AA25*25)/AD25) | AK25: =IF(B25="","",(AB25*40)/AD25) | AL25: =IF(B25="","",(AC25*50)/AD25) | AM25: =IF(B25="","",B25) | AQ25: =IF(AN25="","",AN25/AO25) | AR25: =IF(AN25="","",(AD25/AN25)/1000) | AS25: =IF(AN25="","",AR25*24) | AT25: =IF(AN25="","",(AD25/1000)*100%/AS25) | AU25: =IF(AN25="","",(AE25/AN25)) | AV25: =IF(AN25="","",(AD25/AO25)/1000)
AD26: =IF(B26="","",(((C26+F26+H26+K26+Q26+N26+O26)*50))+((E26*10))+(((I26+J26+D26+G26+L26+M26+U26)*25)+(X26*25)+(Y26*25)+(Z26*25)+(AA26*25)+(AB26*40)+(AC26*50)+(R26*1)+(S26*1)+(T26*1))) | AE26: =IF(B26="","",C26+F26+H26+K26+Q26+N26+O26+((I26+J26+D26+G26+U26)/2)+(R26/50)+(S26/50)+(T26/50)+(E26/5)) | AF26: =IF(B26="","",((AE26*50)/AD26)) | AG26: =IF(C26="","",((Z26)*25)/AD26) | AH26: =IF(B26="","",(X26*25)/AD26) | AI26: =IF(B26="","",(Y26*25)/AD26) | AJ26: =IF(B26="","",(AA26*25)/AD26) | AK26: =IF(B26="","",(AB26*40)/AD26) | AL26: =IF(B26="","",(AC26*50)/AD26) | AM26: =IF(B26="","",B26) | AQ26: =IF(AN26="","",AN26/AO26) | AR26: =IF(AN26="","",(AD26/AN26)/1000) | AS26: =IF(AN26="","",AR26*24) | AT26: =IF(AN26="","",(AD26/1000)*100%/AS26) | AU26: =IF(AN26="","",(AE26/AN26)) | AV26: =IF(AN26="","",(AD26/AO26)/1000)
AD27: =IF(B27="","",(((C27+F27+H27+K27+Q27+N27+O27)*50))+((E27*10))+(((I27+J27+D27+G27+L27+M27+U27)*25)+(X27*25)+(Y27*25)+(Z27*25)+(AA27*25)+(AB27*40)+(AC27*50)+(R27*1)+(S27*1)+(T27*1))) | AE27: =IF(B27="","",C27+F27+H27+K27+Q27+N27+O27+((I27+J27+D27+G27+U27)/2)+(R27/50)+(S27/50)+(T27/50)+(E27/5)) | AF27: =IF(B27="","",((AE27*50)/AD27)) | AG27: =IF(C27="","",((Z27)*25)/AD27) | AH27: =IF(B27="","",(X27*25)/AD27) | AI27: =IF(B27="","",(Y27*25)/AD27) | AJ27: =IF(B27="","",(AA27*25)/AD27) | AK27: =IF(B27="","",(AB27*40)/AD27) | AL27: =IF(B27="","",(AC27*50)/AD27) | AM27: =IF(B27="","",B27) | AQ27: =IF(AN27="","",AN27/AO27) | AR27: =IF(AN27="","",(AD27/AN27)/1000) | AS27: =IF(AN27="","",AR27*24) | AT27: =IF(AN27="","",(AD27/1000)*100%/AS27) | AU27: =IF(AN27="","",(AE27/AN27)) | AV27: =IF(AN27="","",(AD27/AO27)/1000)
AD28: =IF(B28="","",(((C28+F28+H28+K28+Q28+N28+O28)*50))+((E28*10))+(((I28+J28+D28+G28+L28+M28+U28)*25)+(X28*25)+(Y28*25)+(Z28*25)+(AA28*25)+(AB28*40)+(AC28*50)+(R28*1)+(S28*1)+(T28*1))) | AE28: =IF(B28="","",C28+F28+H28+K28+Q28+N28+O28+((I28+J28+D28+G28+U28)/2)+(R28/50)+(S28/50)+(T28/50)+(E28/5)) | AF28: =IF(B28="","",((AE28*50)/AD28)) | AG28: =IF(C28="","",((Z28)*25)/AD28) | AH28: =IF(B28="","",(X28*25)/AD28) | AI28: =IF(B28="","",(Y28*25)/AD28) | AJ28: =IF(B28="","",(AA28*25)/AD28) | AK28: =IF(B28="","",(AB28*40)/AD28) | AL28: =IF(B28="","",(AC28*50)/AD28) | AM28: =IF(B28="","",B28) | AQ28: =IF(AN28="","",AN28/AO28) | AR28: =IF(AN28="","",(AD28/AN28)/1000) | AS28: =IF(AN28="","",AR28*24) | AT28: =IF(AN28="","",(AD28/1000)*100%/AS28) | AU28: =IF(AN28="","",(AE28/AN28)) | AV28: =IF(AN28="","",(AD28/AO28)/1000)
AD29: =IF(B29="","",(((C29+F29+H29+K29+Q29+N29+O29)*50))+((E29*10))+(((I29+J29+D29+G29+L29+M29+U29)*25)+(X29*25)+(Y29*25)+(Z29*25)+(AA29*25)+(AB29*40)+(AC29*50)+(R29*1)+(S29*1)+(T29*1))) | AE29: =IF(B29="","",C29+F29+H29+K29+Q29+N29+O29+((I29+J29+D29+G29+U29)/2)+(R29/50)+(S29/50)+(T29/50)+(E29/5)) | AF29: =IF(B29="","",((AE29*50)/AD29)) | AG29: =IF(C29="","",((Z29)*25)/AD29) | AH29: =IF(B29="","",(X29*25)/AD29) | AI29: =IF(B29="","",(Y29*25)/AD29) | AJ29: =IF(B29="","",(AA29*25)/AD29) | AK29: =IF(B29="","",(AB29*40)/AD29) | AL29: =IF(B29="","",(AC29*50)/AD29) | AM29: =IF(B29="","",B29) | AQ29: =IF(AN29="","",AN29/AO29) | AR29: =IF(AN29="","",(AD29/AN29)/1000) | AS29: =IF(AN29="","",AR29*24) | AT29: =IF(AN29="","",(AD29/1000)*100%/AS29) | AU29: =IF(AN29="","",(AE29/AN29)) | AV29: =IF(AN29="","",(AD29/AO29)/1000)
A30: =IF(B30="","",1+A29) | AD30: =IF(B30="","",(((C30+F30+H30+K30+Q30+N30+O30)*50))+((E30*10))+(((I30+J30+D30+G30+L30+M30+U30)*25)+(X30*25)+(Y30*25)+(Z30*25)+(AA30*25)+(AB30*40)+(AC30*50)+(R30*1)+(S30*1)+(T30*1))) | AE30: =IF(B30="","",C30+F30+H30+K30+Q30+N30+O30+((I30+J30+D30+G30+U30)/2)+(R30/50)+(S30/50)+(T30/50)+(E30/5)) | AF30: =IF(B30="","",((AE30*50)/AD30)) | AG30: =IF(C30="","",((Z30)*25)/AD30) | AH30: =IF(B30="","",(X30*25)/AD30) | AI30: =IF(B30="","",(Y30*25)/AD30) | AJ30: =IF(B30="","",(AA30*25)/AD30) | AK30: =IF(B30="","",(AB30*40)/AD30) | AL30: =IF(B30="","",(AC30*50)/AD30) | AM30: =IF(B30="","",B30) | AQ30: =IF(AN30="","",AN30/AO30) | AR30: =IF(AN30="","",(AD30/AN30)/1000) | AS30: =IF(AN30="","",AR30*24) | AT30: =IF(AN30="","",(AD30/1000)*100%/AS30) | AU30: =IF(AN30="","",(AE30/AN30)) | AV30: =IF(AN30="","",(AD30/AO30)/1000)
A31: =IF(B31="","",1+A30) | AD31: =IF(B31="","",(((C31+F31+H31+K31+Q31+N31+O31)*50))+((E31*10))+(((I31+J31+D31+G31+L31+M31+U31)*25)+(X31*25)+(Y31*25)+(Z31*25)+(AA31*25)+(AB31*40)+(AC31*50)+(R31*1)+(S31*1)+(T31*1))) | AE31: =IF(B31="","",C31+F31+H31+K31+Q31+N31+O31+((I31+J31+D31+G31+U31)/2)+(R31/50)+(S31/50)+(T31/50)+(E31/5)) | AF31: =IF(B31="","",((AE31*50)/AD31)) | AG31: =IF(C31="","",((Z31)*25)/AD31) | AH31: =IF(B31="","",(X31*25)/AD31) | AI31: =IF(B31="","",(Y31*25)/AD31) | AJ31: =IF(B31="","",(AA31*25)/AD31) | AK31: =IF(B31="","",(AB31*40)/AD31) | AL31: =IF(B31="","",(AC31*50)/AD31) | AM31: =IF(B31="","",B31) | AQ31: =IF(AN31="","",AN31/AO31) | AR31: =IF(AN31="","",(AD31/AN31)/1000) | AS31: =IF(AN31="","",AR31*24) | AT31: =IF(AN31="","",(AD31/1000)*100%/AS31) | AU31: =IF(AN31="","",(AE31/AN31)) | AV31: =IF(AN31="","",(AD31/AO31)/1000)
A32: =IF(B32="","",1+A31) | AD32: =IF(B32="","",(((C32+F32+H32+K32+Q32+N32+O32)*50))+((E32*10))+(((I32+J32+D32+G32+L32+M32+U32)*25)+(X32*25)+(Y32*25)+(Z32*25)+(AA32*25)+(AB32*40)+(AC32*50)+(R32*1)+(S32*1)+(T32*1))) | AE32: =IF(B32="","",C32+F32+H32+K32+Q32+N32+O32+((I32+J32+D32+G32+U32)/2)+(R32/50)+(S32/50)+(T32/50)+(E32/5)) | AF32: =IF(B32="","",((AE32*50)/AD32)) | AG32: =IF(C32="","",((Z32)*25)/AD32) | AH32: =IF(B32="","",(X32*25)/AD32) | AI32: =IF(B32="","",(Y32*25)/AD32) | AJ32: =IF(B32="","",(AA32*25)/AD32) | AK32: =IF(B32="","",(AB32*40)/AD32) | AL32: =IF(B32="","",(AC32*50)/AD32) | AM32: =IF(B32="","",B32) | AQ32: =IF(AN32="","",AN32/AO32) | AR32: =IF(AN32="","",(AD32/AN32)/1000) | AS32: =IF(AN32="","",AR32*24) | AT32: =IF(AN32="","",(AD32/1000)*100%/AS32) | AU32: =IF(AN32="","",(AE32/AN32)) | AV32: =IF(AN32="","",(AD32/AO32)/1000)
A33: =IF(B33="","",1+A32) | AD33: =IF(B33="","",(((C33+F33+H33+K33+Q33+N33+O33)*50))+((E33*10))+(((I33+J33+D33+G33+L33+M33+U33)*25)+(X33*25)+(Y33*25)+(Z33*25)+(AA33*25)+(AB33*40)+(AC33*50)+(R33*1)+(S33*1)+(T33*1))) | AE33: =IF(B33="","",C33+F33+H33+K33+Q33+N33+O33+((I33+J33+D33+G33+U33)/2)+(R33/50)+(S33/50)+(T33/50)+(E33/5)) | AF33: =IF(B33="","",((AE33*50)/AD33)) | AG33: =IF(C33="","",((Z33)*25)/AD33) | AH33: =IF(B33="","",(X33*25)/AD33) | AI33: =IF(B33="","",(Y33*25)/AD33) | AJ33: =IF(B33="","",(AA33*25)/AD33) | AK33: =IF(B33="","",(AB33*40)/AD33) | AL33: =IF(B33="","",(AC33*50)/AD33) | AM33: =IF(B33="","",B33) | AQ33: =IF(AN33="","",AN33/AO33) | AR33: =IF(AN33="","",(AD33/AN33)/1000) | AS33: =IF(AN33="","",AR33*24) | AT33: =IF(AN33="","",(AD33/1000)*100%/AS33) | AU33: =IF(AN33="","",(AE33/AN33)) | AV33: =IF(AN33="","",(AD33/AO33)/1000)
A34: =IF(B34="","",1+A33) | AD34: =IF(B34="","",(((C34+F34+H34+K34+Q34+N34+O34)*50))+((E34*10))+(((I34+J34+D34+G34+L34+M34+U34)*25)+(X34*25)+(Y34*25)+(Z34*25)+(AA34*25)+(AB34*40)+(AC34*50)+(R34*1)+(S34*1)+(T34*1))) | AE34: =IF(B34="","",C34+F34+H34+K34+Q34+N34+O34+((I34+J34+D34+G34+U34)/2)+(R34/50)+(S34/50)+(T34/50)+(E34/5)) | AF34: =IF(B34="","",((AE34*50)/AD34)) | AG34: =IF(C34="","",((Z34)*25)/AD34) | AH34: =IF(B34="","",(X34*25)/AD34) | AI34: =IF(B34="","",(Y34*25)/AD34) | AJ34: =IF(B34="","",(AA34*25)/AD34) | AK34: =IF(B34="","",(AB34*40)/AD34) | AL34: =IF(B34="","",(AC34*50)/AD34) | AM34: =IF(B34="","",B34) | AQ34: =IF(AN34="","",AN34/AO34) | AR34: =IF(AN34="","",(AD34/AN34)/1000) | AS34: =IF(AN34="","",AR34*24) | AT34: =IF(AN34="","",(AD34/1000)*100%/AS34) | AU34: =IF(AN34="","",(AE34/AN34)) | AV34: =IF(AN34="","",(AD34/AO34)/1000)
A35: =IF(B35="","",1+A34) | AD35: =IF(B35="","",(((C35+F35+H35+K35+Q35+N35+O35)*50))+((E35*10))+(((I35+J35+D35+G35+L35+M35+U35)*25)+(X35*25)+(Y35*25)+(Z35*25)+(AA35*25)+(AB35*40)+(AC35*50)+(R35*1)+(S35*1)+(T35*1))) | AE35: =IF(B35="","",C35+F35+H35+K35+Q35+N35+O35+((I35+J35+D35+G35+U35)/2)+(R35/50)+(S35/50)+(T35/50)+(E35/5)) | AF35: =IF(B35="","",((AE35*50)/AD35)) | AG35: =IF(C35="","",((Z35)*25)/AD35) | AH35: =IF(B35="","",(X35*25)/AD35) | AI35: =IF(B35="","",(Y35*25)/AD35) | AJ35: =IF(B35="","",(AA35*25)/AD35) | AK35: =IF(B35="","",(AB35*40)/AD35) | AL35: =IF(B35="","",(AC35*50)/AD35) | AM35: =IF(B35="","",B35) | AQ35: =IF(AN35="","",AN35/AO35) | AR35: =IF(AN35="","",(AD35/AN35)/1000) | AS35: =IF(AN35="","",AR35*24) | AT35: =IF(AN35="","",(AD35/1000)*100%/AS35) | AU35: =IF(AN35="","",(AE35/AN35)) | AV35: =IF(AN35="","",(AD35/AO35)/1000)
B36: Total | C36: =SUM(C4:C35) -> 10109 | D36: =SUM(D4:D35) -> 1542 | E36: =SUM(E4:E35) -> 199 | F36: =SUM(F4:F35) -> 855 | G36: =SUM(G4:G35) -> 398 | H36: =SUM(H4:H35) -> 513 | I36: =SUM(I4:I35) -> 6727 | J36: =SUM(J4:J35) -> 80 | ... AE36: =SUM(AE4:AE35) -> 36031.12 | AF36: =IF(AD44=0,"",(AE36*50)/AD36) -> 0.77319137 | AG36: =IF(AD44=0,"",(Z36*50)/AD36) -> 0 | AH36: =IF(AD44=0,"",(X36*25)/AD36) -> 0 | AI36: =IF(AD44=0,"",(Y36*25)/AD36) -> 0.00093346598 | AJ36: =IF(AD44=0,"",(AA36*25)/AD36) -> 0.036448091 | AK36: =IF(AD44=0,"",(AB36*40)/AD36) -> 0.14159499 | AL36: =IF(AD44=0,"",(AC36*50)/AD36) -> 0.047832084 | AM36: Total | AN36: =SUM(AN4:AN35) -> 489.61 | AO36: =SUM(AO4:AO35) -> 355.95907 | AP36: =SUM(AP4:AP35) -> 14.39 | AQ36: =IF(AN36=0,"",AN36/AO36) -> 1.3754671 | AR36: =IF(AN36=0,"",(AD36/AN36)/1000) -> 4.7589428 | AS36: =IF(AN36=0,"",AR36*24) -> 114.21463 | AT36: =IF(AN36=0,"",AD44/(AS36*26)) -> 0.78463141 | AU36: =IF(AN36=0,"",(AE36/AN36)) -> 73.591471 | AV36: =IF(AO36=0,"",(AD36/AO36)/1000) -> 6.5457695 | AW36: =SUM(AW4:AW35)/1000 -> 0 | AX36: =SUM(AX4:AX35)/1000 -> 2373.408 | AY36: =SUM(AY4:AY35)/1000 -> 1837.104 | AZ36: =SUM(AZ4) -> 69185 | BA36: =SUM(BA4:BA35) -> 580 | BB36: =SUM(BB4:BB35) -> 354434 | BC36: =SUM(BC4:BC35)/1000 -> 123963.75 | BD36: =SUM(BD4:BD35)/1000 -> 5884.169 | BE36: =SUM(BE4:BE35)/1000 -> 39502.68 | BF36: =SUM(BF4:BF35)/1000 -> 47025.74
B37: Promedio | C37: =IF(C36=0,"",AVERAGE(C4:C35)) -> 842.41667 | D37: =IF(D36=0,"",AVERAGE(D4:D35)) -> 1542 | E37: =IF(E36=0,"",AVERAGE(E4:E35)) -> 199 | F37: =IF(F36=0,"",AVERAGE(F4:F35)) -> 427.5 | G37: =IF(G36=0,"",AVERAGE(G4:G35)) -> 199 | H37: =IF(H36=0,"",AVERAGE(H4:H35)) -> 513 | I37: =IF(I36=0,"",AVERAGE(I4:I35)) -> 1121.1667 | J37: =IF(J36=0,"",AVERAGE(J4:J35)) -> 80 | ... AC37: =IF(AC36=0,"",AVERAGE(AC4:AC35)) -> 106.14286 | AM37: Promedio | AN37: =IF(AN36=0,"",AVERAGE(AN4:AN35)) -> 23.314762 | AO37: =IF(AO36=0,"",AVERAGE(AO4:AO35)) -> 16.950432 | AP37: =IF(AP36=0,"",AVERAGE(AP4:AP35)) -> 0.6852381 | AQ37: =IF(AQ36="","",AVERAGE(AQ4:AQ35)) -> 1.404657 | AR37: =IF(AR36="","",AVERAGE(AR4:AR35)) -> 4.7736065 | AS37: =IF(AS36="","",AVERAGE(AS4:AS35)) -> 114.56656 | AT37: =IF(AT36="","",AVERAGE(AT4:AT35)) -> 0.97144841 | AU37: =IF(AU36="","",AVERAGE(AU4:AU35)) -> 73.80294 | AV37: =IF(AV36="","",AVERAGE(AV4:AV35)) -> 6.6576162
B38: Cambio de Mezcla | C38: =+SUM(C4:C22) -> 9763 | D38: =+SUM(D4:D22) -> 1542 | E38: =+SUM(E4:E22) -> 199 | F38: =+SUM(F4:F35) -> 855 | G38: =+SUM(G4:G35) -> 398 | I38: 6727 | J38: 80 | K38: =+SUM(K4:K35) -> 0 | L38: =+SUM(L4:L35) -> 0 | M38: =+SUM(M4:M35) -> 0 | N38: =+SUM(N4:N35) -> 0 | O38: =+SUM(O4:O35) -> 0 | P38: =+SUM(P4:P35) -> 0 | Q38: =+SUM(Q4:Q35) -> 0 | R38: =+SUM(R4:R13) -> 364848 | S38: =+SUM(S4:S35) -> 124624 | T38: =+SUM(T4:T35) -> 44760 | U38: =+SUM(U4:U35) -> 475 | AD38: Total Kg.
C39: =+SUM(C23:C24) -> 346 | D39: =+SUM(D23:D24) -> 0 | E39: =+SUM(E23:E24) -> 0 | F39: 0 | G39: 0 | H39: 0 | I39: 0 | J39: 0 | K39: 0 | L39: 0 | M39: 0 | N39: 0 | O39: 0 | P39: 0 | Q39: 0 | R39: =+SUM(R14:R25) -> 460934 | S39: 0 | T39: 0 | U39: 0 | AE39: Total Tm.
B44: Total | C44: =SUM(C4:C35) -> 10109 | D44: =SUM(D4:D35) -> 1542 | E44: =SUM(E4:E35) -> 199 | F44: =SUM(F4:F35) -> 855 | G44: =SUM(G4:G35) -> 398 | H44: =SUM(H4:H35) -> 513 | I44: =SUM(I4:I35) -> 6727 | J44: =SUM(J4:J35) -> 80 | ... AC44: =SUM(AC4:AC35) -> 2229 | AD44: =AD36/1000 -> 2330.026
A46: Grano entero | AA46: 135 | AD46: =(Z46+AA46)*25.8 -> 3483 | AE46: =Z46 -> 0 | AF46: =IF(B46="","",((AE46*25)/AD46)) | AG46: =IF(B46="","",((Z46)*25)/AD46) | AH46: =IF(B46="","",(X46*25)/AD46) | AI46: =IF(B46="","",(Y46*25)/AD46) | AJ46: =IF(B46="","",(AA46*25)/AD46) | AK46: =IF(B46="","",(AB46*40)/AD46) | AL46: =IF(B46="","",(AC46*50)/AD46) | AM46: =IF(B46="","",B46) | AQ46: =IF(AN46="","",AN46/AO46) | AR46: =IF(AN46="","",(AD46/AN46)/1000) | AS46: =IF(AN46="","",AR46*24) | AT46: =IF(AN46="","",(AD46/1000)*100%/AS46) | AU46: =IF(AN46="","",(AE46/AN46)) | AV46: =IF(AN46="","",(AD46/AO46)/1000)
A47: Bio Convercion | AD47: =(Z47*25)+(AA47*25)+(AB47*40)+(AC47*50) -> 0 | AE47: =IF(B47="","",C47+E47+G47+K47+N47+O47+Q47+R47+((D47+H47)/4)+((F47+I47+J47+T47+Z47)/2)) | AF47: =IF(B47="","",((AE47*50)/AD47)) | AG47: =IF(B47="","",((Z47)*25)/AD47) | AH47: =IF(B47="","",(X47*25)/AD47) | AI47: =IF(B47="","",(Y47*25)/AD47) | AJ47: =IF(B47="","",(AA47*25)/AD47) | AK47: =IF(B47="","",(AB47*40)/AD47) | AL47: =IF(B47="","",(AC47*50)/AD47) | AM47: =IF(B47="","",B47) | AQ47: =IF(AN47="","",AN47/AO47) | AR47: =IF(AN47="","",(AD47/AN47)/1000) | AS47: =IF(AN47="","",AR47*24) | AT47: =IF(AN47="","",(AD47/1000)*100%/AS47) | AU47: =IF(AN47="","",(AE47/AN47)) | AV47: =IF(AN47="","",(AD47/AO47)/1000)
A48: trigo granel | AA48: 8090 | AD48: =SUM(U48:AC48)*25 -> 202250 | AE48: =IF(B48="","",C48+E48+G48+K48+N48+O48+Q48+R48+((D48+H48)/4)+((F48+I48+J48+T48)/2)) | AF48: =IF(B48="","",((AE48*50)/AD48)) | AG48: =IF(B48="","",((Z48)*25)/AD48) | AH48: =IF(B48="","",(X48*25)/AD48) | AI48: =IF(B48="","",(Y48*25)/AD48) | AJ48: =IF(B48="","",(AA48*25)/AD48) | AK48: =IF(B48="","",(AB48*40)/AD48) | AL48: =IF(B48="","",(AC48*50)/AD48) | AM48: =IF(B48="","",B48) | AQ48: =IF(AN48="","",AN48/AO48) | AR48: =IF(AN48="","",(AD48/AN48)/1000) | AS48: =IF(AN48="","",AR48*24) | AT48: =IF(AN48="","",(AD48/1000)*100%/AS48) | AU48: =IF(AN48="","",(AE48/AN48)) | AV48: =IF(AN48="","",(AD48/AO48)/1000)
A49: Trigo entero | AA49: =400*3 -> 1200 | AD49: =SUM(U49:AC49)*25.275 -> 30330 | AE49: =IF(B49="","",C49+E49+G49+K49+N49+O49+Q49+R49+((D49+H49)/4)+((F49+I49+J49+T49)/2)) | AF49: =IF(B49="","",((AE49*50)/AD49)) | AG49: =IF(B49="","",((Z49)*25)/AD49) | AH49: =IF(B49="","",(X49*25)/AD49) | AI49: =IF(B49="","",(Y49*25)/AD49) | AJ49: =IF(B49="","",(AA49*25)/AD49) | AK49: =IF(B49="","",(AB49*40)/AD49) | AL49: =IF(B49="","",(AC49*50)/AD49) | AM49: =IF(B49="","",B49) | AQ49: =IF(AN49="","",AN49/AO49) | AR49: =IF(AN49="","",(AD49/AN49)/1000) | AS49: =IF(AN49="","",AR49*24) | AT49: =IF(AN49="","",(AD49/1000)*100%/AS49) | AU49: =IF(AN49="","",(AE49/AN49)) | AV49: =IF(AN49="","",(AD49/AO49)/1000)
AD50: =SUM(AD46:AD49) -> 236063 | AX50: =AX46/1000 -> 0
AD51: Total Kg.
I52: 3.6 | AD52: =AD50/1000 -> 236.063 | AE52: Total Tm.
A53: Produccion | C53: % rendimiento | F53: Energia | I53: ART | K53: PEDIDO PUERTO | N53: SAP | O53: Inicial | R53: CONSUMOS | V53: FINAL
A54: tm trigo: | B54: =AD44+AD52 -> 2566.089 | F54: Precio Kw: | H54: =IF(G57="",0,G60/G57) -> 0 | I54: =IF(I57="",0,I60/I57) -> 0 | M54: =IF($V$54="",0,K54/$V$59) -> 0 | O54: 311 | Q54: =IF($V$54="",0,O54/$V$59) -> -0.00012285523 | R54: =D84 -> CWRS | S54: =+SUMPRODUCT(D86:D110,B86:B110) -> 1725530.3 | U54: =IF($S$59=0,0,S54/$S$59) -> 0.68124294 | V54: =K54+O54-S54 -> -1725219.3 | X54: =IF($V$54="",0,V54/$V$59) -> 0.68151838
A55: Blt harina: | B55: =AE36 -> 36031.12 | C55: =B54/(B64*120) -> 1.0692038 | F55: Kw/tm trigo: | H55: =IF(G57="",0,G57/B54) -> 0 | M55: =IF($V$55="",0,K55/$V$59) -> 0 | O55: 0 | Q55: =IF($V$55="",0,O55/$V$59) -> 0 | R55: =IF(E84="","",E84) -> CPS | S55: =+SUMPRODUCT(B86:B110,E86:E110) -> 0 | U55: =IF($S$59=0,0,S55/$S$59) -> 0 | V55: =K55+O55-S55 -> 0 | X55: =IF($V$55="",0,V55/$V$59) -> 0
A56: Tm harina: | B56: =(B55*50)/1000 -> 1801.556 | F56: Kw/tm harina: | H56: =IF(G57="",0,G57/((B55*50)/1000)) -> 0 | M56: =IF($V$54="",0,K56/$V$59) -> 0 | O56: 683 | Q56: =IF($V$54="",0,O56/$V$59) -> -0.00026980746 | R56: HRW | S56: =+SUMPRODUCT(G86:G110,B86:B110) -> 540438.59 | U56: =IF($S$59=0,0,S56/$S$59) -> 0.21336627 | V56: =K56+O56-S56 -> -539755.59 | X56: =IF($V$54="",0,V56/$V$59) -> 0.21322121
A57: Extraccion: | B57: =IF(AF36="",0,AF36) -> 0.77319137 | F57: KW: | K57: 0 | M57: =IF($V$54="",0,L57/$V$59) -> 0 | O57: 486 | Q57: =IF($V$54="",0,O57/$V$59) -> -0.00019198598 | R57: SRW | S57: =+SUMPRODUCT(B86:B110,F86:F110) -> 266945.87 | U57: =IF($S$59=0,0,S57/$S$59) -> 0.10539078 | V57: =L57+O57-S57 -> -266459.87 | X57: =IF($V$54="",0,V57/$V$59) -> 0.10526041
A58: Hrs molienda: | B58: =AN36 -> 489.61 | F58: KVAR: | K58: 0 | M58: =IF($V$54="",0,L58/$V$59) -> 0 | O58: 0 | Q58: =IF($V$54="",0,O58/$V$59) -> 0 | R58: BIO | S58: =IF(AD47="",0,AD47) -> 0 | U58: =IF($S$59=0,0,S58/$S$59) -> 0 | V58: =L58+O58-S58 -> 0 | X58: =IF($V$54="",0,V58/$V$59) -> 0
A59: Hrs varada: | B59: =IF(B54=0,0,AP36/AN36) -> 0.02939074 | F59: Reactiva: | K59: =SUM(K54:K58) -> 0 | N59: =SUM(N54:N58) -> 0 | O59: =SUM(O54:O58) -> 1480 | S59: =SUM(S54:S58) -> 2532914.8 | V59: =SUM(V54:V58) -> -2531434.8
A60: % dia utilizado: | B60: =AT37 -> 0.97144841 | F60: Precio: | G60: 77284230 | I60: 2803509
A61: Capacidad utilizada: | B61: =+AT36 -> 0.78463141 | F61: Hz neumatico: | K61: Basculas
A62: Capacidad: | B62: =IF(AS36="",0,AS36) -> 114.21463 | K62: Tm Trigo T1: | M62: =AX36 -> 2373.408 | O62: tm
A63: Bultos hora: | B63: =IF(AU36="",0,AU36) -> 73.591471 | F63: Granza: | H63: kg. | K63: Bascula Harina: | M63: =AY36 -> 1837.104 | O63: tm
A64: Dias molienda: | B64: =31-COUNTBLANK(A4:A35) -> 20 | F64: % | G64: =G63/(B54*1000) -> 0 | K64: Extraccion: | M64: =M63/M62 -> 0.77403632 | T64: MYCE | Y64: AA | Z64: Granozyme | AA64: 900 | AB64: Alfa | AC64: 7200 | AD64: 4200 | AE64: 8530
A65: Total Ton de trig: | B65: =AD44+AD52 -> 2566.089 | G65: grf | T65: TRIGO | U65: =+AX4 -> 2373408 | X65: Extrapan 50 | Y65: 10 | Z65: 3 | AA65: 2.5 | AB65: 3 | AC65: 7 | AD65: 2
A66: Ton. molidas/persona: | B66: =B54/B71 -> 106.92037 | F66: Energia M.martillo | K66: Energia C.granel | T66: AGUA m3 | U66: =AZ4 -> 69185 | X66: Extrapan 25 | Y66: 5 | Z66: 1.5 | AA66: 1.25 | AB66: 1.5 | AC66: 3.5 | AD66: 1
A67: Valor tonelada/nomina: | B67: =B79/B54 -> 24964.931 | F67: Ton Molidas | K67: Ton despachadas | O67: 662 | X67: Extrapan 10 | Y67: 2 | Z67: 0.6 | AA67: 0.5 | AB67: 0.6 | AC67: 1.4 | AD67: 0.4
A68: Valor ton/Horas extras: | B68: =B80/B54 -> 3054.2323 | F68: Tiempo de cargue | H68: =(H67*1)*2 -> 0 | K68: Tiempo de cargue | O68: =O67/30 -> 22.066667 | T68: Flowbalancer | X68: Artesanal 50 | Y68: 10 | Z68: 3 | AA68: 0 | AB68: 6 | AC68: 7 | AD68: 0
F69: TRIGO | K69: HARINA | T69: CRWS | U69: =+BC4 -> 123963750 | X69: Exclusiva 25 | Y69: 0 | Z69: 0 | AA69: 0 | AB69: 0 | AC69: 0 | AD69: 0
A70: Datos Generales | F70: HRW | K70: SRW | T70: CPS / HRW | U70: =+BF4+BD4 -> 52909909 | X70: Harina de alta proteina x 1 G | Y70: 0 | Z70: 0 | AA70: 0 | AB70: 0 | AC70: 0 | AD70: 0
A71: Personal de planta | B71: 24 | F71: AMP | H71: =H68*G71 -> 0 | K71: AMP | L71: 100 | M71: =(O68*L71) -> 2206.6667 | T71: SRW | U71: =+BE4 -> 39502680 | X71: Total | Y71: =+SUM(Y65:Y70) -> 27 | Z71: =+SUM(Z65:Z70) -> 8.1 | AA71: =+SUM(AA65:AA70) -> 4.25 | AB71: =+SUM(AB65:AB70) -> 11.1 | AC71: =+SUM(AC65:AC70) -> 18.9 | AD71: =+SUM(AD65:AD70) -> 3.4
A72: Cuota de ventas | B72: 28760 | F72: KW/H | G72: =(G71*436*1.7321*0.96)/1000 -> 0 | H72: =(H71*436*1.7321*0.96)/1000 -> 0 | K72: KW/H | L72: =(L71*436*1.7321*0.96)/1000 -> 72.498778 | T72: OTROS | U72: 0 | X72: Fisico
A73: Ventas reales | B73: 36087 | F73: KW Total | G73: =G72*H67 -> 0 | K73: KW Total | M73: =L72*O68 -> 1599.8064
A74: % de cumplimiento Proy | B74: =+B55/B72 -> 1.2528206 | F74: Precio Kw: | H74: =G73*H54 -> 0 | K74: Precio Kw: | M74: =M73*H54 -> 0 | T74: VALOR X HORA DE VARADA
A75: % de cumplimiento Real | B75: =+B55/B73 -> 0.99845152 | T75: Mob | V75: =AP36*(U75+U76) -> 0 | Y75: Vitamina | Z75: COP | AA75: EXP
T76: Cif | Y76: gr/blt | Z76: 12.5 | AA76: 13.5 | AC76: gr/blt
Y77: Total | Z77: =SUM(A86:A110)*Z76 -> 502882.75 | AA77: =(A97+#REF!)*AA76 -> #REF! | AC77: gr.
A78: Datos Nomina Producción | Y78: Fisico | AC78: gr.
A79: Nomina | B79: 64062235
A80: Horas extras | B80: 7837432
D84: CWRS | E84: CPS | F84: SRW | G84: HRW
A85: Harina | B85: trigo | C85: Codigo | D85: % | E85: % | F85: % | G85: %
A86: =+C38 -> 9763 | B86: =IF(A86=0,0,((A86*50)/$B$57)) -> 631344.34 | C86: Extrapan 50 | D86: 0.7 | E86: 0 | G86: 0.3 | H86: =G86+F86+E86+D86 -> 1
A87: =+C39 -> 346 | B87: =IF(A87=0,0,((A87*50)/$B$57)) -> 22374.797 | C87: Extrapan 50 | D87: 0.6 | E87: 0 | F87: 0 | G87: 0.4
A88: =+D38/2 -> 771 | B88: =IF(A88=0,0,((A88*50)/$B$57)) -> 49858.29 | C88: Extrapan 25 | D88: 0.7 | E88: 0 | G88: 0.3
A89: =+D39/2 -> 0 | B89: =IF(A89=0,0,((A89*50)/$B$57)) -> 0 | C89: Extrapan 25 | D89: 0.6 | E89: 0 | F89: 0 | G89: 0.4
A90: =+E38/5 -> 39.8 | B90: =IF(A90=0,0,((A90*50)/$B$57)) -> 2573.7483 | C90: Extrapan 10 | D90: 0.7 | E90: 0 | G90: 0.3
A91: =+E39/5 -> 0 | B91: =IF(A91=0,0,((A91*50)/$B$57)) -> 0 | C91: Extrapan 10 | D91: 0.6 | E91: 0 | F91: 0 | G91: 0.4
A92: =+F38 -> 855 | B92: =IF(A92=0,0,((A92*50)/$B$57)) -> 55290.322 | C92: =F3 -> Artesanal 50 | D92: 0.52 | E92: 0 | F92: 0.25 | G92: 0.23
A93: =G38/2 -> 199 | B93: =IF(A93=0,0,((A93*50)/$B$57)) -> 12868.742 | C93: =G3 -> Artesanal 25 | D93: 0.52 | E93: 0 | F93: 0.25 | G93: 0.23
A94: =H38 -> 0 | B94: =IF(A94=0,0,((A94*50)/$B$57)) -> 0 | C94: =H3 -> Natural 50 | D94: 0.63 | E94: 0 | F94: 0.14 | G94: 0.23
A96: =I36/2 -> 3363.5 | B96: =IF(A96=0,0,((A96*50)/$B$57)) -> 217507.6 | C96: =I3 -> Fuerte 25 | D96: 0.52 | E96: 0 | F96: 0.23 | G96: 0.25
A97: =J38/2 -> 40 | B97: =IF(A97=0,0,((A97*50)/$B$57)) -> 2586.6817 | C97: =J3 -> Fuerte exp 25 | D97: 0.52 | E97: 0 | F97: 0.23 | G97: 0.25
A98: =K38 -> 0 | B98: =IF(A98=0,0,((A98*50)/$B$57)) -> 0 | C98: =K3 -> Exclusiva 50 | D98: 0.53 | E98: 0 | F98: 0.22 | G98: 0.25
A99: =L38/2 -> 0 | B99: =IF(A99=0,0,((A99*50)/$B$57)) -> 0 | C99: =+L3 -> Exclusiva 25 | D99: 0.53 | E99: 0 | F99: 0.22 | G99: 0.25
A100: =Q38 -> 0 | B100: =IF(A100=0,0,((A100*50)/$B$57)) -> 0 | C100: =Q3 -> ESPECIAL 50 | D100: 0 | E100: 0 | F100: 1 | G100: 0
A101: =R38/50 -> 7296.96 | B101: =IF(A101=0,0,((A101*50)/$B$57)) -> 471872.83 | C101: =R3 -> Harina de alta proteina x 1 G | D101: 0.85 | E101: 0 | F101: 0 | G101: 0.15
A102: =R39/50 -> 9218.68 | B102: =IF(A102=0,0,((A102*50)/$B$57)) -> 596144.78 | C102: =R3 -> Harina de alta proteina x 1 G | D102: 0.75 | E102: 0 | F102: 0 | G102: 0.25
A103: =S38/50 -> 2492.48 | B103: =IF(A103=0,0,((A103*50)/$B$57)) -> 161181.31 | C103: =S3 -> Harina de baja proteina x 1 | F103: 1
A104: =T38/50 -> 895.2 | B104: =IF(A104=0,0,((A104*50)/$B$57)) -> 57889.937 | C104: =T3 -> ARTESANAL X 1 G | D104: 0.53 | E104: 0 | F104: 0.22 | G104: 0.25
A105: =U36/2 -> 237.5 | B105: =IF(A105=0,0,((A105*50)/$B$57)) -> 15358.423 | C105: =U3 -> H. espcial x 25 | E105: 0 | F105: 1
B106: =IF(A106=0,0,((A106*50)/$B$57)) -> 0
A107: =AA46/2 -> 67.5 | B107: =IF(A107=0,0,((A107*51.6))) -> 3483 | C107: =A46 -> Grano entero | D107: 0.7 | E107: 0 | F107: 0 | G107: 0.3
A108: =Z47/2 -> 0 | B108: =IF(A108=0,0,((A108*50)/$B$57)) -> 0 | C108: =A47 -> Bio Convercion
A109: =AA48/2 -> 4045 | B109: =IF(A109=0,0,((A109*50))) -> 202250 | C109: =A49 -> Trigo entero | D109: 1
...

Sheet MAR
B1: Producción | AH1: Extracción | AN1: Indicadores
B2: HARINA EN BULTO | R2: HARINA GRANEL | U2: P. EXP | V2: REPASO | X2: ESPECIAL | AA2: SUBPRODUCTO | AF2: EXTRACION | AN2: HORAS | AQ2: INDICACORES MOLINO | AV2: MOJADORA | AW2: EQUIPOS ELECTRONICOS
A3: Dia | B3: Fecha | C3: Extrapan 50 | D3: Extrapan 25 | E3: Extrapan 10 | F3: Artesanal 50 | G3: Artesanal 25 | H3: Natural 50 | I3: Fuerte 25 | J3: Fuerte exp 25 | K3: Exclusiva 50 | L3: Exclusiva 25 | M3: S. Sal 25 | N3: Harina Tortas y Ponques | O3: Harina Galeras Ligera | P3: Harina Manitoba | Q3: ESPECIAL 50 | R3: Harina de alta proteina x 1 G | S3: Harina de baja proteina x 1 | T3: ARTESANAL X 1 G | U3: H. espcial x 25 | V3: + Repaso | W3: - Reproceso | X3: Germen 25 | Y3: Semola 25 | Z3: Grano entero 25 | AA3: Salvado 25 | AB3: Mogolla 40 | AC3: Segunda 50 | AD3: Total trigo | AE3: Total Bultos | AF3: Harina | AG3: Grano entero partido | AH3: =X3 -> Germen 25 | AI3: Semola | AJ3: =AA3 -> Salvado 25 | AK3: =AB3 -> Mogolla 40 | AL3: =AC3 -> Segunda 50 | AM3: =B3 -> Fecha | AN3: Molienda | AO3: moje | AP3: Horas varada | AQ3: Molido/ Mojado | AR3: Capacidad TM. hora | AS3: Capacidad TM. Día | AT3: % Utilizado | AU3: Bultos Hora | AV3: capacidad TM. hora | AW3: MYFC | AX3: Bascula Trigo | AY3: Bascula Harina | AZ3: Agua M³ | BA3: Bascula Mejorante A | BB3: Bascula Mejorante B | BC3: Flowbalacer 1 | BD3: Flowbalacer 2 | BE3: Flowbalacer 3 | BF3: Flowbalacer 4
A4: =IF(B4="","",1) -> 1 | B4: 46083 | C4: 1040 | D4: 0 | E4: 100 | I4: 1729 | R4: 52065 | Y4: 10 | AA4: 123 | AB4: 406 | AC4: 57 | AD4: =IF(B4="","",(((C4+F4+H4+K4+Q4+N4+O4)*50))+((E4*10))+(((I4+J4+D4+G4+L4+M4+U4)*25)+(X4*25)+(Y4*25)+(Z4*25)+(AA4*25)+(AB4*40)+(AC4*50)+(R4*1)+(S4*1)+(T4*1))) -> 170705 | AE4: =IF(B4="","",C4+F4+H4+K4+Q4+N4+O4+((I4+J4+D4+G4)/2)+(R4/50)+(S4/50)+(T4/50)+(U4/2)+(E4/5)) -> 2965.8 | AF4: =IF(B4="","",((AE4*50)/AD4)) -> 0.8686916 | AG4: =IF(C4="","",((Z4)*25)/AD4) -> 0 | AH4: =IF(B4="","",(X4*25)/AD4) -> 0 | AI4: =IF(B4="","",(Y4*25)/AD4) -> 0.0014645148 | AJ4: =IF(B4="","",(AA4*25)/AD4) -> 0.018013532 | AK4: =IF(B4="","",(AB4*40)/AD4) -> 0.095134882 | AL4: =IF(B4="","",(AC4*50)/AD4) -> 0.016695469 | AM4: =IF(B4="","",B4) -> 46083 | AN4: 24 | AO4: =+AN4-AP4 -> 24 | AP4: 0 | AQ4: =IF(AN4="","",AN4/AO4) -> 1 | AR4: =IF(AN4="","",(AD4/AN4)/1000) -> 7.1127083 | AS4: =IF(AN4="","",AR4*24) -> 170.705 | AT4: =IF(AN4="","",(AD4/1000)*100%/AS4) -> 1 | AU4: =IF(AN4="","",(AE4/AN4)) -> 123.575 | AV4: =IF(AN4="","",(AD4/AO4)/1000) -> 7.1127083 | AX4: 2397600 | AY4: 1869488 | AZ4: 537016 | BA4: 59372 | BB4: 372195 | BC4: 1400504 | BD4: 30058 | BE4: 409380 | BF4: 811544
A5: =IF(B5="","",2) -> 2 | B5: 46084 | C5: 1040 | D5: 999 | I5: 301 | R5: 2288 | Y5: 12 | AA5: 49 | AB5: 245 | AC5: 50 | AD5: =IF(B5="","",(((C5+F5+H5+K5+Q5+N5+O5)*50))+((E5*10))+(((I5+J5+D5+G5+L5+M5+U5)*25)+(X5*25)+(Y5*25)+(Z5*25)+(AA5*25)+(AB5*40)+(AC5*50)+(R5*1)+(S5*1)+(T5*1))) -> 100613 | AE5: =IF(B5="","",C5+F5+H5+K5+Q5+N5+O5+((I5+J5+D5+G5+U5)/2)+(R5/50)+(S5/50)+(T5/50)+(E5/5)) -> 1735.76 | AF5: =IF(B5="","",((AE5*50)/AD5)) -> 0.86259231 | AG5: =IF(C5="","",((Z5)*25)/AD5) -> 0 | AH5: =IF(B5="","",(X5*25)/AD5) -> 0 | AI5: =IF(B5="","",(Y5*25)/AD5) -> 0.002981722 | AJ5: =IF(B5="","",(AA5*25)/AD5) -> 0.012175365 | AK5: =IF(B5="","",(AB5*40)/AD5) -> 0.09740292 | AL5: =IF(B5="","",(AC5*50)/AD5) -> 0.024847684 | AM5: =IF(B5="","",B5) -> 46084 | AN5: 24 | AO5: =+AN5-AP5 -> 24 | AP5: 0 | AQ5: =IF(AN5="","",AN5/AO5) -> 1 | AR5: =IF(AN5="","",(AD5/AN5)/1000) -> 4.1922083 | AS5: =IF(AN5="","",AR5*24) -> 100.613 | AT5: =IF(AN5="","",(AD5/1000)*100%/AS5) -> 1 | AU5: =IF(AN5="","",(AE5/AN5)) -> 72.323333 | AV5: =IF(AN5="","",(AD5/AO5)/1000) -> 4.1922083
A6: =IF(B6="","",3) -> 3 | B6: 46085 | C6: 1040 | F6: 310 | G6: 300 | J6: 80 | L6: 1013 | R6: 73763 | S6: 23760 | Y6: 28 | AA6: 207 | AB6: 250 | AC6: 58 | AD6: =IF(B6="","",(((C6+F6+H6+K6+Q6+N6+O6)*50))+((E6*10))+(((I6+J6+D6+G6+L6+M6+U6)*25)+(X6*25)+(Y6*25)+(Z6*25)+(AA6*25)+(AB6*40)+(AC6*50)+(R6*1)+(S6*1)+(T6*1))) -> 218623 | AE6: =IF(B6="","",C6+F6+H6+K6+Q6+N6+O6+((I6+J6+D6+G6+U6)/2)+(R6/50)+(S6/50)+(T6/50)+(E6/5)) -> 3490.46 | AF6: =IF(B6="","",((AE6*50)/AD6)) -> 0.79828289 | AG6: =IF(C6="","",((Z6)*25)/AD6) -> 0 | AH6: =IF(B6="","",(X6*25)/AD6) -> 0 | AI6: =IF(B6="","",(Y6*25)/AD6) -> 0.0032018589 | AJ6: =IF(B6="","",(AA6*25)/AD6) -> 0.023670885 | AK6: =IF(B6="","",(AB6*40)/AD6) -> 0.045740842 | AL6: =IF(B6="","",(AC6*50)/AD6) -> 0.013264844 | AM6: =IF(B6="","",B6) -> 46085 | AN6: 24 | AO6: =+AN6-AP6 -> 23.833333 | AP6: 0.16666667 | AQ6: =IF(AN6="","",AN6/AO6) -> 1.006993 | AR6: =IF(AN6="","",(AD6/AN6)/1000) -> 9.1092917 | AS6: =IF(AN6="","",AR6*24) -> 218.623 | AT6: =IF(AN6="","",(AD6/1000)*100%/AS6) -> 1 | AU6: =IF(AN6="","",(AE6/AN6)) -> 145.43583 | AV6: =IF(AN6="","",(AD6/AO6)/1000) -> 9.172993
A7: =IF(B7="","",4) -> 4 | B7: 46086 | C7: 1880 | D7: 40 | I7: 381 | R7: 59424 | Y7: 33 | AA7: 148 | AB7: 265 | AC7: 55 | AD7: =IF(B7="","",(((C7+F7+H7+K7+Q7+N7+O7)*50))+((E7*10))+(((I7+J7+D7+G7+L7+M7+U7)*25)+(X7*25)+(Y7*25)+(Z7*25)+(AA7*25)+(AB7*40)+(AC7*50)+(R7*1)+(S7*1)+(T7*1))) -> 181824 | AE7: =IF(B7="","",C7+F7+H7+K7+Q7+N7+O7+((I7+J7+D7+G7+U7)/2)+(R7/50)+(S7/50)+(T7/50)+(E7/5)) -> 3278.98 | AF7: =IF(B7="","",((AE7*50)/AD7)) -> 0.90169065 | AG7: =IF(C7="","",((Z7)*25)/AD7) -> 0 | AH7: =IF(B7="","",(X7*25)/AD7) -> 0 | AI7: =IF(B7="","",(Y7*25)/AD7) -> 0.0045373548 | AJ7: =IF(B7="","",(AA7*25)/AD7) -> 0.020349349 | AK7: =IF(B7="","",(AB7*40)/AD7) -> 0.058298134 | AL7: =IF(B7="","",(AC7*50)/AD7) -> 0.015124516 | AM7: =IF(B7="","",B7) -> 46086 | AN7: 24 | AO7: =+AN7-AP7 -> 23.666667 | AP7: 0.33333333 | AQ7: =IF(AN7="","",AN7/AO7) -> 1.0140845 | AR7: =IF(AN7="","",(AD7/AN7)/1000) -> 7.576 | AS7: =IF(AN7="","",AR7*24) -> 181.824 | AT7: =IF(AN7="","",(AD7/1000)*100%/AS7) -> 1 | AU7: =IF(AN7="","",(AE7/AN7)) -> 136.62417 | AV7: =IF(AN7="","",(AD7/AO7)/1000) -> 7.6827042
A8: =IF(B8="","",5) -> 5 | B8: 46087 | C8: 1440 | E8: 581 | F8: =220+40 -> 260 | I8: 1699 | R8: 52336 | S8: 22496 | AA8: 237 | AB8: 183 | AC8: 35 | AD8: =IF(B8="","",(((C8+F8+H8+K8+Q8+N8+O8)*50))+((E8*10))+(((I8+J8+D8+G8+L8+M8+U8)*25)+(X8*25)+(Y8*25)+(Z8*25)+(AA8*25)+(AB8*40)+(AC8*50)+(R8*1)+(S8*1)+(T8*1))) -> 223112 | AE8: =IF(B8="","",C8+F8+H8+K8+Q8+N8+O8+((I8+J8+D8+G8+U8)/2)+(R8/50)+(S8/50)+(T8/50)+(E8/5)) -> 4162.34 | AF8: =IF(B8="","",((AE8*50)/AD8)) -> 0.9327916 | AG8: =IF(C8="","",((Z8)*25)/AD8) -> 0 | AH8: =IF(B8="","",(X8*25)/AD8) -> 0 | AI8: =IF(B8="","",(Y8*25)/AD8) -> 0 | AJ8: =IF(B8="","",(AA8*25)/AD8) -> 0.026556169 | AK8: =IF(B8="","",(AB8*40)/AD8) -> 0.032808634 | AL8: =IF(B8="","",(AC8*50)/AD8) -> 0.0078435942 | AM8: =IF(B8="","",B8) -> 46087 | AN8: 24 | AO8: =+AN8-AP8 -> 23.833333 | AP8: 0.16666667 | AQ8: =IF(AN8="","",AN8/AO8) -> 1.006993 | AR8: =IF(AN8="","",(AD8/AN8)/1000) -> 9.2963333 | AS8: =IF(AN8="","",AR8*24) -> 223.112 | AT8: =IF(AN8="","",(AD8/1000)*100%/AS8) -> 1 | AU8: =IF(AN8="","",(AE8/AN8)) -> 173.43083 | AV8: =IF(AN8="","",(AD8/AO8)/1000) -> 9.3613427
A9: =IF(B9="","",6) -> 6 | B9: 46090 | C9: 0 | D9: 997 | F9: 30 | I9: 846 | J9: 200 | K9: 601 | R9: 78176 | Y9: 38 | AA9: 210 | AB9: 295 | AC9: 55 | AD9: =IF(B9="","",(((C9+F9+H9+K9+Q9+N9+O9+P9)*50))+((E9*10))+(((I9+J9+D9+G9+L9+M9+U9)*25)+(X9*25)+(Y9*25)+(Z9*25)+(AA9*25)+(AB9*40)+(AC9*50)+(R9*1)+(S9*1)+(T9*1))) -> 181551 | AE9: =IF(B9="","",C9+F9+H9+K9+Q9+N9+O9+((I9+J9+D9+G9+U9)/2)+(R9/50)+(S9/50)+(T9/50)+(E9/5)) -> 3216.02 | AF9: =IF(B9="","",((AE9*50)/AD9)) -> 0.88570705 | AG9: =IF(C9="","",((Z9)*25)/AD9) -> 0 | AH9: =IF(B9="","",(X9*25)/AD9) -> 0 | AI9: =IF(B9="","",(Y9*25)/AD9) -> 0.0052326894 | AJ9: =IF(B9="","",(AA9*25)/AD9) -> 0.028917494 | AK9: =IF(B9="","",(AB9*40)/AD9) -> 0.064995511 | AL9: =IF(B9="","",(AC9*50)/AD9) -> 0.015147259 | AM9: =IF(B9="","",B9) -> 46090 | AN9: 24 | AO9: =+AN9-AP9 -> 23.75 | AP9: 0.25 | AQ9: =IF(AN9="","",AN9/AO9) -> 1.0105263 | AR9: =IF(AN9="","",(AD9/AN9)/1000) -> 7.564625 | AS9: =IF(AN9="","",AR9*24) -> 181.551 | AT9: =IF(AN9="","",(AD9/1000)*100%/AS9) -> 1 | AU9: =IF(AN9="","",(AE9/AN9)) -> 134.00083 | AV9: =IF(AN9="","",(AD9/AO9)/1000) -> 7.6442526
A10: =IF(B10="","",7) -> 7 | B10: 46091 | C10: 1090 | D10: 995 | F10: 327 | G10: 198 | H10: =11+490 -> 501 | I10: 265 | K10: =160+99 -> 259 | R10: 24080 | AA10: 194 | AB10: 190 | AC10: 40 | AD10: =IF(B10="","",(((C10+F10+H10+K10+Q10+N10+O10)*50))+((E10*10))+(((I10+J10+D10+G10+L10+M10+U10)*25)+(X10*25)+(Y10*25)+(Z10*25)+(AA10*25)+(AB10*40)+(AC10*50)+(R10*1)+(S10*1)+(T10*1))) -> 183830 | AE10: =IF(B10="","",C10+F10+H10+K10+Q10+N10+O10+((I10+J10+D10+G10+U10)/2)+(R10/50)+(S10/50)+(T10/50)+(E10/5)) -> 3387.6 | AF10: =IF(B10="","",((AE10*50)/AD10)) -> 0.92139477 | AG10: =IF(C10="","",((Z10)*25)/AD10) -> 0 | AH10: =IF(B10="","",(X10*25)/AD10) -> 0 | AI10: =IF(B10="","",(Y10*25)/AD10) -> 0 | AJ10: =IF(B10="","",(AA10*25)/AD10) -> 0.026383071 | AK10: =IF(B10="","",(AB10*40)/AD10) -> 0.041342545 | AL10: =IF(B10="","",(AC10*50)/AD10) -> 0.010879617 | AM10: =IF(B10="","",B10) -> 46091 | AN10: 24 | AO10: =+AN10-AP10 -> 24 | AP10: 0 | AQ10: =IF(AN10="","",AN10/AO10) -> 1 | AR10: =IF(AN10="","",(AD10/AN10)/1000) -> 7.6595833 | AS10: =IF(AN10="","",AR10*24) -> 183.83 | AT10: =IF(AN10="","",(AD10/1000)*100%/AS10) -> 1 | AU10: =IF(AN10="","",(AE10/AN10)) -> 141.15 | AV10: =IF(AN10="","",(AD10/AO10)/1000) -> 7.6595833
A11: =IF(B11="","",8) -> 8 | B11: 46092 | C11: 1310 | D11: 466 | F11: 141 | G11: 300 | I11: 1700 | K11: 145 | L11: 500 | R11: 50160 | T11: 20160 | AA11: 242 | AB11: 270 | AC11: 50 | AD11: =IF(B11="","",(((C11+F11+H11+K11+Q11+N11+O11)*50))+((E11*10))+(((I11+J11+D11+G11+L11+M11+U11)*25)+(X11*25)+(Y11*25)+(Z11*25)+(AA11*25)+(AB11*40)+(AC11*50)+(R11*1)+(S11*1)+(T11*1))) -> 243620 | AE11: =IF(B11="","",C11+F11+H11+K11+Q11+N11+O11+((I11+J11+D11+G11+U11)/2)+(R11/50)+(S11/50)+(T11/50)+(E11/5)) -> 4235.4 | AF11: =IF(B11="","",((AE11*50)/AD11)) -> 0.86926361 | AG11: =IF(C11="","",((Z11)*25)/AD11) -> 0 | AH11: =IF(B11="","",(X11*25)/AD11) -> 0 | AI11: =IF(B11="","",(Y11*25)/AD11) -> 0 | AJ11: =IF(B11="","",(AA11*25)/AD11) -> 0.024833757 | AK11: =IF(B11="","",(AB11*40)/AD11) -> 0.044331336 | AL11: =IF(B11="","",(AC11*50)/AD11) -> 0.010261883 | AM11: =IF(B11="","",B11) -> 46092 | AN11: 24 | AO11: =+AN11-AP11 -> 23.666667 | AP11: 0.33333333 | AQ11: =IF(AN11="","",AN11/AO11) -> 1.0140845 | AR11: =IF(AN11="","",(AD11/AN11)/1000) -> 10.150833 | AS11: =IF(AN11="","",AR11*24) -> 243.62 | AT11: =IF(AN11="","",(AD11/1000)*100%/AS11) -> 1 | AU11: =IF(AN11="","",(AE11/AN11)) -> 176.475 | AV11: =IF(AN11="","",(AD11/AO11)/1000) -> 10.293803
A12: =IF(B12="","",9) -> 9 | B12: 46093 | C12: 1070 | D12: 529 | F12: 208 | I12: 1027 | K12: 246 | L12: 500 | R12: 6112 | S12: 24966 | AA12: 219 | AB12: 245 | AC12: 60 | AD12: =IF(B12="","",(((C12+F12+H12+K12+Q12+N12+O12)*50))+((E12*10))+(((I12+J12+D12+G12+L12+M12+U12)*25)+(X12*25)+(Y12*25)+(Z12*25)+(AA12*25)+(AB12*40)+(AC12*50)+(R12*1)+(S12*1)+(T12*1))) -> 176953 | AE12: =IF(B12="","",C12+F12+H12+K12+Q12+N12+O12+((I12+J12+D12+G12+U12)/2)+(R12/50)+(S12/50)+(T12/50)+(E12/5)) -> 2923.56 | AF12: =IF(B12="","",((AE12*50)/AD12)) -> 0.82608376 | AG12: =IF(C12="","",((Z12)*25)/AD12) -> 0 | AH12: =IF(B12="","",(X12*25)/AD12) -> 0 | AI12: =IF(B12="","",(Y12*25)/AD12) -> 0 | AJ12: =IF(B12="","",(AA12*25)/AD12) -> 0.030940419 | AK12: =IF(B12="","",(AB12*40)/AD12) -> 0.055381938 | AL12: =IF(B12="","",(AC12*50)/AD12) -> 0.016953654 | AM12: =IF(B12="","",B12) -> 46093 | AN12: 24 | AO12: =+AN12-AP12 -> 22.25 | AP12: 1.75 | AQ12: =IF(AN12="","",AN12/AO12) -> 1.0786517 | AR12: =IF(AN12="","",(AD12/AN12)/1000) -> 7.3730417 | AS12: =IF(AN12="","",AR12*24) -> 176.953 | AT12: =IF(AN12="","",(AD12/1000)*100%/AS12) -> 1 | AU12: =IF(AN12="","",(AE12/AN12)) -> 121.815 | AV12: =IF(AN12="","",(AD12/AO12)/1000) -> 7.9529438
A13: =IF(B13="","",11) -> 11 | B13: 46094 | C13: 1030 | E13: 100 | R13: 96016 | S13: 49200 | AA13: 218 | AB13: 379 | AC13: 565 | AD13: =IF(B13="","",(((C13+F13+H13+K13+Q13+N13+O13)*50))+((E13*10))+(((I13+J13+D13+G13+L13+M13+U13)*25)+(X13*25)+(Y13*25)+(Z13*25)+(AA13*25)+(AB13*40)+(AC13*50)+(R13*1)+(S13*1)+(T13*1))) -> 246576 | AE13: =IF(B13="","",C13+F13+H13+K13+Q13+N13+O13+((I13+J13+D13+G13+U13)/2)+(R13/50)+(S13/50)+(T13/50)+(E13/5)) -> 3954.32 | AF13: =IF(B13="","",((AE13*50)/AD13)) -> 0.80184608 | AG13: =IF(C13="","",((Z13)*25)/AD13) -> 0 | AH13: =IF(B13="","",(X13*25)/AD13) -> 0 | AI13: =IF(B13="","",(Y13*25)/AD13) -> 0 | AJ13: =IF(B13="","",(AA13*25)/AD13) -> 0.022102719 | AK13: =IF(B13="","",(AB13*40)/AD13) -> 0.061482058 | AL13: =IF(B13="","",(AC13*50)/AD13) -> 0.11456914 | AM13: =IF(B13="","",B13) -> 46094 | AN13: 24 | AO13: =+AN13-AP13 -> 23.416667 | AP13: 0.58333333 | AQ13: =IF(AN13="","",AN13/AO13) -> 1.024911 | AR13: =IF(AN13="","",(AD13/AN13)/1000) -> 10.274 | AS13: =IF(AN13="","",AR13*24) -> 246.576 | AT13: =IF(AN13="","",(AD13/1000)*100%/AS13) -> 1 | AU13: =IF(AN13="","",(AE13/AN13)) -> 164.76333 | AV13: =IF(AN13="","",(AD13/AO13)/1000) -> 10.529936
A14: =IF(B14="","",12) -> 12 | B14: 46097 | C14: 270 | D14: 897 | F14: 900 | G14: 200 | K14: 297 | L14: 644 | R14: 41168 | S14: 24080 | AA14: 254 | AB14: 230 | AC14: 60 | AD14: =IF(B14="","",(((C14+F14+H14+K14+Q14+N14+O14)*50))+((E14*10))+(((I14+J14+D14+G14+L14+M14+U14)*25)+(X14*25)+(Y14*25)+(Z14*25)+(AA14*25)+(AB14*40)+(AC14*50)+(R14*1)+(S14*1)+(T14*1))) -> 200673 | AE14: =IF(B14="","",C14+F14+H14+K14+Q14+N14+O14+((I14+J14+D14+G14+U14)/2)+(R14/50)+(S14/50)+(T14/50)+(E14/5)) -> 3320.46 | AF14: =IF(B14="","",((AE14*50)/AD14)) -> 0.82733103 | AG14: =IF(C14="","",((Z14)*25)/AD14) -> 0 | AH14: =IF(B14="","",(X14*25)/AD14) -> 0 | AI14: =IF(B14="","",(Y14*25)/AD14) -> 0 | AJ14: =IF(B14="","",(AA14*25)/AD14) -> 0.03164352 | AK14: =IF(B14="","",(AB14*40)/AD14) -> 0.045845729 | AL14: =IF(B14="","",(AC14*50)/AD14) -> 0.014949694 | AM14: =IF(B14="","",B14) -> 46097 | AN14: 24 | AO14: =+AN14-AP14 -> 23.416667 | AP14: 0.58333333 | AQ14: =IF(AN14="","",AN14/AO14) -> 1.024911 | AR14: =IF(AN14="","",(AD14/AN14)/1000) -> 8.361375 | AS14: =IF(AN14="","",AR14*24) -> 200.673 | AT14: =IF(AN14="","",(AD14/1000)*100%/AS14) -> 1 | AU14: =IF(AN14="","",(AE14/AN14)) -> 138.3525 | AV14: =IF(AN14="","",(AD14/AO14)/1000) -> 8.5696655
A15: =IF(B15="","",13) -> 13 | B15: 46098 | C15: 1040 | R15: 33936 | AA15: 97 | AB15: 206 | AC15: 45 | AD15: =IF(B15="","",(((C15+F15+H15+K15+Q15+N15+O15)*50))+((E15*10))+(((I15+J15+D15+G15+L15+M15+U15)*25)+(X15*25)+(Y15*25)+(Z15*25)+(AA15*25)+(AB15*40)+(AC15*50)+(R15*1)+(S15*1)+(T15*1))) -> 98851 | AE15: =IF(B15="","",C15+F15+H15+K15+Q15+N15+O15+((I15+J15+D15+G15+U15)/2)+(R15/50)+(S15/50)+(T15/50)+(E15/5)) -> 1718.72 | AF15: =IF(B15="","",((AE15*50)/AD15)) -> 0.86934882 | AG15: =IF(C15="","",((Z15)*25)/AD15) -> 0 | AH15: =IF(B15="","",(X15*25)/AD15) -> 0 | AI15: =IF(B15="","",(Y15*25)/AD15) -> 0 | AJ15: =IF(B15="","",(AA15*25)/AD15) -> 0.024531871 | AK15: =IF(B15="","",(AC15*40)/AD15) -> 0.018209224 | AL15: =IF(B15="","",(AC15*50)/AD15) -> 0.02276153 | AM15: =IF(B15="","",B15) -> 46098 | AN15: 24 | AO15: =+AN15-AP15 -> 16.333333 | AP15: 7.6666667 | AQ15: =IF(AN15="","",AN15/AO15) -> 1.4693878 | AR15: =IF(AN15="","",(AD15/AN15)/1000) -> 4.1187917 | AS15: =IF(AN15="","",AR15*24) -> 98.851 | AT15: =IF(AN15="","",(AD15/1000)*100%/AS15) -> 1 | AU15: =IF(AN15="","",(AE15/AN15)) -> 71.613333 | AV15: =IF(AN15="","",(AD15/AO15)/1000) -> 6.052102
A16: =IF(B16="","",1+A15) -> 14 | B16: 46099 | C16: 100 | F16: 900 | I16: 524 | J16: 80 | R16: 26944 | S16: 46496 | AA16: 141 | AB16: 305 | AC16: 45 | AD16: =IF(B16="","",(((C16+F16+H16+K16+Q16+N16+O16)*50))+((E16*10))+(((I16+J16+D16+G16+L16+M16+U16)*25)+(X16*25)+(Y16*25)+(Z16*25)+(AA16*25)+(AB16*40)+(AC16*50)+(R16*1)+(S16*1)+(T16*1))) -> 156515 | AE16: =IF(B16="","",C16+F16+H16+K16+Q16+N16+O16+((I16+J16+D16+G16+U16)/2)+(R16/50)+(S16/50)+(T16/50)+(E16/5)) -> 2770.8 | AF16: =IF(B16="","",((AE16*50)/AD16)) -> 0.88515478 | AG16: =IF(C16="","",((Z16)*25)/AD16) -> 0 | AH16: =IF(B16="","",(X16*25)/AD16) -> 0 | AI16: =IF(B16="","",(Y16*25)/AD16) -> 0 | AJ16: =IF(B16="","",(AA16*25)/AD16) -> 0.022521803 | AK16: =IF(B16="","",(AB16*40)/AD16) -> 0.077947801 | AL16: =IF(B16="","",(AC16*50)/AD16) -> 0.014375619 | AM16: =IF(B16="","",B16) -> 46099 | AN16: 24 | AO16: =+AN16-AP16 -> 24 | AP16: 0 | AQ16: =IF(AN16="","",AN16/AO16) -> 1 | AR16: =IF(AN16="","",(AD16/AN16)/1000) -> 6.5214583 | AS16: =IF(AN16="","",AR16*24) -> 156.515 | AT16: =IF(AN16="","",(AD16/1000)*100%/AS16) -> 1 | AU16: =IF(AN16="","",(AE16/AN16)) -> 115.45 | AV16: =IF(AN16="","",(AD16/AO16)/1000) -> 6.5214583
A17: =IF(B17="","",15) -> 15 | B17: 46100 | C17: 527 | F17: 500 | G17: 397 | H17: 360 | I17: 659 | J17: 140 | R17: 28160 | AA17: 165 | AB17: 407 | AC17: 14 | AD17: =IF(B17="","",(((C17+F17+H17+K17+Q17+N17+O17)*50))+((E17*10))+(((I17+J17+D17+G17+L17+M17+U17)*25)+(X17*25)+(Y17*25)+(Z17*25)+(AA17*25)+(AB17*40)+(AC17*50)+(R17*1)+(S17*1)+(T17*1))) -> 148515 | AE17: =IF(B17="","",C17+F17+H17+K17+Q17+N17+O17+((I17+J17+D17+G17+U17)/2)+(R17/50)+(S17/50)+(T17/50)+(E17/5)) -> 2548.2 | AF17: =IF(B17="","",((AE17*50)/AD17)) -> 0.85789314 | AG17: =IF(C17="","",((Z17)*25)/AD17) -> 0 | AH17: =IF(B17="","",(X17*25)/AD17) -> 0 | AI17: =IF(B17="","",(Y17*25)/AD17) -> 0 | AJ17: =IF(B17="","",(AA17*25)/AD17) -> 0.027774972 | AK17: =IF(B17="","",(AB17*40)/AD17) -> 0.10961856 | AL17: =IF(B17="","",(AC17*50)/AD17) -> 0.0047133286 | AM17: =IF(B17="","",B17) -> 46100 | AN17: 24 | AO17: =+AN17-AP17 -> 23.75 | AP17: 0.25 | AQ17: =IF(AN17="","",AN17/AO17) -> 1.0105263 | AR17: =IF(AN17="","",(AD17/AN17)/1000) -> 6.188125 | AS17: =IF(AN17="","",AR17*24) -> 148.515 | AT17: =IF(AN17="","",(AD17/1000)*100%/AS17) -> 1 | AU17: =IF(AN17="","",(AE17/AN17)) -> 106.175 | AV17: =IF(AN17="","",(AD17/AO17)/1000) -> 6.2532632
A18: =IF(B18="","",16) -> 16 | B18: 46101 | C18: 1314 | D18: 50 | F18: 245 | G18: 200 | H18: 468 | R18: 23200 | S18: 25408 | AA18: 225 | AB18: 355 | AC18: 80 | AD18: =IF(B18="","",(((C18+F18+H18+K18+Q18+N18+O18)*50))+((E18*10))+(((I18+J18+D18+G18+L18+M18+U18)*25)+(X18*25)+(Y18*25)+(Z18*25)+(AA18*25)+(AB18*40)+(AC18*50)+(R18*1)+(S18*1)+(T18*1))) -> 180033 | AE18: =IF(B18="","",C18+F18+H18+K18+Q18+N18+O18+((I18+J18+D18+G18+U18)/2)+(R18/50)+(S18/50)+(T18/50)+(E18/5)) -> 3124.16 | AF18: =IF(B18="","",((AE18*50)/AD18)) -> 0.86766315 | AG18: =IF(C18="","",((Z18)*25)/AD18) -> 0 | AH18: =IF(B18="","",(X18*25)/AD18) -> 0 | AI18: =IF(B18="","",(Y18*25)/AD18) -> 0 | AJ18: =IF(B18="","",(AA18*25)/AD18) -> 0.031244272 | AK18: =IF(B18="","",(AB18*40)/AD18) -> 0.078874429 | AL18: =IF(B18="","",(AC18*50)/AD18) -> 0.022218149 | AM18: =IF(B18="","",B18) -> 46101 | AN18: 24 | AO18: =+AN18-AP18 -> 24 | AP18: 0 | AQ18: =IF(AN18="","",AN18/AO18) -> 1 | AR18: =IF(AN18="","",(AD18/AN18)/1000) -> 7.501375 | AS18: =IF(AN18="","",AR18*24) -> 180.033 | AT18: =IF(AN18="","",(AD18/1000)*100%/AS18) -> 1 | AU18: =IF(AN18="","",(AE18/AN18)) -> 130.17333 | AV18: =IF(AN18="","",(AD18/AO18)/1000) -> 7.501375
A19: =IF(B19="","",17) -> 17 | B19: 46105 | C19: 516 | D19: 999 | F19: 155 | G19: 198 | H19: 494 | I19: 1017 | R19: 8896 | S19: 51600 | AA19: 203 | AB19: 379 | AC19: 123 | AD19: =IF(B19="","",(((C19+F19+H19+K19+Q19+N19+O19)*50))+((E19*10))+(((I19+J19+D19+G19+L19+M19+U19)*25)+(X19*25)+(Y19*25)+(Z19*25)+(AA19*25)+(AB19*40)+(AC19*50)+(R19*1)+(S19*1)+(T19*1))) -> 200481 | AE19: =IF(B19="","",C19+F19+H19+K19+Q19+N19+O19+((I19+J19+D19+G19+U19)/2)+(R19/50)+(S19/50)+(T19/50)+(E19/5)) -> 3481.92 | AF19: =IF(B19="","",((AE19*50)/AD19)) -> 0.86839152 | AG19: =IF(C19="","",((Z19)*25)/AD19) -> 0 | AH19: =IF(B19="","",(X19*25)/AD19) -> 0 | AI19: =IF(B19="","",(Y19*25)/AD19) -> 0 | AJ19: =IF(B19="","",(AA19*25)/AD19) -> 0.02531412 | AK19: =IF(B19="","",(AB19*40)/AD19) -> 0.075618138 | AL19: =IF(B19="","",(AC19*50)/AD19) -> 0.030676224 | AM19: =IF(B19="","",B19) -> 46105 | AN19: 24 | AO19: =+AN19-AP19 -> 22 | AP19: 2 | AQ19: =IF(AN19="","",AN19/AO19) -> 1.0909091 | AR19: =IF(AN19="","",(AD19/AN19)/1000) -> 8.353375 | AS19: =IF(AN19="","",AR19*24) -> 200.481 | AT19: =IF(AN19="","",(AD19/1000)*100%/AS19) -> 1 | AU19: =IF(AN19="","",(AE19/AN19)) -> 145.08 | AV19: =IF(AN19="","",(AD19/AO19)/1000) -> 9.1127727
A20: =IF(B20="","",1+A19) -> 18 | B20: 46106 | C20: 882 | D20: 1 | G20: 2000 | H20: 496 | R20: 33336 | S20: 24656 | T20: 20656 | Y20: 23 | AA20: 326 | AB20: 400 | AC20: 306 | AD20: =IF(B20="","",(((C20+F20+H20+K20+Q20+N20+O20)*50))+((E20*10))+(((I20+J20+D20+G20+L20+M20+U20)*25)+(X20*25)+(Y20*25)+(Z20*25)+(AA20*25)+(AB20*40)+(AC20*50)+(R20*1)+(S20*1)+(T20*1))) -> 237598 | AE20: =IF(B20="","",C20+F20+H20+K20+Q20+N20+O20+((I20+J20+D20+G20+U20)/2)+(R20/50)+(S20/50)+(T20/50)+(E20/5)) -> 3951.46 | AF20: =IF(B20="","",((AE20*50)/AD20)) -> 0.83154319 | AG20: =IF(C20="","",((Z20)*25)/AD20) -> 0 | AH20: =IF(B20="","",(X20*25)/AD20) -> 0 | AI20: =IF(B20="","",(Y20*25)/AD20) -> 0.002420054 | AJ20: =IF(B20="","",(AA20*25)/AD20) -> 0.034301636 | AK20: =IF(B20="","",(AB20*40)/AD20) -> 0.067340634 | AL20: =IF(B20="","",(AC20*50)/AD20) -> 0.064394481 | AM20: =IF(B20="","",B20) -> 46106 | AN20: 24 | AO20: =+AN20-AP20 -> 23.75 | AP20: 0.25 | AQ20: =IF(AN20="","",AN20/AO20) -> 1.0105263 | AR20: =IF(AN20="","",(AD20/AN20)/1000) -> 9.8999167 | AS20: =IF(AN20="","",AR20*24) -> 237.598 | AT20: =IF(AN20="","",(AD20/1000)*100%/AS20) -> 1 | AU20: =IF(AN20="","",(AE20/AN20)) -> 164.64417 | AV20: =IF(AN20="","",(AD20/AO20)/1000) -> 10.004126
A21: =IF(B21="","",1+A20) -> 19 | B21: 46107 | C21: 1040 | E21: 300 | I21: 868 | J21: 80 | R21: 32960 | S21: 5760 | AA21: 175 | AB21: 395 | AC21: 55 | AD21: =IF(B21="","",(((C21+F21+H21+K21+Q21+N21+O21)*50))+((E21*10))+(((I21+J21+D21+G21+L21+M21+U21)*25)+(X21*25)+(Y21*25)+(Z21*25)+(AA21*25)+(AB21*40)+(AC21*50)+(R21*1)+(S21*1)+(T21*1))) -> 140345 | AE21: =IF(B21="","",C21+F21+H21+K21+Q21+N21+O21+((I21+J21+D21+G21+U21)/2)+(R21/50)+(S21/50)+(T21/50)+(E21/5)) -> 2348.4 | AF21: =IF(B21="","",((AE21*50)/AD21)) -> 0.83665253 | AG21: =IF(C21="","",((Z21)*25)/AD21) -> 0 | AH21: =IF(B21="","",(X21*25)/AD21) -> 0 | AI21: =IF(B21="","",(Y21*25)/AD21) -> 0 | AJ21: =IF(B21="","",(AA21*25)/AD21) -> 0.03117318 | AK21: =IF(B21="","",(AB21*40)/AD21) -> 0.11257971 | AL21: =IF(B21="","",(AC21*50)/AD21) -> 0.019594571 | AM21: =IF(B21="","",B21) -> 46107 | AN21: 24 | AO21: =+AN21-AP21 -> 23.583333 | AP21: 0.41666667 | AQ21: =IF(AN21="","",AN21/AO21) -> 1.0176678 | AR21: =IF(AN21="","",(AD21/AN21)/1000) -> 5.8477083 | AS21: =IF(AN21="","",AR21*24) -> 140.345 | AT21: =IF(AN21="","",(AD21/1000)*100%/AS21) -> 1 | AU21: =IF(AN21="","",(AE21/AN21)) -> 97.85 | AV21: =IF(AN21="","",(AD21/AO21)/1000) -> 5.9510247
A22: =IF(B22="","",1+A21) -> 20 | B22: 46108 | C22: 1040 | E22: 100 | G22: 178 | Q22: 266 | R22: 30816 | S22: 47328 | T22: 21040 | AA22: 223 | AB22: 543 | AC22: 357 | AD22: =IF(B22="","",(((C22+F22+H22+K22+Q22+N22+O22)*50))+((E22*10))+(((I22+J22+D22+G22+L22+M22+U22)*25)+(X22*25)+(Y22*25)+(Z22*25)+(AA22*25)+(AB22*40)+(AC22*50)+(R22*1)+(S22*1)+(T22*1))) -> 215079 | AE22: =IF(B22="","",C22+F22+H22+K22+Q22+N22+O22+((I22+J22+D22+G22+U22)/2)+(R22/50)+(S22/50)+(T22/50)+(E22/5)) -> 3398.68 | AF22: =IF(B22="","",((AE22*50)/AD22)) -> 0.79010038 | AG22: =IF(C22="","",((Z22)*25)/AD22) -> 0 | AH22: =IF(B22="","",(X22*25)/AD22) -> 0 | AI22: =IF(B22="","",(Y22*25)/AD22) -> 0 | AJ22: =IF(B22="","",(AA22*25)/AD22) -> 0.025920708 | AK22: =IF(B22="","",(AB22*40)/AD22) -> 0.10098615 | AL22: =IF(B22="","",(AC22*50)/AD22) -> 0.082992761 | AM22: =IF(B22="","",B22) -> 46108 | AN22: 24 | AO22: =+AN22-AP22 -> 21.416667 | AP22: 2.5833333 | AQ22: =IF(AN22="","",AN22/AO22) -> 1.1206226 | AR22: =IF(AN22="","",(AD22/AN22)/1000) -> 8.961625 | AS22: =IF(AN22="","",AR22*24) -> 215.079 | AT22: =IF(AN22="","",(AD22/1000)*100%/AS22) -> 1 | AU22: =IF(AN22="","",(AE22/AN22)) -> 141.61167 | AV22: =IF(AN22="","",(AD22/AO22)/1000) -> 10.042599
A23: =IF(B23="","",1+A22) -> 21 | B23: 46111 | C23: 1300 | F23: 350 | G23: 300 | R23: 26256 | AA23: 174 | AB23: 240 | AC23: 50 | AD23: =IF(B23="","",(((C23+F23+H23+K23+Q23+N23+O23)*50))+((E23*10))+(((I23+J23+D23+G23+L23+M23+U23)*25)+(X23*25)+(Y23*25)+(Z23*25)+(AA23*25)+(AB23*40)+(AC23*50)+(R23*1)+(S23*1)+(T23*1))) -> 132706 | AE23: =IF(B23="","",C23+F23+H23+K23+Q23+N23+O23+((I23+J23+D23+G23+U23)/2)+(R23/50)+(S23/50)+(T23/50)+(E23/5)) -> 2325.12 | AF23: =IF(B23="","",((AE23*50)/AD23)) -> 0.87604178 | AG23: =IF(C23="","",((Z23)*25)/AD23) -> 0 | AH23: =IF(B23="","",(X23*25)/AD23) -> 0 | AI23: =IF(B23="","",(Y23*25)/AD23) -> 0 | AJ23: =IF(B23="","",(AA23*25)/AD23) -> 0.032779226 | AK23: =IF(B23="","",(AB23*40)/AD23) -> 0.072340361 | AL23: =IF(B23="","",(AC23*50)/AD23) -> 0.018838636 | AM23: =IF(B23="","",B23) -> 46111 | AN23: 24 | AO23: =+AN23-AP23 -> 24 | AP23: 0 | AQ23: =IF(AN23="","",AN23/AO23) -> 1 | AR23: =IF(AN23="","",(AD23/AN23)/1000) -> 5.5294167 | AS23: =IF(AN23="","",AR23*24) -> 132.706 | AT23: =IF(AN23="","",(AD23/1000)*100%/AS23) -> 1 | AU23: =IF(AN23="","",(AE23/AN23)) -> 96.88 | AV23: =IF(AN23="","",(AD23/AO23)/1000) -> 5.5294167
A24: =IF(B24="","",1+A23) | C24: 100 | D24: 1002 | E24: 201 | H24: 575 | I24: 2000 | R24: 76608 | AA24: 304 | AB24: 531 | AC24: 19 | AD24: =IF(B24="","",(((C24+F24+H24+K24+Q24+N24+O24)*50))+((E24*10))+(((I24+J24+D24+G24+L24+M24+U24)*25)+(X24*25)+(Y24*25)+(Z24*25)+(AA24*25)+(AB24*40)+(AC24*50)+(R24*1)+(S24*1)+(T24*1))) | AE24: =IF(B24="","",C24+F24+H24+K24+Q24+N24+O24+((I24+J24+D24+G24+U24)/2)+(R24/50)+(S24/50)+(T24/50)+(E24/5)) | AF24: =IF(B24="","",((AE24*50)/AD24)) | AG24: =IF(C24="","",((Z24)*25)/AD24) -> #VALUE! | AH24: =IF(B24="","",(X24*25)/AD24) | AI24: =IF(B24="","",(Y24*25)/AD24) | AJ24: =IF(B24="","",(AA24*25)/AD24) | AK24: =IF(B24="","",(AB24*40)/AD24) | AL24: =IF(B24="","",(AC24*50)/AD24) | AM24: =IF(B24="","",B24) | AQ24: =IF(AN24="","",AN24/AO24) | AR24: =IF(AN24="","",(AD24/AN24)/1000) | AS24: =IF(AN24="","",AR24*24) | AT24: =IF(AN24="","",(AD24/1000)*100%/AS24) | AU24: =IF(AN24="","",(AE24/AN24)) | AV24: =IF(AN24="","",(AD24/AO24)/1000)
C25: 1866 | R25: 43376 | S25: 24192 | Y25: 8 | AA25: 220 | AB25: 401 | AC25: 21 | AD25: =IF(B25="","",(((C25+F25+H25+K25+Q25+N25+O25)*50))+((E25*10))+(((I25+J25+D25+G25+L25+M25+U25)*25)+(X25*25)+(Y25*25)+(Z25*25)+(AA25*25)+(AB25*40)+(AC25*50)+(R25*1)+(S25*1)+(T25*1))) | AE25: =IF(B25="","",C25+F25+H25+K25+Q25+N25+O25+((I25+J25+D25+G25+U25)/2)+(R25/50)+(S25/50)+(T25/50)+(E25/5)) | AF25: =IF(B25="","",((AE25*50)/AD25)) | AG25: =IF(C25="","",((Z25)*25)/AD25) -> #VALUE! | AH25: =IF(B25="","",(X25*25)/AD25) | AI25: =IF(B25="","",(Y25*25)/AD25) | AJ25: =IF(B25="","",(AA25*25)/AD25) | AK25: =IF(B25="","",(AB25*40)/AD25) | AL25: =IF(B25="","",(AC25*50)/AD25) | AM25: =IF(B25="","",B25) | AQ25: =IF(AN25="","",AN25/AO25) | AR25: =IF(AN25="","",(AD25/AN25)/1000) | AS25: =IF(AN25="","",AR25*24) | AT25: =IF(AN25="","",(AD25/1000)*100%/AS25) | AU25: =IF(AN25="","",(AE25/AN25)) | AV25: =IF(AN25="","",(AD25/AO25)/1000)
C26: 366 | D26: 999 | F26: 388 | G26: 200 | R26: 12288 | S26: 11008 | Y26: 9 | AA26: 216 | AB26: 376 | AC26: 199 | AD26: =IF(B26="","",(((C26+F26+H26+K26+Q26+N26+O26)*50))+((E26*10))+(((I26+J26+D26+G26+L26+M26+U26)*25)+(X26*25)+(Y26*25)+(Z26*25)+(AA26*25)+(AB26*40)+(AC26*50)+(R26*1)+(S26*1)+(T26*1))) | AE26: =IF(B26="","",C26+F26+H26+K26+Q26+N26+O26+((I26+J26+D26+G26+U26)/2)+(R26/50)+(S26/50)+(T26/50)+(E26/5)) | AF26: =IF(B26="","",((AE26*50)/AD26)) | AG26: =IF(C26="","",((Z26)*25)/AD26) -> #VALUE! | AH26: =IF(B26="","",(X26*25)/AD26) | AI26: =IF(B26="","",(Y26*25)/AD26) | AJ26: =IF(B26="","",(AA26*25)/AD26) | AK26: =IF(B26="","",(AB26*40)/AD26) | AL26: =IF(B26="","",(AC26*50)/AD26) | AM26: =IF(B26="","",B26) | AQ26: =IF(AN26="","",AN26/AO26) | AR26: =IF(AN26="","",(AD26/AN26)/1000) | AS26: =IF(AN26="","",AR26*24) | AT26: =IF(AN26="","",(AD26/1000)*100%/AS26) | AU26: =IF(AN26="","",(AE26/AN26)) | AV26: =IF(AN26="","",(AD26/AO26)/1000)
C27: 1040 | D27: 50 | E27: 200 | F27: 407 | G27: 200 | I27: 660 | K27: 10752 | R27: 54052 | S27: 23520 | Y27: 40 | AA27: 154 | AB27: 235 | AC27: 50 | AD27: =IF(B27="","",(((C27+F27+H27+K27+Q27+N27+O27)*50))+((E27*10))+(((I27+J27+D27+G27+L27+M27+U27)*25)+(X27*25)+(Y27*25)+(Z27*25)+(AA27*25)+(AB27*40)+(AC27*50)+(R27*1)+(S27*1)+(T27*1))) | AE27: =IF(B27="","",C27+F27+H27+K27+Q27+N27+O27+((I27+J27+D27+G27+U27)/2)+(R27/50)+(S27/50)+(T27/50)+(E27/5)) | AF27: =IF(B27="","",((AE27*50)/AD27)) | AG27: =IF(C27="","",((Z27)*25)/AD27) -> #VALUE! | AH27: =IF(B27="","",(X27*25)/AD27) | AI27: =IF(B27="","",(Y27*25)/AD27) | AJ27: =IF(B27="","",(AA27*25)/AD27) | AK27: =IF(B27="","",(AB27*40)/AD27) | AL27: =IF(B27="","",(AC27*50)/AD27) | AM27: =IF(B27="","",B27) | AQ27: =IF(AN27="","",AN27/AO27) | AR27: =IF(AN27="","",(AD27/AN27)/1000) | AS27: =IF(AN27="","",AR27*24) | AT27: =IF(AN27="","",(AD27/1000)*100%/AS27) | AU27: =IF(AN27="","",(AE27/AN27)) | AV27: =IF(AN27="","",(AD27/AO27)/1000)
C28: 1040 | I28: 355 | R28: 51224 | S28: 44112 | AA28: 157 | AB28: 260 | AC28: 65 | AD28: =IF(B28="","",(((C28+F28+H28+K28+Q28+N28+O28)*50))+((E28*10))+(((I28+J28+D28+G28+L28+M28+U28)*25)+(X28*25)+(Y28*25)+(Z28*25)+(AA28*25)+(AB28*40)+(AC28*50)+(R28*1)+(S28*1)+(T28*1))) | AE28: =IF(B28="","",C28+F28+H28+K28+Q28+N28+O28+((I28+J28+D28+G28+U28)/2)+(R28/50)+(S28/50)+(T28/50)+(E28/5)) | AF28: =IF(B28="","",((AE28*50)/AD28)) | AG28: =IF(C28="","",((Z28)*25)/AD28) -> #VALUE! | AH28: =IF(B28="","",(X28*25)/AD28) | AI28: =IF(B28="","",(Y28*25)/AD28) | AJ28: =IF(B28="","",(AA28*25)/AD28) | AK28: =IF(B28="","",(AB28*40)/AD28) | AL28: =IF(B28="","",(AC28*50)/AD28) | AM28: =IF(B28="","",B28) | AQ28: =IF(AN28="","",AN28/AO28) | AR28: =IF(AN28="","",(AD28/AN28)/1000) | AS28: =IF(AN28="","",AR28*24) | AT28: =IF(AN28="","",(AD28/1000)*100%/AS28) | AU28: =IF(AN28="","",(AE28/AN28)) | AV28: =IF(AN28="","",(AD28/AO28)/1000)
C29: 2080 | R29: 58240 | S29: 19894 | AA29: 182 | AB29: 424 | AC29: 94 | AD29: =IF(B29="","",(((C29+F29+H29+K29+Q29+N29+O29)*50))+((E29*10))+(((I29+J29+D29+G29+L29+M29+U29)*25)+(X29*25)+(Y29*25)+(Z29*25)+(AA29*25)+(AB29*40)+(AC29*50)+(R29*1)+(S29*1)+(T29*1))) | AE29: =IF(B29="","",C29+F29+H29+K29+Q29+N29+O29+((I29+J29+D29+G29+U29)/2)+(R29/50)+(S29/50)+(T29/50)+(E29/5)) | AF29: =IF(B29="","",((AE29*50)/AD29)) | AG29: =IF(C29="","",((Z29)*25)/AD29) -> #VALUE! | AH29: =IF(B29="","",(X29*25)/AD29) | AI29: =IF(B29="","",(Y29*25)/AD29) | AJ29: =IF(B29="","",(AA29*25)/AD29) | AK29: =IF(B29="","",(AB29*40)/AD29) | AL29: =IF(B29="","",(AC29*50)/AD29) | AM29: =IF(B29="","",B29) | AQ29: =IF(AN29="","",AN29/AO29) | AR29: =IF(AN29="","",(AD29/AN29)/1000) | AS29: =IF(AN29="","",AR29*24) | AT29: =IF(AN29="","",(AD29/1000)*100%/AS29) | AU29: =IF(AN29="","",(AE29/AN29)) | AV29: =IF(AN29="","",(AD29/AO29)/1000)
A30: =IF(B30="","",1+A29) | C30: 1070 | I30: 2064 | R30: 26400 | Y30: 8 | AA30: 161 | AB30: 250 | AC30: 45 | AD30: =IF(B30="","",(((C30+F30+H30+K30+Q30+N30+O30)*50))+((E30*10))+(((I30+J30+D30+G30+L30+M30+U30)*25)+(X30*25)+(Y30*25)+(Z30*25)+(AA30*25)+(AB30*40)+(AC30*50)+(R30*1)+(S30*1)+(T30*1))) | AE30: =IF(B30="","",C30+F30+H30+K30+Q30+N30+O30+((I30+J30+D30+G30+U30)/2)+(R30/50)+(S30/50)+(T30/50)+(E30/5)) | AF30: =IF(B30="","",((AE30*50)/AD30)) | AG30: =IF(C30="","",((Z30)*25)/AD30) -> #VALUE! | AH30: =IF(B30="","",(X30*25)/AD30) | AI30: =IF(B30="","",(Y30*25)/AD30) | AJ30: =IF(B30="","",(AA30*25)/AD30) | AK30: =IF(B30="","",(AB30*40)/AD30) | AL30: =IF(B30="","",(AC30*50)/AD30) | AM30: =IF(B30="","",B30) | AQ30: =IF(AN30="","",AN30/AO30) | AR30: =IF(AN30="","",(AD30/AN30)/1000) | AS30: =IF(AN30="","",AR30*24) | AT30: =IF(AN30="","",(AD30/1000)*100%/AS30) | AU30: =IF(AN30="","",(AE30/AN30)) | AV30: =IF(AN30="","",(AD30/AO30)/1000)
A31: =IF(B31="","",1+A30) | C31: 1060 | I31: 1024 | R31: 7664 | Y31: 9 | AA31: 121 | AB31: 238 | AC31: 53 | AD31: =IF(B31="","",(((C31+F31+H31+K31+Q31+N31+O31)*50))+((E31*10))+(((I31+J31+D31+G31+L31+M31+U31)*25)+(X31*25)+(Y31*25)+(Z31*25)+(AA31*25)+(AB31*40)+(AC31*50)+(R31*1)+(S31*1)+(T31*1))) | AE31: =IF(B31="","",C31+F31+H31+K31+Q31+N31+O31+((I31+J31+D31+G31+U31)/2)+(R31/50)+(S31/50)+(T31/50)+(E31/5)) | AF31: =IF(B31="","",((AE31*50)/AD31)) | AG31: =IF(C31="","",((Z31)*25)/AD31) -> #VALUE! | AH31: =IF(B31="","",(X31*25)/AD31) | AI31: =IF(B31="","",(Y31*25)/AD31) | AJ31: =IF(B31="","",(AA31*25)/AD31) | AK31: =IF(B31="","",(AB31*40)/AD31) | AL31: =IF(B31="","",(AC31*50)/AD31) | AM31: =IF(B31="","",B31) | AQ31: =IF(AN31="","",AN31/AO31) | AR31: =IF(AN31="","",(AD31/AN31)/1000) | AS31: =IF(AN31="","",AR31*24) | AT31: =IF(AN31="","",(AD31/1000)*100%/AS31) | AU31: =IF(AN31="","",(AE31/AN31)) | AV31: =IF(AN31="","",(AD31/AO31)/1000)
A32: =IF(B32="","",1+A31) | R32: 70096 | S32: 26160 | AA32: 148 | AB32: 338 | AC32: 183 | AD32: =IF(B32="","",(((C32+F32+H32+K32+Q32+N32+O32)*50))+((E32*10))+(((I32+J32+D32+G32+L32+M32+U32)*25)+(X32*25)+(Y32*25)+(Z32*25)+(AA32*25)+(AB32*40)+(AC32*50)+(R32*1)+(S32*1)+(T32*1))) | AE32: =IF(B32="","",C32+F32+H32+K32+Q32+N32+O32+((I32+J32+D32+G32+U32)/2)+(R32/50)+(S32/50)+(T32/50)+(E32/5)) | AF32: =IF(B32="","",((AE32*50)/AD32)) | AG32: =IF(C32="","",((Z32)*25)/AD32) | AH32: =IF(B32="","",(X32*25)/AD32) | AI32: =IF(B32="","",(Y32*25)/AD32) | AJ32: =IF(B32="","",(AA32*25)/AD32) | AK32: =IF(B32="","",(AB32*40)/AD32) | AL32: =IF(B32="","",(AC32*50)/AD32) | AM32: =IF(B32="","",B32) | AQ32: =IF(AN32="","",AN32/AO32) | AR32: =IF(AN32="","",(AD32/AN32)/1000) | AS32: =IF(AN32="","",AR32*24) | AT32: =IF(AN32="","",(AD32/1000)*100%/AS32) | AU32: =IF(AN32="","",(AE32/AN32)) | AV32: =IF(AN32="","",(AD32/AO32)/1000)
A33: =IF(B33="","",1+A32) | AD33: =IF(B33="","",(((C33+F33+H33+K33+Q33+N33+O33)*50))+((E33*10))+(((I33+J33+D33+G33+L33+M33+U33)*25)+(X33*25)+(Y33*25)+(Z33*25)+(AA33*25)+(AB33*40)+(AC33*50)+(R33*1)+(S33*1)+(T33*1))) | AE33: =IF(B33="","",C33+F33+H33+K33+Q33+N33+O33+((I33+J33+D33+G33+U33)/2)+(R33/50)+(S33/50)+(T33/50)+(E33/5)) | AF33: =IF(B33="","",((AE33*50)/AD33)) | AG33: =IF(C33="","",((Z33)*25)/AD33) | AH33: =IF(B33="","",(X33*25)/AD33) | AI33: =IF(B33="","",(Y33*25)/AD33) | AJ33: =IF(B33="","",(AA33*25)/AD33) | AK33: =IF(B33="","",(AB33*40)/AD33) | AL33: =IF(B33="","",(AC33*50)/AD33) | AM33: =IF(B33="","",B33) | AQ33: =IF(AN33="","",AN33/AO33) | AR33: =IF(AN33="","",(AD33/AN33)/1000) | AS33: =IF(AN33="","",AR33*24) | AT33: =IF(AN33="","",(AD33/1000)*100%/AS33) | AU33: =IF(AN33="","",(AE33/AN33)) | AV33: =IF(AN33="","",(AD33/AO33)/1000)
A34: =IF(B34="","",1+A33) | AD34: =IF(B34="","",(((C34+F34+H34+K34+Q34+N34+O34)*50))+((E34*10))+(((I34+J34+D34+G34+L34+M34+U34)*25)+(X34*25)+(Y34*25)+(Z34*25)+(AA34*25)+(AB34*40)+(AC34*50)+(R34*1)+(S34*1)+(T34*1))) | AE34: =IF(B34="","",C34+F34+H34+K34+Q34+N34+O34+((I34+J34+D34+G34+U34)/2)+(R34/50)+(S34/50)+(T34/50)+(E34/5)) | AF34: =IF(B34="","",((AE34*50)/AD34)) | AG34: =IF(C34="","",((Z34)*25)/AD34) | AH34: =IF(B34="","",(X34*25)/AD34) | AI34: =IF(B34="","",(Y34*25)/AD34) | AJ34: =IF(B34="","",(AA34*25)/AD34) | AK34: =IF(B34="","",(AB34*40)/AD34) | AL34: =IF(B34="","",(AC34*50)/AD34) | AM34: =IF(B34="","",B34) | AQ34: =IF(AN34="","",AN34/AO34) | AR34: =IF(AN34="","",(AD34/AN34)/1000) | AS34: =IF(AN34="","",AR34*24) | AT34: =IF(AN34="","",(AD34/1000)*100%/AS34) | AU34: =IF(AN34="","",(AE34/AN34)) | AV34: =IF(AN34="","",(AD34/AO34)/1000)
A35: =IF(B35="","",1+A34) | AD35: =IF(B35="","",(((C35+F35+H35+K35+Q35+N35+O35)*50))+((E35*10))+(((I35+J35+D35+G35+L35+M35+U35)*25)+(X35*25)+(Y35*25)+(Z35*25)+(AA35*25)+(AB35*40)+(AC35*50)+(R35*1)+(S35*1)+(T35*1))) | AE35: =IF(B35="","",C35+F35+H35+K35+Q35+N35+O35+((I35+J35+D35+G35+U35)/2)+(R35/50)+(S35/50)+(T35/50)+(E35/5)) | AF35: =IF(B35="","",((AE35*50)/AD35)) | AG35: =IF(C35="","",((Z35)*25)/AD35) | AH35: =IF(B35="","",(X35*25)/AD35) | AI35: =IF(B35="","",(Y35*25)/AD35) | AJ35: =IF(B35="","",(AA35*25)/AD35) | AK35: =IF(B35="","",(AB35*40)/AD35) | AL35: =IF(B35="","",(AC35*50)/AD35) | AM35: =IF(B35="","",B35) | AQ35: =IF(AN35="","",AN35/AO35) | AR35: =IF(AN35="","",(AD35/AN35)/1000) | AS35: =IF(AN35="","",AR35*24) | AT35: =IF(AN35="","",(AD35/1000)*100%/AS35) | AU35: =IF(AN35="","",(AE35/AN35)) | AV35: =IF(AN35="","",(AD35/AO35)/1000)
B36: Total | C36: =SUM(C4:C35) -> 27591 | D36: =SUM(D4:D35) -> 8024 | E36: =SUM(E4:E35) -> 1582 | F36: =SUM(F4:F35) -> 5121 | G36: =SUM(G4:G35) -> 4671 | H36: =SUM(H4:H35) -> 2894 | I36: =SUM(I4:I35) -> 17119 | J36: =SUM(J4:J35) -> 580 | ... Q36: =SUM(Q4:Q35) -> 266 | R36: =SUM(R4:R21) -> 723020 | S36: =SUM(S4:S35) -> 494636 | T36: =SUM(T4:T35) -> 61856 | U36: =SUM(U4:U35) -> 0 | V36: =SUM(V4:V35) -> 0 | W36: =SUM(W4:W35) -> 0 | X36: =SUM(X4:X35) -> 0 | Y36: =SUM(Y4:Y35) -> 218 | Z36: =SUM(Z4:Z35) -> 0 | ... AC36: =SUM(AC4:AC35) -> 2889 | AD36: =(SUM(AD4:AD35))/1000 -> 3638.203 | AE36: =SUM(AE4:AE35) -> 62338.16 | AF36: =IF(AD41=0,"",((AE36*50)/1000)/AD36) -> 0.85671635 | AG36: =IF(AD41=0,"",(Z36*50)/AD36) -> 0 | AH36: =IF(AD41=0,"",(X36*25)/AD36) -> 0 | AI36: =IF(AD41=0,"",(Y36*25)/AD36) -> 1.4979923 | AJ36: =IF(AD41=0,"",(AA36*25)/AD36) -> 37.745282 | AK36: =IF(AD41=0,"",(AB36*40)/AD36) -> 101.59961 | AL36: =IF(AD41=0,"",(AC36*50)/AD36) -> 39.703667 | AM36: Total | AN36: =SUM(AN4:AN35) -> 480 | AO36: =SUM(AO4:AO35) -> 462.66667 | AP36: =SUM(AP4:AP35) -> 17.333333 | AQ36: =IF(AN36=0,"",AN36/AO36) -> 1.037464 | AR36: =IF(AN36=0,"",(AD36/AN36)/1000) -> 0.0075795896 | AS36: =IF(AN36=0,"",AR36*24) -> 0.18191015 | AT36: =IF(AN36=0,"",AD41/(AS36*26)) -> 769.23077 | AU36: =IF(AN36=0,"",(AE36/AN36)) -> 129.87117 | AV36: =IF(AO36=0,"",(AD36/AO36)/1000) -> 0.0078635512 | AW36: =SUM(AW4:AW35)/1000 -> 0 | AX36: =SUM(AX4:AX35)/1000 -> 2397.6 | AY36: =SUM(AY4:AY35)/1000 -> 1869.488 | AZ36: =SUM(AZ4) -> 537016 | BA36: =SUM(BA4:BA35) -> 59372 | BB36: =SUM(BB4:BB35) -> 372195 | BC36: =SUM(BC4:BC35)/1000 -> 1400.504 | BD36: =SUM(BD4:BD35)/1000 -> 30.058 | BE36: =SUM(BE4:BE35)/1000 -> 409.38 | BF36: =SUM(BF4:BF35)/1000 -> 811.544
B37: Toneladas para Forecast | C37: =(C36*50)/1000 -> 1379.55 | D37: =(D36*25)/1000 -> 200.6 | E37: =(E36*10)/1000 -> 15.82 | F37: =(F36*50)/1000 -> 256.05 | G37: =(G36*25)/1000 -> 116.775 | H37: =(H36*50)/1000 -> 144.7 | I37: =(I36*25)/1000 -> 427.975 | J37: =(J36*25)/1000 -> 14.5 | K37: =(K36*50)/1000 -> 615 | L37: =(L36*25)/1000 -> 66.425 | M37: =(M36*25)/1000 -> 0 | N37: =(N36*25)/1000 -> 0 | O37: =(O36*50)/1000 -> 0 | P37: =(P36*50)/1000 -> 0 | Q37: =(Q36*50)/1000 -> 13.3 | R37: =(R36+R39)/1000 -> 1075.88 | S37: =(S36)/1000 -> 494.636 | T37: =(T36)/1000 -> 61.856 | U37: =(U36*25)/1000 -> 0 | V37: =(V36)/1000 -> 0 | W37: =(W36)/1000 -> 0 | X37: =(X36*25)/1000 -> 0 | Y37: =(Y36*25)/1000 -> 5.45 | Z37: =(Z36*25)/1000 -> 0 | AA37: =(AA36*25)/1000 -> 137.325 | AB37: =(AB36*40)/1000 -> 369.64 | AC37: =(AC36*50)/1000 -> 144.45 | AD37: =SUM(C37:AC37) -> 5539.932
B38: Promedio | C38: =IF(C36=0,"",AVERAGE(C4:C35)) -> 985.39286 | D38: =IF(D36=0,"",AVERAGE(D4:D35)) -> 573.14286 | E38: =IF(E36=0,"",AVERAGE(E4:E35)) -> 226 | F38: =IF(F36=0,"",AVERAGE(F4:F35)) -> 365.78571 | G38: =IF(G36=0,"",AVERAGE(G4:G35)) -> 389.25 | H38: =IF(H36=0,"",AVERAGE(H4:H35)) -> 482.33333 | I38: =IF(I36=0,"",AVERAGE(I4:I35)) -> 1007 | J38: =IF(J36=0,"",AVERAGE(J4:J35)) -> 116 | K38: =IF(K36=0,"",AVERAGE(K4:K35)) -> 2050 | N38: =IF(N36=0,"",AVERAGE(N4:N35)) | O38: =IF(O36=0,"",AVERAGE(O4:O35)) | P38: =IF(P36=0,"",AVERAGE(P4:P35)) | Q38: =IF(Q36=0,"",AVERAGE(Q4:Q35)) -> 266 | R38: =IF(R36=0,"",AVERAGE(R4:R35)) -> 40691.034 | S38: =IF(S36=0,"",AVERAGE(S4:S35)) -> 29096.235 | T38: =IF(T36=0,"",AVERAGE(T4:T35)) -> 20618.667 | U38: =IF(U36=0,"",AVERAGE(U4:U35)) | ... AC38: =IF(AC36=0,"",AVERAGE(AC4:AC35)) -> 99.62069 | AD38: =AD36-AD37 -> -1901.729 | AM38: Promedio | AN38: =IF(AN36=0,"",AVERAGE(AN4:AN35)) -> 24 | AO38: =IF(AO36=0,"",AVERAGE(AO4:AO35)) -> 23.133333 | AP38: =IF(AP36=0,"",AVERAGE(AP4:AP35)) -> 0.86666667 | AQ38: =IF(AQ36="","",AVERAGE(AQ4:AQ35)) -> 1.0450397 | AR38: =IF(AR36="","",AVERAGE(AR4:AR35)) -> 7.5795896 | AS38: =IF(AS36="","",AVERAGE(AS4:AS35)) -> 181.91015 | AT38: =IF(AT36="","",AVERAGE(AT4:AT35)) -> 1 | AU38: =IF(AU36="","",AVERAGE(AU4:AU35)) -> 129.87117 | AV38: =IF(AV36="","",AVERAGE(AV4:AV35)) -> 7.8570139
B39: Cambio de Mezcla | R39: =SUM(R22:R29) -> 352860 | AD39: Total Kg.
AE40: Total Tm.
B41: Total | C41: =SUM(C4:C35) -> 27591 | D41: =SUM(D4:D35) -> 8024 | E41: =SUM(E4:E35) -> 1582 | F41: =SUM(F4:F35) -> 5121 | G41: =SUM(G4:G35) -> 4671 | H41: =SUM(H4:H35) -> 2894 | I41: =SUM(I4:I35) -> 17119 | J41: =SUM(J4:J35) -> 580 | ... AC41: =SUM(AC4:AC35) -> 2889 | AD41: =AD36 -> 3638.203
A43: Grano entero | B43: 46090 | Z43: =103+105+66 -> 274 | AD43: =(Z43+AA43)*25.8 -> 7069.2 | AE43: =Z43 -> 274 | AF43: =IF(B43="","",((AE43*25)/AD43)) -> 0.96899225 | AG43: =IF(B43="","",((Z43)*25)/AD43) -> 0.96899225 | AH43: =IF(B43="","",(X43*25)/AD43) -> 0 | AI43: =IF(B43="","",(Y43*25)/AD43) -> 0 | AJ43: =IF(B43="","",(AA43*25)/AD43) -> 0 | AK43: =IF(B43="","",(AB43*40)/AD43) -> 0 | AL43: =IF(B43="","",(AC43*50)/AD43) -> 0 | AM43: =IF(B43="","",B43) -> 46090 | AQ43: =IF(AN43="","",AN43/AO43) | AR43: =IF(AN43="","",(AD43/AN43)/1000) | AS43: =IF(AN43="","",AR43*24) | AT43: =IF(AN43="","",(AD43/1000)*100%/AS43) | AU43: =IF(AN43="","",(AE43/AN43)) | AV43: =IF(AN43="","",(AD43/AO43)/1000)
A44: Bio Convercion | AD44: =(Z44*25)+(AA44*25)+(AB44*40)+(AC44*50) -> 0 | AE44: =IF(B44="","",C44+E44+G44+K44+N44+O44+Q44+R44+((D44+H44)/4)+((F44+I44+J44+T44+Z44)/2)) | AF44: =IF(B44="","",((AE44*50)/AD44)) | AG44: =IF(B44="","",((Z44)*25)/AD44) | AH44: =IF(B44="","",(X44*25)/AD44) | AI44: =IF(B44="","",(Y44*25)/AD44) | AJ44: =IF(B44="","",(AA44*25)/AD44) | AK44: =IF(B44="","",(AB44*40)/AD44) | AL44: =IF(B44="","",(AC44*50)/AD44) | AM44: =IF(B44="","",B44) | AQ44: =IF(AN44="","",AN44/AO44) | AR44: =IF(AN44="","",(AD44/AN44)/1000) | AS44: =IF(AN44="","",AR44*24) | AT44: =IF(AN44="","",(AD44/1000)*100%/AS44) | AU44: =IF(AN44="","",(AE44/AN44)) | AV44: =IF(AN44="","",(AD44/AO44)/1000)
A45: Kamut | AD45: =Z45*25 -> 0 | AE45: =IF(B45="","",C45+E45+G45+K45+N45+O45+Q45+R45+((D45+H45)/4)+((F45+I45+J45+T45)/2)) | AF45: =IF(B45="","",((AE45*50)/AD45)) | AG45: =IF(B45="","",((Z45)*25)/AD45) | AH45: =IF(B45="","",(X45*25)/AD45) | AI45: =IF(B45="","",(Y45*25)/AD45) | AJ45: =IF(B45="","",(AA45*25)/AD45) | AK45: =IF(B45="","",(AB45*40)/AD45) | AL45: =IF(B45="","",(AC45*50)/AD45) | AM45: =IF(B45="","",B45) | AQ45: =IF(AN45="","",AN45/AO45) | AR45: =IF(AN45="","",(AD45/AN45)/1000) | AS45: =IF(AN45="","",AR45*24) | AT45: =IF(AN45="","",(AD45/1000)*100%/AS45) | AU45: =IF(AN45="","",(AE45/AN45)) | AV45: =IF(AN45="","",(AD45/AO45)/1000)
A46: Trigo entero | B46: 46084 | Z46: =400+360+400 -> 1160 | AD46: =(Z46+AA46)*25.275 -> 29319 | AE46: =IF(B46="","",C46+E46+G46+K46+N46+O46+Q46+R46+((D46+H46)/4)+((F46+I46+J46+T46)/2)) -> 0 | AF46: =IF(B46="","",((AE46*50)/AD46)) -> 0 | AG46: =IF(B46="","",((Z46)*25)/AD46) -> 0.98911968 | AH46: =IF(B46="","",(X46*25)/AD46) -> 0 | AI46: =IF(B46="","",(Y46*25)/AD46) -> 0 | AJ46: =IF(B46="","",(AA46*25)/AD46) -> 0 | AK46: =IF(B46="","",(AB46*40)/AD46) -> 0 | AL46: =IF(B46="","",(AC46*50)/AD46) -> 0 | AM46: =IF(B46="","",B46) -> 46084 | AQ46: =IF(AN46="","",AN46/AO46) | AR46: =IF(AN46="","",(AD46/AN46)/1000) | AS46: =IF(AN46="","",AR46*24) | AT46: =IF(AN46="","",(AD46/1000)*100%/AS46) | AU46: =IF(AN46="","",(AE46/AN46)) | AV46: =IF(AN46="","",(AD46/AO46)/1000)
AD47: =SUM(AD43:AD46) -> 36388.2 | AX47: =AX43/1000 -> 0
AD48: Total Kg.
I49: 3.6 | AD49: =AD47/1000 -> 36.3882 | AE49: Total Tm.
A50: Produccion | C50: % rendimiento | F50: Energia | I50: ART | K50: PEDIDO PUERTO | N50: SAP | O50: Inicial | R50: CONSUMOS | V50: FINAL
A51: tm trigo: | B51: =AD41+AD49 -> 3674.5912 | F51: Precio Kw: | H51: =IF(G54="",0,G57/G54) -> 0 | I51: =IF(I54="",0,I57/I54) -> 0 | K51: 0 | M51: =IF($V$51="",0,K51/$V$56) -> 0 | Q51: =IF($V$51="",0,O51/$V$56) -> 0 | R51: =D81 -> CWRS | S51: =(B83*D83)+(B86*D86)+(B87*D87)+(B88*D88)+(B90*D90)+(B93*D93)+(B95*D95)+(B96*D96)+(B99*D99)+(B100*D100)+(B101*D101)+(B103*D103)+(B104*D104)+(B109*D109)+(B112*D112)+(B84*D84)+(B105*D105)+(B85*D85)+(B92*D92)+(B116*D116)+(B107*D107)+(B106*D106)+(B114*D114)+(B111*D111)+(B89*D89)+(B91*D91)+(B97*D97)+(B98*D98)+(B108*D108) -> 3262935.9 | U51: =IF($S$56=0,0,S51/$S$56) -> 0.57663292 | V51: =K51+O51-S51 -> -3262935.9 | X51: =IF($V$51="",0,V51/$V$56) -> 0.57663292
A52: Blt harina: | B52: =AE36 -> 62338.16 | C52: =B51/(B61*120) -> 1.6116628 | F52: Kw/tm trigo: | H52: =IF(G54="",0,G54/B51) -> 0 | M52: =IF($V$52="",0,K52/$V$56) -> 0 | Q52: =IF($V$52="",0,O52/$V$56) -> 0 | R52: =IF(E81="","",E81) -> CPS | S52: =(B83*E83)+(B86*E86)+(B87*E87)+(B88*E88)+(B90*E90)+(B93*E93)+(B95*E95)+(B96*E96)+(B99*E99)+(B100*E100)+(B101*E101)+(B103*E103)+(B104*E104)+(B109*E109)+(B114*E114)+(B106*E106)+(B112*E112)+(B105*E105)+(B84*E84)+(B85*E85)+(B92*E92)+(B107*E107)+(B116*E116)+(B117*E117)+(B111*E111)+(B102*E102)+(B89*E89)+(B91*E91)+(B98*E98)+(B108*E108+B97*E97) -> 119749 | U52: =IF($S$56=0,0,S52/$S$56) -> 0.021162296 | V52: =K52+O52-S52 -> -119749 | X52: =IF($V$52="",0,V52/$V$56) -> 0.021162296
A53: Tm harina: | B53: =(B52*50)/1000 -> 3116.908 | F53: Kw/tm harina: | H53: =IF(G54="",0,G54/((B52*50)/1000)) -> 0 | M53: =IF($V$51="",0,K53/$V$56) -> 0 | Q53: =IF($V$51="",0,O53/$V$56) -> 0 | R53: HRW | S53: =(B83*G83)+(B86*G86)+(B87*G87)+(B88*G88)+(B90*G90)+(B93*G93)+(B95*G95)+(B96*G96)+(B99*G99)+(B100*G100)+(B101*G101)+(B103*G103)+(B104*G104)+(B109*G109)+(B114*G114)+(B110*G110)+(B117*G117)+(B115*G115)+(B116*G116)+(B84*G84)+(B85*G85)+(B105*G105)+(B107*G107)+(B97*G97)+(B98*G98)+(B91*G91)+(B89*G89)+(B106*G106)+(B92*G92)+(B111*G111) -> 1223954.6 | U53: =IF($S$56=0,0,S53/$S$56) -> 0.21629984 | V53: =K53+O53-S53 -> -1223954.6 | X53: =IF($V$51="",0,V53/$V$56) -> 0.21629984
A54: Extraccion: | B54: =IF(AF36="",0,AF36) -> 0.85671635 | F54: KW: | K54: 0 | M54: =IF($V$51="",0,L54/$V$56) -> 0 | Q54: =IF($V$51="",0,O54/$V$56) -> 0 | R54: SRW | S54: =(B83*F83)+(B86*F86)+(B87*F87)+(B88*F88)+(B90*F90)+(B93*F93)+(B95*F95)+(B96*F96)+(B99*F99)+(B100*F100)+(B101*F101)+(B103*F103)+(B104*F104)+(B109*F109)+(B114*F114)+(B116*F116)+(B112*F112)+(B110*F110)+(B106*F106)+(B117*F117)+(B102*F102)+(B89*F89)+(B91*F91)+(B92*F92)+(B107*F107)+(B108*F108)+(B97*F97) -> 1051961.9 | U54: =IF($S$56=0,0,S54/$S$56) -> 0.18590494 | V54: =L54+O54-S54 -> -1051961.9 | X54: =IF($V$51="",0,V54/$V$56) -> 0.18590494
A55: Hrs molienda: | B55: =AN36 -> 480 | F55: KVAR: | K55: 0 | M55: =IF($V$51="",0,L55/$V$56) -> 0 | O55: 0 | Q55: =IF($V$51="",0,O55/$V$56) -> 0 | R55: BIO | S55: =IF(AD44="",0,AD44) -> 0 | U55: =IF($S$56=0,0,S55/$S$56) -> 0 | V55: =L55+O55-S55 -> 0 | X55: =IF($V$51="",0,V55/$V$56) -> 0
A56: Hrs varada: | B56: =IF(B51=0,0,AP36/AN36) -> 0.036111111 | F56: Reactiva: | K56: =SUM(K51:K55) -> 0 | N56: =SUM(N51:N55) -> 0 | O56: =SUM(O51:O55) -> 0 | S56: =SUM(S51:S55) -> 5658601.4 | V56: =SUM(V51:V55) -> -5658601.4
A57: % dia utilizado: | B57: =AT38 -> 1 | F57: Precio: | G57: 77284230 | I57: 2803509
A58: Capacidad utilizada: | B58: =+AT36 -> 769.23077 | F58: Hz neumatico: | K58: Basculas
A59: Capacidad: | B59: =IF(AS36="",0,AS36) -> 0.18191015 | K59: Tm Trigo T1: | M59: =AX36 -> 2397.6 | O59: tm
A60: Bultos hora: | B60: =IF(AU36="",0,AU36) -> 129.87117 | F60: Granza: | H60: kg. | K60: Bascula Harina: | M60: =AY36 -> 1869.488 | O60: tm
A61: Dias molienda: | B61: =31-COUNTBLANK(A4:A35) -> 19 | F61: % | G61: =G60/(B51*1000) -> 0 | K61: Extraccion: | M61: =M60/M59 -> 0.77973307 | T61: MYCE | Y61: AA | Z61: ADA | AA61: 900 | AB61: Alfa | AC61: 7200 | AD61: 4200 | AE61: 8530
A62: Total Ton de trig: | B62: =AD41+AD49 -> 3674.5912 | G62: grf | T62: TRIGO | X62: =C83 -> Extrapan 50 | Y62: 10 | Z62: 3 | AA62: 2.5 | AB62: 3 | AC62: 7 | AD62: 2
A63: Ton. molidas/persona: | B63: =B51/B68 -> 153.10797 | F63: Energia M.martillo | K63: Energia C.granel | T63: AGUA m3 | U63: =AZ4 -> 537016 | X63: =C86 -> Extrapan 25 | Y63: =+Y62/2 -> 5 | Z63: =+Z62/2 -> 1.5 | AA63: =+AA62/2 -> 1.25 | AB63: =+AB62/2 -> 1.5 | AC63: =+AC62/2 -> 3.5 | AD63: =+AD62/2 -> 1
A64: Valor tonelada/nomina: | B64: =B76/B51 -> 17433.84 | F64: Ton Molidas | K64: Ton despachadas | O64: 662 | X64: =C87 -> Extrapan 10 | Y64: =+Y62/5 -> 2 | Z64: =+Z62/5 -> 0.6 | AA64: =+AA62/5 -> 0.5 | AB64: =+AB62/5 -> 0.6 | AC64: =+AC62/5 -> 1.4 | AD64: =+AD62/5 -> 0.4
A65: Valor ton/Horas extras: | B65: =B77/B51 -> 2132.8718 | F65: Tiempo de cargue | H65: =(H64*1)*2 -> 0 | K65: Tiempo de cargue | O65: =O64/30 -> 22.066667 | T65: Flowbalancer | X65: =C88 -> Artesanal 50 | Y65: 10 | Z65: 3 | AA65: 0 | AB65: 6 | AC65: 7 | AD65: 0
F66: TRIGO | K66: HARINA | O66: 811544 | T66: CRWS | U66: =+BC4 -> 1400504 | X66: =C90 -> Artesanal 25 | Y66: =+Y65/2 -> 5 | Z66: =+Z65/2 -> 1.5 | AA66: =+AA65/2 -> 0 | AB66: =+AB65/2 -> 3 | AC66: =+AC65/2 -> 3.5 | AD66: =+AD65/2 -> 0
A67: Datos Generales | F67: HRW | K67: SRW | T67: CPS / HRW | U67: =+BD4+BF4 -> 841602 | X67: =C93 -> Natural 50 | Y67: 0 | Z67: 0 | AA67: 0 | AB67: 0 | AC67: 0 | AD67: 0
A68: Personal de planta | B68: 24 | F68: AMP | H68: =H65*G68 -> 0 | K68: AMP | L68: 100 | M68: =(O65*L68) -> 2206.6667 | T68: SRW | U68: =+BE4 -> 409380 | X68: =C100 -> Harina Tortas y Ponques | Y68: 0 | Z68: 0 | AA68: 0 | AB68: 0 | AC68: 0 | AD68: 0
A69: Cuota de ventas | B69: 28760 | F69: KW/H | G69: =(G68*436*1.7321*0.96)/1000 -> 0 | H69: =(H68*436*1.7321*0.96)/1000 -> 0 | K69: KW/H | L69: =(L68*436*1.7321*0.96)/1000 -> 72.498778 | T69: OTROS | X69: =C101 -> Harina Galeras Ligera | Y69: 0 | Z69: 0 | AA69: 0 | AB69: 0 | AC69: 0 | AD69: 0
A70: Ventas reales | B70: 36087 | F70: KW Total | G70: =G69*H64 -> 0 | K70: KW Total | M70: =L69*O65 -> 1599.8064 | X70: =C104 -> Harina de alta proteina x 1 G | Y70: 0 | Z70: 0 | AA70: 0 | AB70: 0 | AC70: 0 | AD70: 0
A71: % de cumplimiento Proy | B71: =+B52/B69 -> 2.1675299 | F71: Precio Kw: | H71: =G70*H51 -> 0 | K71: Precio Kw: | M71: =M70*H51 -> 0 | T71: VALOR X HORA DE VARADA | X71: Total | Y71: =+SUM(Y62:Y70) -> 32 | Z71: =+SUM(Z62:Z70) -> 9.6 | AA71: =+SUM(AA62:AA70) -> 4.25 | AB71: =+SUM(AB62:AB70) -> 14.1 | AC71: =+SUM(AC62:AC70) -> 22.4 | AD71: =+SUM(AD62:AD70) -> 3.4
A72: % de cumplimiento Real | B72: =+B52/B70 -> 1.7274409 | T72: Mob | V72: =AP36*(U72+U73) -> 0 | X72: Fisico
T73: Cif
A75: Datos Nomina Producción | Y75: Vitamina | Z75: COP | AA75: EXP
A76: Nomina | B76: 64062235 | Y76: gr/blt | Z76: 12.5 | AA76: 13.5 | AC76: gr/blt
A77: Horas extras | B77: 7837432 | Y77: Total | Z77: =SUM(A83+A86+A87+A88+A90+A93+A95+A99+A101+A103+A104+A109+A106+A111+A114+A116+A110+A84+A85+A91+A89+A92+A97+A98+A105+A107+A112)*Z76 -> 1209498 | AA77: =(A96+A100)*AA76 -> 3915 | AC77: gr.
Y78: Fisico | AC78: gr.
D81: CWRS | E81: CPS | F81: SRW | G81: HRW
A82: Harina | B82: trigo | C82: Codigo | D82: % | E82: % | F82: % | G82: %
A83: =C36 -> 27591 | B83: =IF(A83=0,0,((A83*50)/$B$54)) -> 1610276.3 | C83: Extrapan 50 | D83: 0.7 | E83: 0 | G83: 0.3
A84: =C39 -> 0 | B84: =IF(A84=0,0,((A84*50)/$B$54)) -> 0 | C84: Extrapan 50
A85: =C40 -> 0 | B85: =IF(A85=0,0,((A85*50)/$B$54)) -> 0 | C85: Extrapan 50 | D85: 0.8 | E85: 0.2
A86: =D36/2 -> 4012 | B86: =IF(A86=0,0,((A86*50)/$B$54)) -> 234149.84 | C86: =D3 -> Extrapan 25 | D86: 0.7 | E86: 0 | G86: 0.3
A87: =E36/5 -> 316.4 | B87: =IF(A87=0,0,((A87*50)/$B$54)) -> 18465.855 | C87: =E3 -> Extrapan 10 | D87: 0.7 | E87: 0 | G87: 0.3
A88: =F36 -> 5121 | B88: =IF(A88=0,0,((A88*50)/$B$54)) -> 298873.72 | C88: =F3 -> Artesanal 50 | D88: 0.52 | E88: 0 | F88: 0.25 | G88: 0.23
A89: =F39 -> 0 | B89: =IF(A89=0,0,((A89*50)/$B$54)) -> 0 | C89: =C88 -> Artesanal 50 | D89: 0.52 | E89: 0 | F89: 0.25 | G89: 0.23
A90: =G36/2 -> 2335.5 | B90: =IF(A90=0,0,((A90*50)/$B$54)) -> 136305.32 | C90: =G3 -> Artesanal 25 | D90: 0.52 | E90: 0 | F90: 0.25 | G90: 0.23
A91: =G39/2 -> 0 | B91: =IF(A91=0,0,((A91*50)/$B$54)) -> 0 | C91: =C90 -> Artesanal 25 | D91: 0.52 | E91: 0 | F91: 0.25 | G91: 0.23
A92: =H36 -> 2894 | B92: =IF(A92=0,0,((A92*50)/$B$54)) -> 168900.71 | C92: =H3 -> Natural 50 | D92: 0.63 | E92: 0 | F92: 0.14 | G92: 0.23
A93: =H39 -> 0 | B93: =IF(A93=0,0,((A93*50)/$B$54)) -> 0 | C93: =H3 -> Natural 50 | D93: 0.63 | E93: 0.1
B94: =IF(A94=0,0,((A94*50)/$B$54)) -> 0
A95: =I36/2 -> 8559.5 | B95: =IF(A95=0,0,((A95*50)/$B$54)) -> 499552.74 | C95: =I3 -> Fuerte 25 | D95: 0.52 | E95: 0 | F95: 0.25 | G95: 0.23
A96: =J36/2 -> 290 | B96: =IF(A96=0,0,((A96*50)/$B$54)) -> 16925.088 | C96: =J3 -> Fuerte exp 25 | D96: 0.52 | E96: 0 | F96: 0.25 | G96: 0.23
A97: =I39/2 -> 0 | B97: =IF(A97=0,0,((A97*50)/$B$54)) -> 0 | C97: =I3 -> Fuerte 25 | D97: 0.52 | E97: 0 | F97: 0.25 | G97: 0.23
A98: =I40/2 -> 0 | B98: =IF(A98=0,0,((A98*50)/$B$54)) -> 0 | C98: =C97 -> Fuerte 25
A99: =K36 -> 12300 | B99: =IF(A99=0,0,((A99*50)/$B$54)) -> 717857.2 | C99: =K3 -> Exclusiva 50 | D99: 0.52 | E99: 0 | F99: 0.25 | G99: 0.23
A100: =N36 -> 0 | B100: =IF(A100=0,0,((A100*50)/$B$54)) -> 0 | C100: =N3 -> Harina Tortas y Ponques
A101: =O36 -> 0 | B101: =IF(A101=0,0,((A101*50)/$B$54)) -> 0 | C101: =O3 -> Harina Galeras Ligera
A102: =O39 -> 0 | B102: =IF(A102=0,0,((A102*50)/$B$54)) -> 0 | C102: =C101 -> Harina Galeras Ligera
A103: =Q36 -> 266 | B103: =IF(A103=0,0,((A103*50)/$B$54)) -> 15524.391 | C103: =Q3 -> ESPECIAL 50 | F103: 1
A104: =R36/50 -> 14460.4 | B104: =IF(A104=0,0,((A104*50)/$B$54)) -> 843943.27 | C104: =R3 -> Harina de alta proteina x 1 G | D104: 0.75 | G104: 0.25
...

Sheet ABR
B1: Producción | AH1: Extracción | AN1: Indicadores
B2: HARINA EN BULTO | R2: HARINA GRANEL | U2: P. EXP | V2: REPASO | X2: ESPECIAL | AA2: SUBPRODUCTO | AF2: EXTRACION | AN2: HORAS | AQ2: INDICACORES MOLINO | AV2: MOJADORA | AW2: EQUIPOS ELECTRONICOS
A3: Dia | B3: Fecha | C3: Extrapan 50 | D3: Extrapan 25 | E3: Extrapan 10 | F3: Artesanal 50 | G3: Artesanal 25 | H3: Natural 50 | I3: Fuerte 25 | J3: Fuerte exp 25 | K3: Exclusiva 50 | L3: Exclusiva 25 | M3: S. Sal 25 | N3: Harina Tortas y Ponques | O3: Harina Galeras Ligera | P3: H. Manitova | Q3: ESPECIAL 50 | R3: Harina de alta proteina x 1 G | S3: Harina de baja proteina x 1 | T3: ARTESANAL X 1 G | U3: H. espcial x 25 | V3: + Repaso | W3: - Reproceso | X3: Germen 25 | Y3: Semola 25 | Z3: Grano entero 25 | AA3: Salvado 25 | AB3: Mogolla 40 | AC3: Segunda 50 | AD3: Total trigo | AE3: Total Bultos | AF3: Harina | AG3: Grano entero partido | AH3: =X3 -> Germen 25 | AI3: Semola | AJ3: =AA3 -> Salvado 25 | AK3: =AB3 -> Mogolla 40 | AL3: =AC3 -> Segunda 50 | AM3: =B3 -> Fecha | AN3: Molienda | AO3: moje | AP3: Horas varada | AQ3: Molido/ Mojado | AR3: Capacidad TM. hora | AS3: Capacidad TM. Día | AT3: % Utilizado | AU3: Bultos Hora | AV3: capacidad TM. hora | AW3: MYFC | AX3: Bascula Trigo | AY3: Bascula Harina | AZ3: Agua M³ | BA3: Bascula Mejorante A | BB3: Bascula Mejorante B | BC3: Flowbalacer 1 | BD3: Flowbalacer 2 | BE3: Flowbalacer 3 | BF3: Flowbalacer 4
A4: =IF(B4="","",1) | AD4: =IF(B4="","",(((C4+F4+H4+K4+Q4+N4+O4)*50))+((E4*10))+(((I4+J4+D4+G4+L4+M4+U4)*25)+(X4*25)+(Y4*25)+(Z4*25)+(AA4*25)+(AB4*40)+(AC4*50)+(R4*1)+(S4*1)+(T4*1))) | AE4: =IF(B4="","",C4+F4+H4+K4+Q4+N4+O4+((I4+J4+D4+G4)/2)+(R4/50)+(S4/50)+(T4/50)+(U4/2)+(E4/5)) | AF4: =IF(B4="","",((AE4*50)/AD4)) | AG4: =IF(C4="","",((Z4)*25)/AD4) | AH4: =IF(B4="","",(X4*25)/AD4) | AI4: =IF(B4="","",(Y4*25)/AD4) | AJ4: =IF(B4="","",(AA4*25)/AD4) | AK4: =IF(B4="","",(AB4*40)/AD4) | AL4: =IF(B4="","",(AC4*50)/AD4) | AM4: =IF(B4="","",B4) | AQ4: =IF(AN4="","",AN4/AO4) | AR4: =IF(AN4="","",(AD4/AN4)/1000) | AS4: =IF(AN4="","",AR4*24) | AT4: =IF(AN4="","",(AD4/1000)*100%/AS4) | AU4: =IF(AN4="","",(AE4/AN4)) | AV4: =IF(AN4="","",(AD4/AO4)/1000)
A5: =IF(B5="","",2) | AD5: =IF(B5="","",(((C5+F5+H5+K5+Q5+N5+O5)*50))+((E5*10))+(((I5+J5+D5+G5+L5+M5+U5)*25)+(X5*25)+(Y5*25)+(Z5*25)+(AA5*25)+(AB5*40)+(AC5*50)+(R5*1)+(S5*1)+(T5*1))) | AE5: =IF(B5="","",C5+F5+H5+K5+Q5+N5+O5+((I5+J5+D5+G5+U5)/2)+(R5/50)+(S5/50)+(T5/50)+(E5/5)) | AF5: =IF(B5="","",((AE5*50)/AD5)) | AG5: =IF(C5="","",((Z5)*25)/AD5) | AH5: =IF(B5="","",(X5*25)/AD5) | AI5: =IF(B5="","",(Y5*25)/AD5) | AJ5: =IF(B5="","",(AA5*25)/AD5) | AK5: =IF(B5="","",(AB5*40)/AD5) | AL5: =IF(B5="","",(AC5*50)/AD5) | AM5: =IF(B5="","",B5) | AQ5: =IF(AN5="","",AN5/AO5) | AR5: =IF(AN5="","",(AD5/AN5)/1000) | AS5: =IF(AN5="","",AR5*24) | AT5: =IF(AN5="","",(AD5/1000)*100%/AS5) | AU5: =IF(AN5="","",(AE5/AN5)) | AV5: =IF(AN5="","",(AD5/AO5)/1000)
A6: =IF(B6="","",3) | AD6: =IF(B6="","",(((C6+F6+H6+K6+Q6+N6+O6)*50))+((E6*10))+(((I6+J6+D6+G6+L6+M6+U6)*25)+(X6*25)+(Y6*25)+(Z6*25)+(AA6*25)+(AB6*40)+(AC6*50)+(R6*1)+(S6*1)+(T6*1))) | AE6: =IF(B6="","",C6+F6+H6+K6+Q6+N6+O6+((I6+J6+D6+G6+U6)/2)+(R6/50)+(S6/50)+(T6/50)+(E6/5)) | AF6: =IF(B6="","",((AE6*50)/AD6)) | AG6: =IF(C6="","",((Z6)*25)/AD6) | AH6: =IF(B6="","",(X6*25)/AD6) | AI6: =IF(B6="","",(Y6*25)/AD6) | AJ6: =IF(B6="","",(AA6*25)/AD6) | AK6: =IF(B6="","",(AB6*40)/AD6) | AL6: =IF(B6="","",(AC6*50)/AD6) | AM6: =IF(B6="","",B6) | AQ6: =IF(AN6="","",AN6/AO6) | AR6: =IF(AN6="","",(AD6/AN6)/1000) | AS6: =IF(AN6="","",AR6*24) | AT6: =IF(AN6="","",(AD6/1000)*100%/AS6) | AU6: =IF(AN6="","",(AE6/AN6)) | AV6: =IF(AN6="","",(AD6/AO6)/1000)
A7: =IF(B7="","",4) | AD7: =IF(B7="","",(((C7+F7+H7+K7+Q7+N7+O7)*50))+((E7*10))+(((I7+J7+D7+G7+L7+M7+U7)*25)+(X7*25)+(Y7*25)+(Z7*25)+(AA7*25)+(AB7*40)+(AC7*50)+(R7*1)+(S7*1)+(T7*1))) | AE7: =IF(B7="","",C7+F7+H7+K7+Q7+N7+O7+((I7+J7+D7+G7+U7)/2)+(R7/50)+(S7/50)+(T7/50)+(E7/5)) | AF7: =IF(B7="","",((AE7*50)/AD7)) | AG7: =IF(C7="","",((Z7)*25)/AD7) | AH7: =IF(B7="","",(X7*25)/AD7) | AI7: =IF(B7="","",(Y7*25)/AD7) | AJ7: =IF(B7="","",(AA7*25)/AD7) | AK7: =IF(B7="","",(AB7*40)/AD7) | AL7: =IF(B7="","",(AC7*50)/AD7) | AM7: =IF(B7="","",B7) | AQ7: =IF(AN7="","",AN7/AO7) | AR7: =IF(AN7="","",(AD7/AN7)/1000) | AS7: =IF(AN7="","",AR7*24) | AT7: =IF(AN7="","",(AD7/1000)*100%/AS7) | AU7: =IF(AN7="","",(AE7/AN7)) | AV7: =IF(AN7="","",(AD7/AO7)/1000)
A8: =IF(B8="","",5) | AD8: =IF(B8="","",(((C8+F8+H8+K8+Q8+N8+O8)*50))+((E8*10))+(((I8+J8+D8+G8+L8+M8+U8)*25)+(X8*25)+(Y8*25)+(Z8*25)+(AA8*25)+(AB8*40)+(AC8*50)+(R8*1)+(S8*1)+(T8*1))) | AE8: =IF(B8="","",C8+F8+H8+K8+Q8+N8+O8+((I8+J8+D8+G8+U8)/2)+(R8/50)+(S8/50)+(T8/50)+(E8/5)) | AF8: =IF(B8="","",((AE8*50)/AD8)) | AG8: =IF(C8="","",((Z8)*25)/AD8) | AH8: =IF(B8="","",(X8*25)/AD8) | AI8: =IF(B8="","",(Y8*25)/AD8) | AJ8: =IF(B8="","",(AA8*25)/AD8) | AK8: =IF(B8="","",(AB8*40)/AD8) | AL8: =IF(B8="","",(AC8*50)/AD8) | AM8: =IF(B8="","",B8) | AQ8: =IF(AN8="","",AN8/AO8) | AR8: =IF(AN8="","",(AD8/AN8)/1000) | AS8: =IF(AN8="","",AR8*24) | AT8: =IF(AN8="","",(AD8/1000)*100%/AS8) | AU8: =IF(AN8="","",(AE8/AN8)) | AV8: =IF(AN8="","",(AD8/AO8)/1000)
A9: =IF(B9="","",6) | AD9: =IF(B9="","",(((C9+F9+H9+K9+Q9+N9+O9)*50))+((E9*10))+(((I9+J9+D9+G9+L9+M9+U9)*25)+(X9*25)+(Y9*25)+(Z9*25)+(AA9*25)+(AB9*40)+(AC9*50)+(R9*1)+(S9*1)+(T9*1))) | AE9: =IF(B9="","",C9+F9+H9+K9+Q9+N9+O9+((I9+J9+D9+G9+U9)/2)+(R9/50)+(S9/50)+(T9/50)+(E9/5)) | AF9: =IF(B9="","",((AE9*50)/AD9)) | AG9: =IF(C9="","",((Z9)*25)/AD9) | AH9: =IF(B9="","",(X9*25)/AD9) | AI9: =IF(B9="","",(Y9*25)/AD9) | AJ9: =IF(B9="","",(AA9*25)/AD9) | AK9: =IF(B9="","",(AB9*40)/AD9) | AL9: =IF(B9="","",(AC9*50)/AD9) | AM9: =IF(B9="","",B9) | AQ9: =IF(AN9="","",AN9/AO9) | AR9: =IF(AN9="","",(AD9/AN9)/1000) | AS9: =IF(AN9="","",AR9*24) | AT9: =IF(AN9="","",(AD9/1000)*100%/AS9) | AU9: =IF(AN9="","",(AE9/AN9)) | AV9: =IF(AN9="","",(AD9/AO9)/1000)
A10: =IF(B10="","",7) | AD10: =IF(B10="","",(((C10+F10+H10+K10+Q10+N10+O10)*50))+((E10*10))+(((I10+J10+D10+G10+L10+M10+U10)*25)+(X10*25)+(Y10*25)+(Z10*25)+(AA10*25)+(AB10*40)+(AC10*50)+(R10*1)+(S10*1)+(T10*1))) | AE10: =IF(B10="","",C10+F10+H10+K10+Q10+N10+O10+((I10+J10+D10+G10+U10)/2)+(R10/50)+(S10/50)+(T10/50)+(E10/5)) | AF10: =IF(B10="","",((AE10*50)/AD10)) | AG10: =IF(C10="","",((Z10)*25)/AD10) | AH10: =IF(B10="","",(X10*25)/AD10) | AI10: =IF(B10="","",(Y10*25)/AD10) | AJ10: =IF(B10="","",(AA10*25)/AD10) | AK10: =IF(B10="","",(AB10*40)/AD10) | AL10: =IF(B10="","",(AC10*50)/AD10) | AM10: =IF(B10="","",B10) | AQ10: =IF(AN10="","",AN10/AO10) | AR10: =IF(AN10="","",(AD10/AN10)/1000) | AS10: =IF(AN10="","",AR10*24) | AT10: =IF(AN10="","",(AD10/1000)*100%/AS10) | AU10: =IF(AN10="","",(AE10/AN10)) | AV10: =IF(AN10="","",(AD10/AO10)/1000)
A11: =IF(B11="","",8) | AD11: =IF(B11="","",(((C11+F11+H11+K11+Q11+N11+O11)*50))+((E11*10))+(((I11+J11+D11+G11+L11+M11+U11)*25)+(X11*25)+(Y11*25)+(Z11*25)+(AA11*25)+(AB11*40)+(AC11*50)+(R11*1)+(S11*1)+(T11*1))) | AE11: =IF(B11="","",C11+F11+H11+K11+Q11+N11+O11+((I11+J11+D11+G11+U11+P11)/2)+(R11/50)+(S11/50)+(T11/50)+(E11/5)) | AF11: =IF(B11="","",((AE11*50)/AD11)) | AG11: =IF(C11="","",((Z11)*25)/AD11) | AH11: =IF(B11="","",(X11*25)/AD11) | AI11: =IF(B11="","",(Y11*25)/AD11) | AJ11: =IF(B11="","",(AA11*25)/AD11) | AK11: =IF(B11="","",(AB11*40)/AD11) | AL11: =IF(B11="","",(AC11*50)/AD11) | AM11: =IF(B11="","",B11) | AQ11: =IF(AN11="","",AN11/AO11) | AR11: =IF(AN11="","",(AD11/AN11)/1000) | AS11: =IF(AN11="","",AR11*24) | AT11: =IF(AN11="","",(AD11/1000)*100%/AS11) | AU11: =IF(AN11="","",(AE11/AN11)) | AV11: =IF(AN11="","",(AD11/AO11)/1000)
A12: =IF(B12="","",9) | AD12: =IF(B12="","",(((C12+F12+H12+K12+Q12+N12+O12)*50))+((E12*10))+(((I12+J12+D12+G12+L12+M12+U12)*25)+(X12*25)+(Y12*25)+(Z12*25)+(AA12*25)+(AB12*40)+(AC12*50)+(R12*1)+(S12*1)+(T12*1))) | AE12: =IF(B12="","",C12+F12+H12+K12+Q12+N12+O12+((I12+J12+D12+G12+U12)/2)+(R12/50)+(S12/50)+(T12/50)+(E12/5)) | AF12: =IF(B12="","",((AE12*50)/AD12)) | AG12: =IF(C12="","",((Z12)*25)/AD12) | AH12: =IF(B12="","",(X12*25)/AD12) | AI12: =IF(B12="","",(Y12*25)/AD12) | AJ12: =IF(B12="","",(AA12*25)/AD12) | AK12: =IF(B12="","",(AB12*40)/AD12) | AL12: =IF(B12="","",(AC12*50)/AD12) | AM12: =IF(B12="","",B12) | AQ12: =IF(AN12="","",AN12/AO12) | AR12: =IF(AN12="","",(AD12/AN12)/1000) | AS12: =IF(AN12="","",AR12*24) | AT12: =IF(AN12="","",(AD12/1000)*100%/AS12) | AU12: =IF(AN12="","",(AE12/AN12)) | AV12: =IF(AN12="","",(AD12/AO12)/1000)
A13: =IF(B13="","",11) | AD13: =IF(B13="","",(((C13+F13+H13+K13+Q13+N13+O13)*50))+((E13*10))+(((I13+J13+D13+G13+L13+M13+U13)*25)+(X13*25)+(Y13*25)+(Z13*25)+(AA13*25)+(AB13*40)+(AC13*50)+(R13*1)+(S13*1)+(T13*1))) | AE13: =IF(B13="","",C13+F13+H13+K13+Q13+N13+O13+((I13+J13+D13+G13+U13)/2)+(R13/50)+(S13/50)+(T13/50)+(E13/5)) | AF13: =IF(B13="","",((AE13*50)/AD13)) | AG13: =IF(C13="","",((Z13)*25)/AD13) | AH13: =IF(B13="","",(X13*25)/AD13) | AI13: =IF(B13="","",(Y13*25)/AD13) | AJ13: =IF(B13="","",(AA13*25)/AD13) | AK13: =IF(B13="","",(AB13*40)/AD13) | AL13: =IF(B13="","",(AC13*50)/AD13) | AM13: =IF(B13="","",B13) | AQ13: =IF(AN13="","",AN13/AO13) | AR13: =IF(AN13="","",(AD13/AN13)/1000) | AS13: =IF(AN13="","",AR13*24) | AT13: =IF(AN13="","",(AD13/1000)*100%/AS13) | AU13: =IF(AN13="","",(AE13/AN13)) | AV13: =IF(AN13="","",(AD13/AO13)/1000)
A14: =IF(B14="","",12) | AD14: =IF(B14="","",(((C14+F14+H14+K14+Q14+N14+O14)*50))+((E14*10))+(((I14+J14+D14+G14+L14+M14+U14)*25)+(X14*25)+(Y14*25)+(Z14*25)+(AA14*25)+(AB14*40)+(AC14*50)+(R14*1)+(S14*1)+(T14*1))) | AE14: =IF(B14="","",C14+F14+H14+K14+Q14+N14+O14+((I14+J14+D14+G14+U14)/2)+(R14/50)+(S14/50)+(T14/50)+(E14/5)) | AF14: =IF(B14="","",((AE14*50)/AD14)) | AG14: =IF(C14="","",((Z14)*25)/AD14) | AH14: =IF(B14="","",(X14*25)/AD14) | AI14: =IF(B14="","",(Y14*25)/AD14) | AJ14: =IF(B14="","",(AA14*25)/AD14) | AK14: =IF(B14="","",(AB14*40)/AD14) | AL14: =IF(B14="","",(AC14*50)/AD14) | AM14: =IF(B14="","",B14) | AQ14: =IF(AN14="","",AN14/AO14) | AR14: =IF(AN14="","",(AD14/AN14)/1000) | AS14: =IF(AN14="","",AR14*24) | AT14: =IF(AN14="","",(AD14/1000)*100%/AS14) | AU14: =IF(AN14="","",(AE14/AN14)) | AV14: =IF(AN14="","",(AD14/AO14)/1000)
A15: =IF(B15="","",13) | AD15: =IF(B15="","",(((C15+F15+H15+K15+Q15+N15+O15)*50))+((E15*10))+(((I15+J15+D15+G15+L15+M15+U15)*25)+(X15*25)+(Y15*25)+(Z15*25)+(AA15*25)+(AB15*40)+(AC15*50)+(R15*1)+(S15*1)+(T15*1))) | AE15: =IF(B15="","",C15+F15+H15+K15+Q15+N15+O15+((I15+J15+D15+G15+U15)/2)+(R15/50)+(S15/50)+(T15/50)+(E15/5)) | AF15: =IF(B15="","",((AE15*50)/AD15)) | AG15: =IF(C15="","",((Z15)*25)/AD15) | AH15: =IF(B15="","",(X15*25)/AD15) | AI15: =IF(B15="","",(Y15*25)/AD15) | AJ15: =IF(B15="","",(AA15*25)/AD15) | AK15: =IF(B15="","",(AC15*40)/AD15) | AL15: =IF(B15="","",(AC15*50)/AD15) | AM15: =IF(B15="","",B15) | AQ15: =IF(AN15="","",AN15/AO15) | AR15: =IF(AN15="","",(AD15/AN15)/1000) | AS15: =IF(AN15="","",AR15*24) | AT15: =IF(AN15="","",(AD15/1000)*100%/AS15) | AU15: =IF(AN15="","",(AE15/AN15)) | AV15: =IF(AN15="","",(AD15/AO15)/1000)
A16: =IF(B16="","",1+A15) | AD16: =IF(B16="","",(((C16+F16+H16+K16+Q16+N16+O16)*50))+((E16*10))+(((I16+J16+D16+G16+L16+M16+U16)*25)+(X16*25)+(Y16*25)+(Z16*25)+(AA16*25)+(AB16*40)+(AC16*50)+(R16*1)+(S16*1)+(T16*1))) | AE16: =IF(B16="","",C16+F16+H16+K16+Q16+N16+O16+((I16+J16+D16+G16+U16)/2)+(R16/50)+(S16/50)+(T16/50)+(E16/5)) | AF16: =IF(B16="","",((AE16*50)/AD16)) | AG16: =IF(C16="","",((Z16)*25)/AD16) | AH16: =IF(B16="","",(X16*25)/AD16) | AI16: =IF(B16="","",(Y16*25)/AD16) | AJ16: =IF(B16="","",(AA16*25)/AD16) | AK16: =IF(B16="","",(AB16*40)/AD16) | AL16: =IF(B16="","",(AC16*50)/AD16) | AM16: =IF(B16="","",B16) | AQ16: =IF(AN16="","",AN16/AO16) | AR16: =IF(AN16="","",(AD16/AN16)/1000) | AS16: =IF(AN16="","",AR16*24) | AT16: =IF(AN16="","",(AD16/1000)*100%/AS16) | AU16: =IF(AN16="","",(AE16/AN16)) | AV16: =IF(AN16="","",(AD16/AO16)/1000)
A17: =IF(B17="","",15) | AD17: =IF(B17="","",(((C17+F17+H17+K17+Q17+N17+O17)*50))+((E17*10))+(((I17+J17+D17+G17+L17+M17+U17)*25)+(X17*25)+(Y17*25)+(Z17*25)+(AA17*25)+(AB17*40)+(AC17*50)+(R17*1)+(S17*1)+(T17*1))) | AE17: =IF(B17="","",C17+F17+H17+K17+Q17+N17+O17+((I17+J17+D17+G17+U17)/2)+(R17/50)+(S17/50)+(T17/50)+(E17/5)) | AF17: =IF(B17="","",((AE17*50)/AD17)) | AG17: =IF(C17="","",((Z17)*25)/AD17) | AH17: =IF(B17="","",(X17*25)/AD17) | AI17: =IF(B17="","",(Y17*25)/AD17) | AJ17: =IF(B17="","",(AA17*25)/AD17) | AK17: =IF(B17="","",(AB17*40)/AD17) | AL17: =IF(B17="","",(AC17*50)/AD17) | AM17: =IF(B17="","",B17) | AQ17: =IF(AN17="","",AN17/AO17) | AR17: =IF(AN17="","",(AD17/AN17)/1000) | AS17: =IF(AN17="","",AR17*24) | AT17: =IF(AN17="","",(AD17/1000)*100%/AS17) | AU17: =IF(AN17="","",(AE17/AN17)) | AV17: =IF(AN17="","",(AD17/AO17)/1000)
A18: =IF(B18="","",16) | AD18: =IF(B18="","",(((C18+F18+H18+K18+Q18+N18+O18)*50))+((E18*10))+(((I18+J18+D18+G18+L18+M18+U18)*25)+(X18*25)+(Y18*25)+(Z18*25)+(AA18*25)+(AB18*40)+(AC18*50)+(R18*1)+(S18*1)+(T18*1))) | AE18: =IF(B18="","",C18+F18+H18+K18+Q18+N18+O18+((I18+J18+D18+G18+U18)/2)+(R18/50)+(S18/50)+(T18/50)+(E18/5)) | AF18: =IF(B18="","",((AE18*50)/AD18)) | AG18: =IF(C18="","",((Z18)*25)/AD18) | AH18: =IF(B18="","",(X18*25)/AD18) | AI18: =IF(B18="","",(Y18*25)/AD18) | AJ18: =IF(B18="","",(AA18*25)/AD18) | AK18: =IF(B18="","",(AB18*40)/AD18) | AL18: =IF(B18="","",(AC18*50)/AD18) | AM18: =IF(B18="","",B18) | AQ18: =IF(AN18="","",AN18/AO18) | AR18: =IF(AN18="","",(AD18/AN18)/1000) | AS18: =IF(AN18="","",AR18*24) | AT18: =IF(AN18="","",(AD18/1000)*100%/AS18) | AU18: =IF(AN18="","",(AE18/AN18)) | AV18: =IF(AN18="","",(AD18/AO18)/1000)
A19: =IF(B19="","",17) | AD19: =IF(B19="","",(((C19+F19+H19+K19+Q19+N19+O19)*50))+((E19*10))+(((I19+J19+D19+G19+L19+M19+U19)*25)+(X19*25)+(Y19*25)+(Z19*25)+(AA19*25)+(AB19*40)+(AC19*50)+(R19*1)+(S19*1)+(T19*1))) | AE19: =IF(B19="","",C19+F19+H19+K19+Q19+N19+O19+((I19+J19+D19+G19+U19)/2)+(R19/50)+(S19/50)+(T19/50)+(E19/5)) | AF19: =IF(B19="","",((AE19*50)/AD19)) | AG19: =IF(C19="","",((Z19)*25)/AD19) | AH19: =IF(B19="","",(X19*25)/AD19) | AI19: =IF(B19="","",(Y19*25)/AD19) | AJ19: =IF(B19="","",(AA19*25)/AD19) | AK19: =IF(B19="","",(AB19*40)/AD19) | AL19: =IF(B19="","",(AC19*50)/AD19) | AM19: =IF(B19="","",B19) | AQ19: =IF(AN19="","",AN19/AO19) | AR19: =IF(AN19="","",(AD19/AN19)/1000) | AS19: =IF(AN19="","",AR19*24) | AT19: =IF(AN19="","",(AD19/1000)*100%/AS19) | AU19: =IF(AN19="","",(AE19/AN19)) | AV19: =IF(AN19="","",(AD19/AO19)/1000)
A20: =IF(B20="","",1+A19) | AD20: =IF(B20="","",(((C20+F20+H20+K20+Q20+N20+O20)*50))+((E20*10))+(((I20+J20+D20+G20+L20+M20+U20)*25)+(X20*25)+(Y20*25)+(Z20*25)+(AA20*25)+(AB20*40)+(AC20*50)+(R20*1)+(S20*1)+(T20*1))) | AE20: =IF(B20="","",C20+F20+H20+K20+Q20+N20+O20+((I20+J20+D20+G20+U20)/2)+(R20/50)+(S20/50)+(T20/50)+(E20/5)) | AF20: =IF(B20="","",((AE20*50)/AD20)) | AG20: =IF(C20="","",((Z20)*25)/AD20) | AH20: =IF(B20="","",(X20*25)/AD20) | AI20: =IF(B20="","",(Y20*25)/AD20) | AJ20: =IF(B20="","",(AA20*25)/AD20) | AK20: =IF(B20="","",(AB20*40)/AD20) | AL20: =IF(B20="","",(AC20*50)/AD20) | AM20: =IF(B20="","",B20) | AQ20: =IF(AN20="","",AN20/AO20) | AR20: =IF(AN20="","",(AD20/AN20)/1000) | AS20: =IF(AN20="","",AR20*24) | AT20: =IF(AN20="","",(AD20/1000)*100%/AS20) | AU20: =IF(AN20="","",(AE20/AN20)) | AV20: =IF(AN20="","",(AD20/AO20)/1000)
A21: =IF(B21="","",1+A20) | AE21: =IF(B21="","",C21+F21+H21+K21+Q21+N21+O21+((I21+J21+D21+G21+U21)/2)+(R21/50)+(S21/50)+(T21/50)+(E21/5)) | AF21: =IF(B21="","",((AE21*50)/AD21)) | AG21: =IF(C21="","",((Z21)*25)/AD21) | AH21: =IF(B21="","",(X21*25)/AD21) | AI21: =IF(B21="","",(Y21*25)/AD21) | AJ21: =IF(B21="","",(AA21*25)/AD21) | AK21: =IF(B21="","",(AB21*40)/AD21) | AL21: =IF(B21="","",(AC21*50)/AD21) | AM21: =IF(B21="","",B21) | AQ21: =IF(AN21="","",AN21/AO21) | AR21: =IF(AN21="","",(AD21/AN21)/1000) | AS21: =IF(AN21="","",AR21*24) | AT21: =IF(AN21="","",(AD21/1000)*100%/AS21) | AU21: =IF(AN21="","",(AE21/AN21)) | AV21: =IF(AN21="","",(AD21/AO21)/1000)
A22: =IF(B22="","",1+A21) | AD22: =IF(B22="","",(((C22+F22+H22+K22+Q22+N22+O22)*50))+((E22*10))+(((I22+J22+D22+G22+L22+M22+U22)*25)+(X22*25)+(Y22*25)+(Z22*25)+(AA22*25)+(AB22*40)+(AC22*50)+(R22*1)+(S22*1)+(T22*1))) | AE22: =IF(B22="","",C22+F22+H22+K22+Q22+N22+O22+((I22+J22+D22+G22+U22)/2)+(R22/50)+(S22/50)+(T22/50)+(E22/5)) | AF22: =IF(B22="","",((AE22*50)/AD22)) | AG22: =IF(C22="","",((Z22)*25)/AD22) | AH22: =IF(B22="","",(X22*25)/AD22) | AI22: =IF(B22="","",(Y22*25)/AD22) | AJ22: =IF(B22="","",(AA22*25)/AD22) | AK22: =IF(B22="","",(AB22*40)/AD22) | AL22: =IF(B22="","",(AC22*50)/AD22) | AM22: =IF(B22="","",B22) | AQ22: =IF(AN22="","",AN22/AO22) | AR22: =IF(AN22="","",(AD22/AN22)/1000) | AS22: =IF(AN22="","",AR22*24) | AT22: =IF(AN22="","",(AD22/1000)*100%/AS22) | AU22: =IF(AN22="","",(AE22/AN22)) | AV22: =IF(AN22="","",(AD22/AO22)/1000)
A23: =IF(B23="","",1+A22) | AE23: =IF(B23="","",C23+F23+H23+K23+Q23+N23+O23+((I23+J23+D23+G23+U23)/2)+(R23/50)+(S23/50)+(T23/50)+(E23/5)) | AF23: =IF(B23="","",((AE23*50)/AD23)) | AG23: =IF(C23="","",((Z23)*25)/AD23) | AH23: =IF(B23="","",(X23*25)/AD23) | AI23: =IF(B23="","",(Y23*25)/AD23) | AJ23: =IF(B23="","",(AA23*25)/AD23) | AK23: =IF(B23="","",(AB23*40)/AD23) | AL23: =IF(B23="","",(AC23*50)/AD23) | AM23: =IF(B23="","",B23) | AQ23: =IF(AN23="","",AN23/AO23) | AR23: =IF(AN23="","",(AD23/AN23)/1000) | AS23: =IF(AN23="","",AR23*24) | AT23: =IF(AN23="","",(AD23/1000)*100%/AS23) | AU23: =IF(AN23="","",(AE23/AN23)) | AV23: =IF(AN23="","",(AD23/AO23)/1000)
A24: =IF(B24="","",1+A23) | AD24: =IF(B24="","",(((C24+F24+H24+K24+Q24+N24+O24)*50))+((E24*10))+(((I24+J24+D24+G24+L24+M24+U24)*25)+(X24*25)+(Y24*25)+(Z24*25)+(AA24*25)+(AB24*40)+(AC24*50)+(R24*1)+(S24*1)+(T24*1))) | AE24: =IF(B24="","",C24+F24+H24+K24+Q24+N24+O24+((I24+J24+D24+G24+U24)/2)+(R24/50)+(S24/50)+(T24/50)+(E24/5)) | AF24: =IF(B24="","",((AE24*50)/AD24)) | AG24: =IF(C24="","",((Z24)*25)/AD24) | AH24: =IF(B24="","",(X24*25)/AD24) | AI24: =IF(B24="","",(Y24*25)/AD24) | AJ24: =IF(B24="","",(AA24*25)/AD24) | AK24: =IF(B24="","",(AB24*40)/AD24) | AL24: =IF(B24="","",(AC24*50)/AD24) | AM24: =IF(B24="","",B24) | AQ24: =IF(AN24="","",AN24/AO24) | AR24: =IF(AN24="","",(AD24/AN24)/1000) | AS24: =IF(AN24="","",AR24*24) | AT24: =IF(AN24="","",(AD24/1000)*100%/AS24) | AU24: =IF(AN24="","",(AE24/AN24)) | AV24: =IF(AN24="","",(AD24/AO24)/1000)
AD25: =IF(B25="","",(((C25+F25+H25+K25+Q25+N25+O25)*50))+((E25*10))+(((I25+J25+D25+G25+L25+M25+U25)*25)+(X25*25)+(Y25*25)+(Z25*25)+(AA25*25)+(AB25*40)+(AC25*50)+(R25*1)+(S25*1)+(T25*1))) | AE25: =IF(B25="","",C25+F25+H25+K25+Q25+N25+O25+((I25+J25+D25+G25+U25)/2)+(R25/50)+(S25/50)+(T25/50)+(E25/5)) | AF25: =IF(B25="","",((AE25*50)/AD25)) | AG25: =IF(C25="","",((Z25)*25)/AD25) | AH25: =IF(B25="","",(X25*25)/AD25) | AI25: =IF(B25="","",(Y25*25)/AD25) | AJ25: =IF(B25="","",(AA25*25)/AD25) | AK25: =IF(B25="","",(AB25*40)/AD25) | AL25: =IF(B25="","",(AC25*50)/AD25) | AM25: =IF(B25="","",B25) | AQ25: =IF(AN25="","",AN25/AO25) | AR25: =IF(AN25="","",(AD25/AN25)/1000) | AS25: =IF(AN25="","",AR25*24) | AT25: =IF(AN25="","",(AD25/1000)*100%/AS25) | AU25: =IF(AN25="","",(AE25/AN25)) | AV25: =IF(AN25="","",(AD25/AO25)/1000)
AD26: =IF(B26="","",(((C26+F26+H26+K26+Q26+N26+O26)*50))+((E26*10))+(((I26+J26+D26+G26+L26+M26+U26)*25)+(X26*25)+(Y26*25)+(Z26*25)+(AA26*25)+(AB26*40)+(AC26*50)+(R26*1)+(S26*1)+(T26*1))) | AE26: =IF(B26="","",C26+F26+H26+K26+Q26+N26+O26+((I26+J26+D26+G26+U26)/2)+(R26/50)+(S26/50)+(T26/50)+(E26/5)) | AF26: =IF(B26="","",((AE26*50)/AD26)) | AG26: =IF(C26="","",((Z26)*25)/AD26) | AH26: =IF(B26="","",(X26*25)/AD26) | AI26: =IF(B26="","",(Y26*25)/AD26) | AJ26: =IF(B26="","",(AA26*25)/AD26) | AK26: =IF(B26="","",(AB26*40)/AD26) | AL26: =IF(B26="","",(AC26*50)/AD26) | AM26: =IF(B26="","",B26) | AQ26: =IF(AN26="","",AN26/AO26) | AR26: =IF(AN26="","",(AD26/AN26)/1000) | AS26: =IF(AN26="","",AR26*24) | AT26: =IF(AN26="","",(AD26/1000)*100%/AS26) | AU26: =IF(AN26="","",(AE26/AN26)) | AV26: =IF(AN26="","",(AD26/AO26)/1000)
AD27: =IF(B27="","",(((C27+F27+H27+K27+Q27+N27+O27)*50))+((E27*10))+(((I27+J27+D27+G27+L27+M27+U27)*25)+(X27*25)+(Y27*25)+(Z27*25)+(AA27*25)+(AB27*40)+(AC27*50)+(R27*1)+(S27*1)+(T27*1))) | AE27: =IF(B27="","",C27+F27+H27+K27+Q27+N27+O27+((I27+J27+D27+G27+U27)/2)+(R27/50)+(S27/50)+(T27/50)+(E27/5)) | AF27: =IF(B27="","",((AE27*50)/AD27)) | AG27: =IF(C27="","",((Z27)*25)/AD27) | AH27: =IF(B27="","",(X27*25)/AD27) | AI27: =IF(B27="","",(Y27*25)/AD27) | AJ27: =IF(B27="","",(AA27*25)/AD27) | AK27: =IF(B27="","",(AB27*40)/AD27) | AL27: =IF(B27="","",(AC27*50)/AD27) | AM27: =IF(B27="","",B27) | AQ27: =IF(AN27="","",AN27/AO27) | AR27: =IF(AN27="","",(AD27/AN27)/1000) | AS27: =IF(AN27="","",AR27*24) | AT27: =IF(AN27="","",(AD27/1000)*100%/AS27) | AU27: =IF(AN27="","",(AE27/AN27)) | AV27: =IF(AN27="","",(AD27/AO27)/1000)
AD28: =IF(B28="","",(((C28+F28+H28+K28+Q28+N28+O28)*50))+((E28*10))+(((I28+J28+D28+G28+L28+M28+U28)*25)+(X28*25)+(Y28*25)+(Z28*25)+(AA28*25)+(AB28*40)+(AC28*50)+(R28*1)+(S28*1)+(T28*1))) | AE28: =IF(B28="","",C28+F28+H28+K28+Q28+N28+O28+((I28+J28+D28+G28+U28)/2)+(R28/50)+(S28/50)+(T28/50)+(E28/5)) | AF28: =IF(B28="","",((AE28*50)/AD28)) | AG28: =IF(C28="","",((Z28)*25)/AD28) | AH28: =IF(B28="","",(X28*25)/AD28) | AI28: =IF(B28="","",(Y28*25)/AD28) | AJ28: =IF(B28="","",(AA28*25)/AD28) | AK28: =IF(B28="","",(AB28*40)/AD28) | AL28: =IF(B28="","",(AC28*50)/AD28) | AM28: =IF(B28="","",B28) | AQ28: =IF(AN28="","",AN28/AO28) | AR28: =IF(AN28="","",(AD28/AN28)/1000) | AS28: =IF(AN28="","",AR28*24) | AT28: =IF(AN28="","",(AD28/1000)*100%/AS28) | AU28: =IF(AN28="","",(AE28/AN28)) | AV28: =IF(AN28="","",(AD28/AO28)/1000)
AD29: =IF(B29="","",(((C29+F29+H29+K29+Q29+N29+O29)*50))+((E29*10))+(((I29+J29+D29+G29+L29+M29+U29)*25)+(X29*25)+(Y29*25)+(Z29*25)+(AA29*25)+(AB29*40)+(AC29*50)+(R29*1)+(S29*1)+(T29*1))) | AE29: =IF(B29="","",C29+F29+H29+K29+Q29+N29+O29+((I29+J29+D29+G29+U29)/2)+(R29/50)+(S29/50)+(T29/50)+(E29/5)) | AF29: =IF(B29="","",((AE29*50)/AD29)) | AG29: =IF(C29="","",((Z29)*25)/AD29) | AH29: =IF(B29="","",(X29*25)/AD29) | AI29: =IF(B29="","",(Y29*25)/AD29) | AJ29: =IF(B29="","",(AA29*25)/AD29) | AK29: =IF(B29="","",(AB29*40)/AD29) | AL29: =IF(B29="","",(AC29*50)/AD29) | AM29: =IF(B29="","",B29) | AQ29: =IF(AN29="","",AN29/AO29) | AR29: =IF(AN29="","",(AD29/AN29)/1000) | AS29: =IF(AN29="","",AR29*24) | AT29: =IF(AN29="","",(AD29/1000)*100%/AS29) | AU29: =IF(AN29="","",(AE29/AN29)) | AV29: =IF(AN29="","",(AD29/AO29)/1000)
A30: =IF(B30="","",1+A29) | AD30: =IF(B30="","",(((C30+F30+H30+K30+Q30+N30+O30)*50))+((E30*10))+(((I30+J30+D30+G30+L30+M30+U30)*25)+(X30*25)+(Y30*25)+(Z30*25)+(AA30*25)+(AB30*40)+(AC30*50)+(R30*1)+(S30*1)+(T30*1))) | AE30: =IF(B30="","",C30+F30+H30+K30+Q30+N30+O30+((I30+J30+D30+G30+U30)/2)+(R30/50)+(S30/50)+(T30/50)+(E30/5)) | AF30: =IF(B30="","",((AE30*50)/AD30)) | AG30: =IF(C30="","",((Z30)*25)/AD30) | AH30: =IF(B30="","",(X30*25)/AD30) | AI30: =IF(B30="","",(Y30*25)/AD30) | AJ30: =IF(B30="","",(AA30*25)/AD30) | AK30: =IF(B30="","",(AB30*40)/AD30) | AL30: =IF(B30="","",(AC30*50)/AD30) | AM30: =IF(B30="","",B30) | AQ30: =IF(AN30="","",AN30/AO30) | AR30: =IF(AN30="","",(AD30/AN30)/1000) | AS30: =IF(AN30="","",AR30*24) | AT30: =IF(AN30="","",(AD30/1000)*100%/AS30) | AU30: =IF(AN30="","",(AE30/AN30)) | AV30: =IF(AN30="","",(AD30/AO30)/1000)
A31: =IF(B31="","",1+A30) | AD31: =IF(B31="","",(((C31+F31+H31+K31+Q31+N31+O31)*50))+((E31*10))+(((I31+J31+D31+G31+L31+M31+U31)*25)+(X31*25)+(Y31*25)+(Z31*25)+(AA31*25)+(AB31*40)+(AC31*50)+(R31*1)+(S31*1)+(T31*1))) | AE31: =IF(B31="","",C31+F31+H31+K31+Q31+N31+O31+((I31+J31+D31+G31+U31)/2)+(R31/50)+(S31/50)+(T31/50)+(E31/5)) | AF31: =IF(B31="","",((AE31*50)/AD31)) | AG31: =IF(C31="","",((Z31)*25)/AD31) | AH31: =IF(B31="","",(X31*25)/AD31) | AI31: =IF(B31="","",(Y31*25)/AD31) | AJ31: =IF(B31="","",(AA31*25)/AD31) | AK31: =IF(B31="","",(AB31*40)/AD31) | AL31: =IF(B31="","",(AC31*50)/AD31) | AM31: =IF(B31="","",B31) | AQ31: =IF(AN31="","",AN31/AO31) | AR31: =IF(AN31="","",(AD31/AN31)/1000) | AS31: =IF(AN31="","",AR31*24) | AT31: =IF(AN31="","",(AD31/1000)*100%/AS31) | AU31: =IF(AN31="","",(AE31/AN31)) | AV31: =IF(AN31="","",(AD31/AO31)/1000)
A32: =IF(B32="","",1+A31) | AD32: =IF(B32="","",(((C32+F32+H32+K32+Q32+N32+O32)*50))+((E32*10))+(((I32+J32+D32+G32+L32+M32+U32)*25)+(X32*25)+(Y32*25)+(Z32*25)+(AA32*25)+(AB32*40)+(AC32*50)+(R32*1)+(S32*1)+(T32*1))) | AE32: =IF(B32="","",C32+F32+H32+K32+Q32+N32+O32+((I32+J32+D32+G32+U32)/2)+(R32/50)+(S32/50)+(T32/50)+(E32/5)) | AF32: =IF(B32="","",((AE32*50)/AD32)) | AG32: =IF(C32="","",((Z32)*25)/AD32) | AH32: =IF(B32="","",(X32*25)/AD32) | AI32: =IF(B32="","",(Y32*25)/AD32) | AJ32: =IF(B32="","",(AA32*25)/AD32) | AK32: =IF(B32="","",(AB32*40)/AD32) | AL32: =IF(B32="","",(AC32*50)/AD32) | AM32: =IF(B32="","",B32) | AQ32: =IF(AN32="","",AN32/AO32) | AR32: =IF(AN32="","",(AD32/AN32)/1000) | AS32: =IF(AN32="","",AR32*24) | AT32: =IF(AN32="","",(AD32/1000)*100%/AS32) | AU32: =IF(AN32="","",(AE32/AN32)) | AV32: =IF(AN32="","",(AD32/AO32)/1000)
A33: =IF(B33="","",1+A32) | AD33: =IF(B33="","",(((C33+F33+H33+K33+Q33+N33+O33)*50))+((E33*10))+(((I33+J33+D33+G33+L33+M33+U33)*25)+(X33*25)+(Y33*25)+(Z33*25)+(AA33*25)+(AB33*40)+(AC33*50)+(R33*1)+(S33*1)+(T33*1))) | AE33: =IF(B33="","",C33+F33+H33+K33+Q33+N33+O33+((I33+J33+D33+G33+U33)/2)+(R33/50)+(S33/50)+(T33/50)+(E33/5)) | AF33: =IF(B33="","",((AE33*50)/AD33)) | AG33: =IF(C33="","",((Z33)*25)/AD33) | AH33: =IF(B33="","",(X33*25)/AD33) | AI33: =IF(B33="","",(Y33*25)/AD33) | AJ33: =IF(B33="","",(AA33*25)/AD33) | AK33: =IF(B33="","",(AB33*40)/AD33) | AL33: =IF(B33="","",(AC33*50)/AD33) | AM33: =IF(B33="","",B33) | AQ33: =IF(AN33="","",AN33/AO33) | AR33: =IF(AN33="","",(AD33/AN33)/1000) | AS33: =IF(AN33="","",AR33*24) | AT33: =IF(AN33="","",(AD33/1000)*100%/AS33) | AU33: =IF(AN33="","",(AE33/AN33)) | AV33: =IF(AN33="","",(AD33/AO33)/1000)
A34: =IF(B34="","",1+A33) | AD34: =IF(B34="","",(((C34+F34+H34+K34+Q34+N34+O34)*50))+((E34*10))+(((I34+J34+D34+G34+L34+M34+U34)*25)+(X34*25)+(Y34*25)+(Z34*25)+(AA34*25)+(AB34*40)+(AC34*50)+(R34*1)+(S34*1)+(T34*1))) | AE34: =IF(B34="","",C34+F34+H34+K34+Q34+N34+O34+((I34+J34+D34+G34+U34)/2)+(R34/50)+(S34/50)+(T34/50)+(E34/5)) | AF34: =IF(B34="","",((AE34*50)/AD34)) | AG34: =IF(C34="","",((Z34)*25)/AD34) | AH34: =IF(B34="","",(X34*25)/AD34) | AI34: =IF(B34="","",(Y34*25)/AD34) | AJ34: =IF(B34="","",(AA34*25)/AD34) | AK34: =IF(B34="","",(AB34*40)/AD34) | AL34: =IF(B34="","",(AC34*50)/AD34) | AM34: =IF(B34="","",B34) | AQ34: =IF(AN34="","",AN34/AO34) | AR34: =IF(AN34="","",(AD34/AN34)/1000) | AS34: =IF(AN34="","",AR34*24) | AT34: =IF(AN34="","",(AD34/1000)*100%/AS34) | AU34: =IF(AN34="","",(AE34/AN34)) | AV34: =IF(AN34="","",(AD34/AO34)/1000)
A35: =IF(B35="","",1+A34) | AD35: =IF(B35="","",(((C35+F35+H35+K35+Q35+N35+O35)*50))+((E35*10))+(((I35+J35+D35+G35+L35+M35+U35)*25)+(X35*25)+(Y35*25)+(Z35*25)+(AA35*25)+(AB35*40)+(AC35*50)+(R35*1)+(S35*1)+(T35*1))) | AE35: =IF(B35="","",C35+F35+H35+K35+Q35+N35+O35+((I35+J35+D35+G35+U35)/2)+(R35/50)+(S35/50)+(T35/50)+(E35/5)) | AF35: =IF(B35="","",((AE35*50)/AD35)) | AG35: =IF(C35="","",((Z35)*25)/AD35) | AH35: =IF(B35="","",(X35*25)/AD35) | AI35: =IF(B35="","",(Y35*25)/AD35) | AJ35: =IF(B35="","",(AA35*25)/AD35) | AK35: =IF(B35="","",(AB35*40)/AD35) | AL35: =IF(B35="","",(AC35*50)/AD35) | AM35: =IF(B35="","",B35) | AQ35: =IF(AN35="","",AN35/AO35) | AR35: =IF(AN35="","",(AD35/AN35)/1000) | AS35: =IF(AN35="","",AR35*24) | AT35: =IF(AN35="","",(AD35/1000)*100%/AS35) | AU35: =IF(AN35="","",(AE35/AN35)) | AV35: =IF(AN35="","",(AD35/AO35)/1000)
B36: Total | C36: =SUM(C4:C35) -> 0 | D36: =SUM(D4:D35) -> 0 | E36: =SUM(E4:E35) -> 0 | F36: =SUM(F4:F35) -> 0 | G36: =SUM(G4:G35) -> 0 | H36: =SUM(H4:H35) -> 0 | I36: =SUM(I4:I35) -> 0 | J36: =SUM(J4:J35) -> 0 | ... AE36: =SUM(AE4:AE35) -> 0 | AF36: =IF(AD40=0,"",(AE36*50)/AD36) | AG36: =IF(AD40=0,"",(Z36*50)/AD36) | AH36: =IF(AD40=0,"",(X36*25)/AD36) | AI36: =IF(AD40=0,"",(Y36*25)/AD36) | AJ36: =IF(AD40=0,"",(AA36*25)/AD36) | AK36: =IF(AD40=0,"",(AB36*40)/AD36) | AL36: =IF(AD40=0,"",(AC36*50)/AD36) | AM36: Total | AN36: =SUM(AN4:AN35) -> 0 | AO36: =SUM(AO4:AO35) -> 0 | AP36: =SUM(AP4:AP35) -> 0 | AQ36: =IF(AN36=0,"",AN36/AO36) | AR36: =IF(AN36=0,"",(AD36/AN36)/1000) | AS36: =IF(AN36=0,"",AR36*24) | AT36: =IF(AN36=0,"",AD40/(AS36*26)) | AU36: =IF(AN36=0,"",(AE36/AN36)) | AV36: =IF(AO36=0,"",(AD36/AO36)/1000) | AW36: =SUM(AW4:AW35)/1000 -> 0 | AX36: =SUM(AX4:AX35)/1000 -> 0 | AY36: =SUM(AY4:AY35)/1000 -> 0 | AZ36: =SUM(AZ4) -> 0 | BA36: =SUM(BA4:BA35) -> 0 | BB36: =SUM(BB4:BB35) -> 0 | BC36: =SUM(BC4:BC35)/1000 -> 0 | BD36: =SUM(BD4:BD35)/1000 -> 0 | BE36: =SUM(BE4:BE35)/1000 -> 0 | BF36: =SUM(BF4:BF35)/1000 -> 0
B37: Promedio | C37: =IF(C36=0,"",AVERAGE(C4:C35)) | D37: =IF(D36=0,"",AVERAGE(D4:D35)) | E37: =IF(E36=0,"",AVERAGE(E4:E35)) | F37: =IF(F36=0,"",AVERAGE(F4:F35)) | G37: =IF(G36=0,"",AVERAGE(G4:G35)) | H37: =IF(H36=0,"",AVERAGE(H4:H35)) | I37: =IF(I36=0,"",AVERAGE(I4:I35)) | J37: =IF(J36=0,"",AVERAGE(J4:J35)) | K37: =IF(K36=0,"",AVERAGE(K4:K35)) | N37: =IF(N36=0,"",AVERAGE(N4:N35)) | O37: =IF(O36=0,"",AVERAGE(O4:O35)) | P37: =IF(P36=0,"",AVERAGE(P4:P35)) | Q37: =IF(Q36=0,"",AVERAGE(Q4:Q35)) | R37: =IF(R36=0,"",AVERAGE(R4:R35)) | S37: =IF(S36=0,"",AVERAGE(S4:S35)) | T37: =IF(T36=0,"",AVERAGE(T4:T35)) | U37: =IF(U36=0,"",AVERAGE(U4:U35)) | ... AC37: =IF(AC36=0,"",AVERAGE(AC4:AC35)) | AM37: Promedio | AN37: =IF(AN36=0,"",AVERAGE(AN4:AN35)) | AO37: =IF(AO36=0,"",AVERAGE(AO4:AO35)) | AP37: =IF(AP36=0,"",AVERAGE(AP4:AP35)) | AQ37: =IF(AQ36="","",AVERAGE(AQ4:AQ35)) | AR37: =IF(AR36="","",AVERAGE(AR4:AR35)) | AS37: =IF(AS36="","",AVERAGE(AS4:AS35)) | AT37: =IF(AT36="","",AVERAGE(AT4:AT35)) | AU37: =IF(AU36="","",AVERAGE(AU4:AU35)) | AV37: =IF(AV36="","",AVERAGE(AV4:AV35))
B38: Cambio de Mezcla | AD38: Total Kg.
AE39: Total Tm.
B40: Total | C40: =SUM(C4:C35) -> 0 | D40: =SUM(D4:D35) -> 0 | E40: =SUM(E4:E35) -> 0 | F40: =SUM(F4:F35) -> 0 | G40: =SUM(G4:G35) -> 0 | H40: =SUM(H4:H35) -> 0 | I40: =SUM(I4:I35) -> 0 | J40: =SUM(J4:J35) -> 0 | ... AC40: =SUM(AC4:AC35) -> 0 | AD40: =AD36/1000 -> 0
A42: Grano entero | AD42: =(Z42+AA42)*25.8 -> 0 | AE42: =Z42 -> 0 | AF42: =IF(B42="","",((AE42*25)/AD42)) | AG42: =IF(B42="","",((Z42)*25)/AD42) | AH42: =IF(B42="","",(X42*25)/AD42) | AI42: =IF(B42="","",(Y42*25)/AD42) | AJ42: =IF(B42="","",(AA42*25)/AD42) | AK42: =IF(B42="","",(AB42*40)/AD42) | AL42: =IF(B42="","",(AC42*50)/AD42) | AM42: =IF(B42="","",B42) | AQ42: =IF(AN42="","",AN42/AO42) | AR42: =IF(AN42="","",(AD42/AN42)/1000) | AS42: =IF(AN42="","",AR42*24) | AT42: =IF(AN42="","",(AD42/1000)*100%/AS42) | AU42: =IF(AN42="","",(AE42/AN42)) | AV42: =IF(AN42="","",(AD42/AO42)/1000)
A43: Bio Convercion | AD43: =(Z43*25)+(AA43*25)+(AB43*40)+(AC43*50) -> 0 | AE43: =IF(B43="","",C43+E43+G43+K43+N43+O43+Q43+R43+((D43+H43)/4)+((F43+I43+J43+T43+Z43)/2)) | AF43: =IF(B43="","",((AE43*50)/AD43)) | AG43: =IF(B43="","",((Z43)*25)/AD43) | AH43: =IF(B43="","",(X43*25)/AD43) | AI43: =IF(B43="","",(Y43*25)/AD43) | AJ43: =IF(B43="","",(AA43*25)/AD43) | AK43: =IF(B43="","",(AB43*40)/AD43) | AL43: =IF(B43="","",(AC43*50)/AD43) | AM43: =IF(B43="","",B43) | AQ43: =IF(AN43="","",AN43/AO43) | AR43: =IF(AN43="","",(AD43/AN43)/1000) | AS43: =IF(AN43="","",AR43*24) | AT43: =IF(AN43="","",(AD43/1000)*100%/AS43) | AU43: =IF(AN43="","",(AE43/AN43)) | AV43: =IF(AN43="","",(AD43/AO43)/1000)
A44: Kamut | AD44: =Z44*25 -> 0 | AE44: =IF(B44="","",C44+E44+G44+K44+N44+O44+Q44+R44+((D44+H44)/4)+((F44+I44+J44+T44)/2)) | AF44: =IF(B44="","",((AE44*50)/AD44)) | AG44: =IF(B44="","",((Z44)*25)/AD44) | AH44: =IF(B44="","",(X44*25)/AD44) | AI44: =IF(B44="","",(Y44*25)/AD44) | AJ44: =IF(B44="","",(AA44*25)/AD44) | AK44: =IF(B44="","",(AB44*40)/AD44) | AL44: =IF(B44="","",(AC44*50)/AD44) | AM44: =IF(B44="","",B44) | AQ44: =IF(AN44="","",AN44/AO44) | AR44: =IF(AN44="","",(AD44/AN44)/1000) | AS44: =IF(AN44="","",AR44*24) | AT44: =IF(AN44="","",(AD44/1000)*100%/AS44) | AU44: =IF(AN44="","",(AE44/AN44)) | AV44: =IF(AN44="","",(AD44/AO44)/1000)
A45: Trigo entero | AD45: =(Z45+AA45)*25.275 -> 0 | AE45: =IF(B45="","",C45+E45+G45+K45+N45+O45+Q45+R45+((D45+H45)/4)+((F45+I45+J45+T45)/2)) | AF45: =IF(B45="","",((AE45*50)/AD45)) | AG45: =IF(B45="","",((Z45)*25)/AD45) | AH45: =IF(B45="","",(X45*25)/AD45) | AI45: =IF(B45="","",(Y45*25)/AD45) | AJ45: =IF(B45="","",(AA45*25)/AD45) | AK45: =IF(B45="","",(AB45*40)/AD45) | AL45: =IF(B45="","",(AC45*50)/AD45) | AM45: =IF(B45="","",B45) | AQ45: =IF(AN45="","",AN45/AO45) | AR45: =IF(AN45="","",(AD45/AN45)/1000) | AS45: =IF(AN45="","",AR45*24) | AT45: =IF(AN45="","",(AD45/1000)*100%/AS45) | AU45: =IF(AN45="","",(AE45/AN45)) | AV45: =IF(AN45="","",(AD45/AO45)/1000)
AD46: =SUM(AD42:AD45) -> 0 | AX46: =AX42/1000 -> 0
AD47: Total Kg.
I48: 3.6 | AD48: =AD46/1000 -> 0 | AE48: Total Tm.
A49: Produccion | C49: % rendimiento | F49: Energia | I49: ART | K49: PEDIDO PUERTO | N49: SAP | O49: Inicial | R49: CONSUMOS | V49: FINAL
A50: tm trigo: | B50: =AD40+AD48 -> 0 | F50: Precio Kw: | H50: =IF(G53="",0,G56/G53) -> 0 | I50: =IF(I53="",0,I56/I53) -> 0 | K50: 1899000 | M50: =IF($V$50="",0,K50/$V$55) -> 0.33486158 | N50: 1576000 | O50: 1892000 | Q50: =IF($V$50="",0,O50/$V$55) -> 0.33362723 | R50: =D80 -> CWRS | S50: =(B82*D82)+(B85*D85)+(B86*D86)+(B87*D87)+(B89*D89)+(B92*D92)+(B94*D94)+(B95*D95)+(B98*D98)+(B99*D99)+(B100*D100)+(B102*D102)+(B103*D103)+(B108*D108)+(B111*D111)+(B83*D83)+(B104*D104)+(B84*D84)+(B91*D91)+(B115*D115)+(B106*D106)+(B105*D105)+(B113*D113)+(B110*D110)+(B88*D88)+(B90*D90)+(B96*D96)+(B97*D97)+(B107*D107) -> 0 | U50: =IF($S$55=0,0,S50/$S$55) -> 0 | V50: =K50+O50-S50 -> 3791000 | X50: =IF($V$50="",0,V50/$V$55) -> 0.6684888
A51: Blt harina: | B51: =AE36 -> 0 | C51: =B50/(B60*120) -> 0 | F51: Kw/tm trigo: | H51: =IF(G53="",0,G53/B50) -> 0 | K51: 800000 | M51: =IF($V$51="",0,K51/$V$55) -> 0.14106859 | N51: 181000 | O51: 180000 | Q51: =IF($V$51="",0,O51/$V$55) -> 0.031740434 | R51: =IF(E80="","",E80) -> CPS | S51: =(B82*E82)+(B85*E85)+(B86*E86)+(B87*E87)+(B89*E89)+(B92*E92)+(B94*E94)+(B95*E95)+(B98*E98)+(B99*E99)+(B100*E100)+(B102*E102)+(B103*E103)+(B108*E108)+(B113*E113)+(B105*E105)+(B111*E111)+(B104*E104)+(B83*E83)+(B84*E84)+(B91*E91)+(B106*E106)+(B115*E115)+(B116*E116)+(B110*E110)+(B101*E101)+(B88*E88)+(B90*E90)+(B97*E97)+(B107*E107+B96*E96) -> 0 | U51: =IF($S$55=0,0,S51/$S$55) -> 0 | V51: =K51+O51-S51 -> 980000 | X51: =IF($V$51="",0,V51/$V$55) -> 0.17280903
A52: Tm harina: | B52: =(B51*50)/1000 -> 0 | F52: Kw/tm harina: | H52: =IF(G53="",0,G53/((B51*50)/1000)) -> 0 | K52: 0 | M52: =IF($V$50="",0,K52/$V$55) -> 0 | N52: 254000 | O52: 450000 | Q52: =IF($V$50="",0,O52/$V$55) -> 0.079351084 | R52: HRW | S52: =(B82*G82)+(B85*G85)+(B86*G86)+(B87*G87)+(B89*G89)+(B92*G92)+(B94*G94)+(B95*G95)+(B98*G98)+(B99*G99)+(B100*G100)+(B102*G102)+(B103*G103)+(B108*G108)+(B113*G113)+(B109*G109)+(B116*G116)+(B114*G114)+(B115*G115)+(B83*G83)+(B84*G84)+(B104*G104)+(B106*G106)+(B96*G96)+(B97*G97)+(B90*G90)+(B88*G88)+(B105*G105)+(B91*G91)+(B110*G110) -> 0 | U52: =IF($S$55=0,0,S52/$S$55) -> 0 | V52: =K52+O52-S52 -> 450000 | X52: =IF($V$50="",0,V52/$V$55) -> 0.079351084
A53: Extraccion: | B53: =IF(AF36="",0,AF36) -> 0 | F53: KW: | K53: 0 | M53: =IF($V$50="",0,L53/$V$55) -> 0 | N53: 702000 | O53: 450000 | Q53: =IF($V$50="",0,O53/$V$55) -> 0.079351084 | R53: SRW | S53: =(B82*F82)+(B85*F85)+(B86*F86)+(B87*F87)+(B89*F89)+(B92*F92)+(B94*F94)+(B95*F95)+(B98*F98)+(B99*F99)+(B100*F100)+(B102*F102)+(B103*F103)+(B108*F108)+(B113*F113)+(B115*F115)+(B111*F111)+(B109*F109)+(B105*F105)+(B116*F116)+(B101*F101)+(B88*F88)+(B90*F90)+(B91*F91)+(B106*F106)+(B107*F107)+(B96*F96) -> 0 | U53: =IF($S$55=0,0,S53/$S$55) -> 0 | V53: =L53+O53-S53 -> 450000 | X53: =IF($V$50="",0,V53/$V$55) -> 0.079351084
A54: Hrs molienda: | B54: =AN36 -> 0 | F54: KVAR: | K54: 0 | M54: =IF($V$50="",0,L54/$V$55) -> 0 | N54: 0 | O54: 0 | Q54: =IF($V$50="",0,O54/$V$55) -> 0 | R54: BIO | S54: =IF(AD43="",0,AD43) -> 0 | U54: =IF($S$55=0,0,S54/$S$55) -> 0 | V54: =L54+O54-S54 -> 0 | X54: =IF($V$50="",0,V54/$V$55) -> 0
A55: Hrs varada: | B55: =IF(B50=0,0,AP36/AN36) -> 0 | F55: Reactiva: | K55: =SUM(K50:K54) -> 2699000 | N55: =SUM(N50:N54) -> 2713000 | O55: =SUM(O50:O54) -> 2972000 | S55: =SUM(S50:S54) -> 0 | V55: =SUM(V50:V54) -> 5671000
A56: % dia utilizado: | B56: =AT37 | F56: Precio: | G56: 77284230 | I56: 2803509
A57: Capacidad utilizada: | B57: =+AT36 | F57: Hz neumatico: | K57: Basculas
A58: Capacidad: | B58: =IF(AS36="",0,AS36) -> 0 | K58: Tm Trigo T1: | M58: =AX36 -> 0 | O58: tm
A59: Bultos hora: | B59: =IF(AU36="",0,AU36) -> 0 | F59: Granza: | H59: kg. | K59: Bascula Harina: | M59: =AY36 -> 0 | O59: tm
A60: Dias molienda: | B60: =31-COUNTBLANK(A4:A35) -> -1 | F60: % | G60: =G59/(B50*1000) -> #DIV/0! | K60: Extraccion: | M60: =M59/M58 -> #DIV/0! | T60: MYCE | Y60: AA | Z60: ADA | AA60: 900 | AB60: Alfa | AC60: 7200 | AD60: 4200 | AE60: 8530
A61: Total Ton de trig: | B61: =AD40+AD48 -> 0 | G61: grf | T61: TRIGO | X61: =C82 -> Extrapan 50
A62: Ton. molidas/persona: | B62: =B50/B67 -> 0 | F62: Energia M.martillo | K62: Energia C.granel | T62: AGUA m3 | U62: =AZ4 -> 0 | X62: =C85 -> Extrapan 25
A63: Valor tonelada/nomina: | B63: =B75/B50 -> #DIV/0! | F63: Ton Molidas | K63: Ton despachadas | O63: 662 | X63: =C86 -> Extrapan 10
A64: Valor ton/Horas extras: | B64: =B76/B50 -> #DIV/0! | F64: Tiempo de cargue | H64: =(H63*1)*2 -> 0 | K64: Tiempo de cargue | O64: =O63/30 -> 22.066667 | T64: Flowbalancer | X64: =C87 -> Artesanal 50
F65: TRIGO | K65: HARINA | T65: CRWS | X65: =C89 -> Artesanal 25
A66: Datos Generales | F66: HRW | K66: SRW | T66: CPS / HRW | X66: =C92 -> Natural 50
A67: Personal de planta | B67: 24 | F67: AMP | H67: =H64*G67 -> 0 | K67: AMP | L67: 100 | M67: =(O64*L67) -> 2206.6667 | T67: SRW | X67: =C99 -> Harina Tortas y Ponques
A68: Cuota de ventas | B68: 28760 | F68: KW/H | G68: =(G67*436*1.7321*0.96)/1000 -> 0 | H68: =(H67*436*1.7321*0.96)/1000 -> 0 | K68: KW/H | L68: =(L67*436*1.7321*0.96)/1000 -> 72.498778 | T68: OTROS | X68: =C100 -> Harina Galeras Ligera
A69: Ventas reales | B69: 36087 | F69: KW Total | G69: =G68*H63 -> 0 | K69: KW Total | M69: =L68*O64 -> 1599.8064 | X69: =C103 -> Harina de alta proteina x 1 G
A70: % de cumplimiento Proy | B70: =+B51/B68 -> 0 | F70: Precio Kw: | H70: =G69*H50 -> 0 | K70: Precio Kw: | M70: =M69*H50 -> 0 | T70: VALOR X HORA DE VARADA | X70: Total
A71: % de cumplimiento Real | B71: =+B51/B69 -> 0 | T71: Mob | V71: =AP36*(U71+U72) -> 0 | X71: Fisico
T72: Cif
A74: Datos Nomina Producción | Y74: Vitamina | Z74: COP | AA74: EXP
A75: Nomina | B75: 64062235 | Y75: gr/blt | Z75: 12.5 | AA75: 13.5 | AC75: gr/blt
A76: Horas extras | B76: 7837432 | Y76: Total | Z76: =SUM(A82+A85+A86+A87+A89+A92+A94+A98+A100+A102+A103+A108+A105+A110+A113+A115+A109+A83+A84+A90+A88+A91+A96+A97+A104+A106+A111)*Z75 -> 0 | AA76: =(A95+A99)*AA75 -> 0 | AC76: gr.
Y77: Fisico | AC77: gr.
D80: CWRS | E80: CPS | F80: SRW | G80: HRW
A81: Harina | B81: trigo | C81: Codigo | D81: % | E81: % | F81: % | G81: %
A82: =C36 -> 0 | B82: =IF(A82=0,0,((A82*50)/$B$53)) -> 0 | C82: Extrapan 50 | D82: 0.8 | E82: 0.2
A83: =C38 -> 0 | B83: =IF(A83=0,0,((A83*50)/$B$53)) -> 0 | C83: Extrapan 50
A84: =C39 -> 0 | B84: =IF(A84=0,0,((A84*50)/$B$53)) -> 0 | C84: Extrapan 50 | D84: 0.8 | E84: 0.2
A85: =D36/2 -> 0 | B85: =IF(A85=0,0,((A85*50)/$B$53)) -> 0 | C85: =D3 -> Extrapan 25 | D85: 0.8 | E85: 0.2
A86: =E36/5 -> 0 | B86: =IF(A86=0,0,((A86*50)/$B$53)) -> 0 | C86: =E3 -> Extrapan 10 | D86: 0.8 | E86: 0.2
A87: =F36 -> 0 | B87: =IF(A87=0,0,((A87*50)/$B$53)) -> 0 | C87: =F3 -> Artesanal 50 | D87: 0.6 | E87: 0.15 | F87: 0.25
A88: =F38 -> 0 | B88: =IF(A88=0,0,((A88*50)/$B$53)) -> 0 | C88: =C87 -> Artesanal 50
A89: =G36/2 -> 0 | B89: =IF(A89=0,0,((A89*50)/$B$53)) -> 0 | C89: =G3 -> Artesanal 25 | D89: 0.6 | E89: 0.15 | F89: 0.25
A90: =G38/2 -> 0 | B90: =IF(A90=0,0,((A90*50)/$B$53)) -> 0 | C90: =C89 -> Artesanal 25
A91: =H36 -> 0 | B91: =IF(A91=0,0,((A91*50)/$B$53)) -> 0 | C91: =H3 -> Natural 50 | D91: 0.7 | E91: 0.07 | F91: 0.23
A92: =H38 -> 0 | B92: =IF(A92=0,0,((A92*50)/$B$53)) -> 0 | C92: =H3 -> Natural 50
B93: =IF(A93=0,0,((A93*50)/$B$53)) -> 0
A94: =I36/2 -> 0 | B94: =IF(A94=0,0,((A94*50)/$B$53)) -> 0 | C94: =I3 -> Fuerte 25 | D94: 0.57 | E94: 0.13 | F94: 0.3
A95: =J36/2 -> 0 | B95: =IF(A95=0,0,((A95*50)/$B$53)) -> 0 | C95: =J3 -> Fuerte exp 25 | D95: 0.57 | E95: 0.13 | F95: 0.3
A96: =I38/2 -> 0 | B96: =IF(A96=0,0,((A96*50)/$B$53)) -> 0 | C96: =I3 -> Fuerte 25
A97: =I39/2 -> 0 | B97: =IF(A97=0,0,((A97*50)/$B$53)) -> 0 | C97: =C96 -> Fuerte 25
A98: =K36 -> 0 | B98: =IF(A98=0,0,((A98*50)/$B$53)) -> 0 | C98: =K3 -> Exclusiva 50 | D98: 0.62 | E98: 0.13 | F98: 0.25
A99: =N36 -> 0 | B99: =IF(A99=0,0,((A99*50)/$B$53)) -> 0 | C99: =N3 -> Harina Tortas y Ponques
A100: =O36 -> 0 | B100: =IF(A100=0,0,((A100*50)/$B$53)) -> 0 | C100: =O3 -> Harina Galeras Ligera
A101: =O38 -> 0 | B101: =IF(A101=0,0,((A101*50)/$B$53)) -> 0 | C101: =C100 -> Harina Galeras Ligera
A102: =Q36 -> 0 | B102: =IF(A102=0,0,((A102*50)/$B$53)) -> 0 | C102: =Q3 -> ESPECIAL 50
A103: =R36/50 -> 0 | B103: =IF(A103=0,0,((A103*50)/$B$53)) -> 0 | C103: =R3 -> Harina de alta proteina x 1 G | D103: 1
A104: =R38/50 -> 0 | B104: =IF(A104=0,0,((A104*50)/$B$53)) -> 0 | C104: T1G
...

Sheet MAY
B1: Producción | AH1: Extracción | AN1: Indicadores
B2: HARINA EN BULTO | R2: HARINA GRANEL | U2: P. EXP | V2: REPASO | X2: ESPECIAL | AA2: SUBPRODUCTO | AF2: EXTRACION | AN2: HORAS | AQ2: INDICACORES MOLINO | AV2: MOJADORA | AW2: EQUIPOS ELECTRONICOS
A3: Dia | B3: Fecha | C3: Extrapan 50 | D3: Extrapan 25 | E3: Extrapan 10 | F3: Artesanal 50 | G3: Artesanal 25 | H3: Natural 50 | I3: Fuerte 25 | J3: Fuerte exp 25 | K3: Exclusiva 50 | L3: Exclusiva 25 | M3: S. Sal 25 | N3: Harina Tortas y Ponques | O3: Harina Galeras Ligera | P3: H. Manitova | Q3: ESPECIAL 50 | R3: Harina de alta proteina x 1 G | S3: Harina de baja proteina x 1 | T3: ARTESANAL X 1 G | U3: H. espcial x 25 | V3: + Repaso | W3: - Reproceso | X3: Germen 25 | Y3: Semola 25 | Z3: Grano entero 25 | AA3: Salvado 25 | AB3: Mogolla 40 | AC3: Segunda 50 | AD3: Total trigo | AE3: Total Bultos | AF3: Harina | AG3: Grano entero partido | AH3: =X3 -> Germen 25 | AI3: Semola | AJ3: =AA3 -> Salvado 25 | AK3: =AB3 -> Mogolla 40 | AL3: =AC3 -> Segunda 50 | AM3: =B3 -> Fecha | AN3: Molienda | AO3: moje | AP3: Horas varada | AQ3: Molido/ Mojado | AR3: Capacidad TM. hora | AS3: Capacidad TM. Día | AT3: % Utilizado | AU3: Bultos Hora | AV3: capacidad TM. hora | AW3: MYFC | AX3: Bascula Trigo | AY3: Bascula Harina | AZ3: Agua M³ | BA3: Bascula Mejorante A | BB3: Bascula Mejorante B | BC3: Flowbalacer 1 | BD3: Flowbalacer 2 | BE3: Flowbalacer 3 | BF3: Flowbalacer 4
A4: =IF(B4="","",1) | AD4: =IF(B4="","",(((C4+F4+H4+K4+Q4+N4+O4)*50))+((E4*10))+(((I4+J4+D4+G4+L4+M4+U4)*25)+(X4*25)+(Y4*25)+(Z4*25)+(AA4*25)+(AB4*40)+(AC4*50)+(R4*1)+(S4*1)+(T4*1))) | AE4: =IF(B4="","",C4+F4+H4+K4+Q4+N4+O4+((I4+J4+D4+G4)/2)+(R4/50)+(S4/50)+(T4/50)+(U4/2)+(E4/5)) | AF4: =IF(B4="","",((AE4*50)/AD4)) | AG4: =IF(C4="","",((Z4)*25)/AD4) | AH4: =IF(B4="","",(X4*25)/AD4) | AI4: =IF(B4="","",(Y4*25)/AD4) | AJ4: =IF(B4="","",(AA4*25)/AD4) | AK4: =IF(B4="","",(AB4*40)/AD4) | AL4: =IF(B4="","",(AC4*50)/AD4) | AM4: =IF(B4="","",B4) | AQ4: =IF(AN4="","",AN4/AO4) | AR4: =IF(AN4="","",(AD4/AN4)/1000) | AS4: =IF(AN4="","",AR4*24) | AT4: =IF(AN4="","",(AD4/1000)*100%/AS4) | AU4: =IF(AN4="","",(AE4/AN4)) | AV4: =IF(AN4="","",(AD4/AO4)/1000)
A5: =IF(B5="","",2) | AD5: =IF(B5="","",(((C5+F5+H5+K5+Q5+N5+O5)*50))+((E5*10))+(((I5+J5+D5+G5+L5+M5+U5)*25)+(X5*25)+(Y5*25)+(Z5*25)+(AA5*25)+(AB5*40)+(AC5*50)+(R5*1)+(S5*1)+(T5*1))) | AE5: =IF(B5="","",C5+F5+H5+K5+Q5+N5+O5+((I5+J5+D5+G5+U5)/2)+(R5/50)+(S5/50)+(T5/50)+(E5/5)) | AF5: =IF(B5="","",((AE5*50)/AD5)) | AG5: =IF(C5="","",((Z5)*25)/AD5) | AH5: =IF(B5="","",(X5*25)/AD5) | AI5: =IF(B5="","",(Y5*25)/AD5) | AJ5: =IF(B5="","",(AA5*25)/AD5) | AK5: =IF(B5="","",(AB5*40)/AD5) | AL5: =IF(B5="","",(AC5*50)/AD5) | AM5: =IF(B5="","",B5) | AQ5: =IF(AN5="","",AN5/AO5) | AR5: =IF(AN5="","",(AD5/AN5)/1000) | AS5: =IF(AN5="","",AR5*24) | AT5: =IF(AN5="","",(AD5/1000)*100%/AS5) | AU5: =IF(AN5="","",(AE5/AN5)) | AV5: =IF(AN5="","",(AD5/AO5)/1000)
A6: =IF(B6="","",3) | AD6: =IF(B6="","",(((C6+F6+H6+K6+Q6+N6+O6)*50))+((E6*10))+(((I6+J6+D6+G6+L6+M6+U6)*25)+(X6*25)+(Y6*25)+(Z6*25)+(AA6*25)+(AB6*40)+(AC6*50)+(R6*1)+(S6*1)+(T6*1))) | AE6: =IF(B6="","",C6+F6+H6+K6+Q6+N6+O6+((I6+J6+D6+G6+U6)/2)+(R6/50)+(S6/50)+(T6/50)+(E6/5)) | AF6: =IF(B6="","",((AE6*50)/AD6)) | AG6: =IF(C6="","",((Z6)*25)/AD6) | AH6: =IF(B6="","",(X6*25)/AD6) | AI6: =IF(B6="","",(Y6*25)/AD6) | AJ6: =IF(B6="","",(AA6*25)/AD6) | AK6: =IF(B6="","",(AB6*40)/AD6) | AL6: =IF(B6="","",(AC6*50)/AD6) | AM6: =IF(B6="","",B6) | AQ6: =IF(AN6="","",AN6/AO6) | AR6: =IF(AN6="","",(AD6/AN6)/1000) | AS6: =IF(AN6="","",AR6*24) | AT6: =IF(AN6="","",(AD6/1000)*100%/AS6) | AU6: =IF(AN6="","",(AE6/AN6)) | AV6: =IF(AN6="","",(AD6/AO6)/1000)
A7: =IF(B7="","",4) | AD7: =IF(B7="","",(((C7+F7+H7+K7+Q7+N7+O7)*50))+((E7*10))+(((I7+J7+D7+G7+L7+M7+U7)*25)+(X7*25)+(Y7*25)+(Z7*25)+(AA7*25)+(AB7*40)+(AC7*50)+(R7*1)+(S7*1)+(T7*1))) | AE7: =IF(B7="","",C7+F7+H7+K7+Q7+N7+O7+((I7+J7+D7+G7+U7)/2)+(R7/50)+(S7/50)+(T7/50)+(E7/5)) | AF7: =IF(B7="","",((AE7*50)/AD7)) | AG7: =IF(C7="","",((Z7)*25)/AD7) | AH7: =IF(B7="","",(X7*25)/AD7) | AI7: =IF(B7="","",(Y7*25)/AD7) | AJ7: =IF(B7="","",(AA7*25)/AD7) | AK7: =IF(B7="","",(AB7*40)/AD7) | AL7: =IF(B7="","",(AC7*50)/AD7) | AM7: =IF(B7="","",B7) | AQ7: =IF(AN7="","",AN7/AO7) | AR7: =IF(AN7="","",(AD7/AN7)/1000) | AS7: =IF(AN7="","",AR7*24) | AT7: =IF(AN7="","",(AD7/1000)*100%/AS7) | AU7: =IF(AN7="","",(AE7/AN7)) | AV7: =IF(AN7="","",(AD7/AO7)/1000)
A8: =IF(B8="","",5) | AD8: =IF(B8="","",(((C8+F8+H8+K8+Q8+N8+O8)*50))+((E8*10))+(((I8+J8+D8+G8+L8+M8+U8)*25)+(X8*25)+(Y8*25)+(Z8*25)+(AA8*25)+(AB8*40)+(AC8*50)+(R8*1)+(S8*1)+(T8*1))) | AE8: =IF(B8="","",C8+F8+H8+K8+Q8+N8+O8+((I8+J8+D8+G8+U8)/2)+(R8/50)+(S8/50)+(T8/50)+(E8/5)) | AF8: =IF(B8="","",((AE8*50)/AD8)) | AG8: =IF(C8="","",((Z8)*25)/AD8) | AH8: =IF(B8="","",(X8*25)/AD8) | AI8: =IF(B8="","",(Y8*25)/AD8) | AJ8: =IF(B8="","",(AA8*25)/AD8) | AK8: =IF(B8="","",(AB8*40)/AD8) | AL8: =IF(B8="","",(AC8*50)/AD8) | AM8: =IF(B8="","",B8) | AQ8: =IF(AN8="","",AN8/AO8) | AR8: =IF(AN8="","",(AD8/AN8)/1000) | AS8: =IF(AN8="","",AR8*24) | AT8: =IF(AN8="","",(AD8/1000)*100%/AS8) | AU8: =IF(AN8="","",(AE8/AN8)) | AV8: =IF(AN8="","",(AD8/AO8)/1000)
A9: =IF(B9="","",6) | AD9: =IF(B9="","",(((C9+F9+H9+K9+Q9+N9+O9)*50))+((E9*10))+(((I9+J9+D9+G9+L9+M9+U9)*25)+(X9*25)+(Y9*25)+(Z9*25)+(AA9*25)+(AB9*40)+(AC9*50)+(R9*1)+(S9*1)+(T9*1))) | AE9: =IF(B9="","",C9+F9+H9+K9+Q9+N9+O9+((I9+J9+D9+G9+U9)/2)+(R9/50)+(S9/50)+(T9/50)+(E9/5)) | AF9: =IF(B9="","",((AE9*50)/AD9)) | AG9: =IF(C9="","",((Z9)*25)/AD9) | AH9: =IF(B9="","",(X9*25)/AD9) | AI9: =IF(B9="","",(Y9*25)/AD9) | AJ9: =IF(B9="","",(AA9*25)/AD9) | AK9: =IF(B9="","",(AB9*40)/AD9) | AL9: =IF(B9="","",(AC9*50)/AD9) | AM9: =IF(B9="","",B9) | AQ9: =IF(AN9="","",AN9/AO9) | AR9: =IF(AN9="","",(AD9/AN9)/1000) | AS9: =IF(AN9="","",AR9*24) | AT9: =IF(AN9="","",(AD9/1000)*100%/AS9) | AU9: =IF(AN9="","",(AE9/AN9)) | AV9: =IF(AN9="","",(AD9/AO9)/1000)
A10: =IF(B10="","",7) | AD10: =IF(B10="","",(((C10+F10+H10+K10+Q10+N10+O10)*50))+((E10*10))+(((I10+J10+D10+G10+L10+M10+U10)*25)+(X10*25)+(Y10*25)+(Z10*25)+(AA10*25)+(AB10*40)+(AC10*50)+(R10*1)+(S10*1)+(T10*1))) | AE10: =IF(B10="","",C10+F10+H10+K10+Q10+N10+O10+((I10+J10+D10+G10+U10)/2)+(R10/50)+(S10/50)+(T10/50)+(E10/5)) | AF10: =IF(B10="","",((AE10*50)/AD10)) | AG10: =IF(C10="","",((Z10)*25)/AD10) | AH10: =IF(B10="","",(X10*25)/AD10) | AI10: =IF(B10="","",(Y10*25)/AD10) | AJ10: =IF(B10="","",(AA10*25)/AD10) | AK10: =IF(B10="","",(AB10*40)/AD10) | AL10: =IF(B10="","",(AC10*50)/AD10) | AM10: =IF(B10="","",B10) | AQ10: =IF(AN10="","",AN10/AO10) | AR10: =IF(AN10="","",(AD10/AN10)/1000) | AS10: =IF(AN10="","",AR10*24) | AT10: =IF(AN10="","",(AD10/1000)*100%/AS10) | AU10: =IF(AN10="","",(AE10/AN10)) | AV10: =IF(AN10="","",(AD10/AO10)/1000)
A11: =IF(B11="","",8) | AD11: =IF(B11="","",(((C11+F11+H11+K11+Q11+N11+O11)*50))+((E11*10))+(((I11+J11+D11+G11+L11+M11+U11)*25)+(X11*25)+(Y11*25)+(Z11*25)+(AA11*25)+(AB11*40)+(AC11*50)+(R11*1)+(S11*1)+(T11*1))) | AE11: =IF(B11="","",C11+F11+H11+K11+Q11+N11+O11+((I11+J11+D11+G11+U11+P11)/2)+(R11/50)+(S11/50)+(T11/50)+(E11/5)) | AF11: =IF(B11="","",((AE11*50)/AD11)) | AG11: =IF(C11="","",((Z11)*25)/AD11) | AH11: =IF(B11="","",(X11*25)/AD11) | AI11: =IF(B11="","",(Y11*25)/AD11) | AJ11: =IF(B11="","",(AA11*25)/AD11) | AK11: =IF(B11="","",(AB11*40)/AD11) | AL11: =IF(B11="","",(AC11*50)/AD11) | AM11: =IF(B11="","",B11) | AQ11: =IF(AN11="","",AN11/AO11) | AR11: =IF(AN11="","",(AD11/AN11)/1000) | AS11: =IF(AN11="","",AR11*24) | AT11: =IF(AN11="","",(AD11/1000)*100%/AS11) | AU11: =IF(AN11="","",(AE11/AN11)) | AV11: =IF(AN11="","",(AD11/AO11)/1000)
